Workbook

Sheet START HERE
A1: WORKLOAD & PROFIT PLAN - START HERE
A2: Click any sheet name to jump straight to it. Blue-text cells anywhere in this workbook are inputs you can change; green text is pulled from another sheet; black is calculated.
A4: 1 - WHERE YOU ENTER DATA | B4: What you put there | C4: How often
A5: TS Ahmed | B5: Paste Ahmed's monthly timesheet export into cell A4 | C5: Monthly
A6: TS Osama | B6: Paste Osama's monthly timesheet export into cell A4 | C6: Monthly
A7: TS Kirolos | B7: Paste Kirolos's monthly timesheet export into cell A4 | C7: Monthly
A8: Deliverables | B8: Progress: step reached, credit %, status date, engineer % split | C8: Monthly
A9: Deliverable Actuals | B9: Real milestone dates - submitted, comments received, resubmitted, completed (blue block W:AB) | C9: Monthly
A10: Support Plan | B10: Bengaluru and draftsman support: planned, delivered, office shift date and reason | C10: When resourcing changes
A11: Profit Plan | B11: Expected hours to finish each deliverable (column K) and the planning assumptions at the top | C11: When re-planning
A12: Phasing | B12: Planned MM overrides only (the block from row 93). Actual MM is now calculated from the timesheet - do not type in it. | C12: Rarely
A13: Inputs | B13: Project master data: budget MM, start and end dates, team availability | C13: When a project is added
A14: Work Calendar | B14: Working week, public holidays, engineer name patterns, hours per day | C14: Rarely
A16: 2 - WHERE YOU READ THE OUTPUT | B16: What it answers
A17: Delivery Sequence | B17: In what order should we deliver, and where does the year-end profit land?
A18: Profit Plan | B18: What does the rest of the year look like, and is the plan credible?
A19: Dashboard | B19: Portfolio KPIs for any year or quarter: planned, actual, earned, CPI, utilisation
A20: Mgmt Review | B20: Team performance, plan adherence, and dependency on draftsmen and Bengaluru
A21: Timesheet Daily | B21: Who charged what on every date: project, proposal, absence, overtime, idle or leave
A22: Deliverable Actuals | B22: Real start and finish dates, dormant days, stoppages, activity spells
A23: Proposals | B23: Proposal effort by real proposal number and by year
A24: Engineer KPIs | B24: Per-engineer performance measures
A25: Scorecard | B25: Summary scoring view
A26: Team Member | B26: Individual workload detail
A27: Analysis | B27: Quarterly efficiency and profitability by project
A28: Timesheet Raw | B28: Consolidated timesheet - read only, builds itself from the three TS sheets
A30: 3 - HOW THE WORKBOOK FLOWS
A31: The three TS sheets feed Timesheet Raw, which feeds Timesheet Daily (day-by-day) and Deliverable Actuals (deliverable-by-deliverable).
A32: Deliverable Actuals plus the Deliverables register feed the Profit Plan, which ranks the remaining work and produces the Delivery Sequence.
A33: Support Plan feeds the dependency section of Mgmt Review. Proposals feeds the proposal rows of the register.
A34: Inputs and Phasing feed Analysis, which feeds the Dashboard. Phasing actual MM is now calculated from the timesheet, so the Dashboard and Analysis move as soon as you paste.
A36: 4 - MONTHLY ROUTINE
A37: Step 1. Paste each engineer's export into TS Ahmed, TS Osama and TS Kirolos (cell A4, after deleting the old rows).
A38: Step 2. Open Work Calendar and check the DATA CHECK block: row count, date range, and that no rows are unmatched.
A39: Step 3. Update progress on the Deliverables register and milestone dates on Deliverable Actuals.
A40: Step 4. Nothing to retype for actual MM - Phasing now reads it from the timesheet. Just check the Dashboard and Analysis have moved.
A41: Step 5. Read the result on Delivery Sequence, Profit Plan and Mgmt Review.
A43: 5 - TAB COLOUR GUIDE
A44: Tabs are ordered and coloured by role, left to right.
A45: Purple | B45: Guide and glossary | C45: START HERE, Definitions
A46: Blue | B46: Reports - read these | C46: Dashboard, Mgmt Review, Engineer KPIs, Team Member, Scorecard, Delivery Sequence
A47: Green | B47: Plan and enter data here | C47: Inputs, Deliverables, Profit Plan, Support Plan, Proposals, Phasing, Analysis
A48: Amber | B48: Reference tables - change rarely | C48: Project Types, Rules of Credit, Work Calendar
A49: Grey | B49: Engine and raw paste targets | C49: Deliverable Actuals, Timesheet Daily, Timesheet Raw, TS Ahmed / Osama / Kirolos

Sheet Definitions
A1: FIELD DEFINITIONS — HOW TO READ THE DASHBOARD
A2: ="All effort in Man-Months (MM). The Current column below is live and follows the Dashboard filter, showing: "&Dashboard!$H$5 -> All effort in Man-Months (MM). The Current column below is live and follows the Dashboard filter, showing: Full year 2026
A4: SECTION 1 — THE THREE CORE MEASURES (everything else is built from these)
A5: Field | B5: Where it appears | C5: What it actually means | D5: How it is calculated | E5: Current | F5: How to read it
A6: Planned MM | B6: Selected Period band | C6: The effort we SAID we would spend in this period. It comes from each project's budget spread across the months between its start and end date, so a 12 MM project running 2 years contributes 1.5 MM to each quarter. | D6: Straight-line spread of Budget across the project's start-to-end window, summed for every project touching the period. Overridable per project per quarter on the Phasing sheet. | E6: =Dashboard!$B$10 -> 44.829171 | F6: This is the yardstick, not an achievement. It answers: how much work was this period supposed to absorb?
A7: Actual MM | B7: Selected Period band | C7: The effort we REALLY spent in this period — the man-months your team actually booked against projects in those three months (or that year). | D7: Sum of the quarterly actuals grid on Phasing, for the quarters inside the selected period, across all projects and all three engineers. | E7: =Dashboard!$C$10 -> 17.908108 | F7: The only hard fact of the three. If this is blank, nobody logged time — the period is unmeasurable, not efficient.
A8: Earned MM | B8: Selected Period band | C8: The VALUE we delivered in this period, expressed in man-months of budget. If a project is 70% complete on a 26 MM budget, 18.2 MM of value has been earned regardless of how long it took. | D8: Budget x % Complete for each project, then spread across quarters in proportion to when the time was actually booked. | E8: =Dashboard!$D$10 -> 14.186137 | F8: This is what the client is effectively paying for. Compare it with Actual MM to see whether effort is converting into progress.
A10: SECTION 2 — PERIOD METRICS (flow: what happened inside the chosen window)
A11: Field | B11: Where it appears | C11: What it actually means | D11: How it is calculated | E11: Current | F11: How to read it
A12: Profit / (Loss) in period | B12: Selected Period band | C12: Value delivered less effort burned, in this period only. Positive means you got more budget-value out than man-months you put in. | D12: Earned MM less Actual MM. | E12: =Dashboard!$E$10 -> -3.7219708 | F12: A performance score for the period, NOT money in the bank. It says nothing about whether the project will finish in profit.
A13: Capacity MM | B13: Selected Period band | C13: How much the team could deliver in this period if fully applied to projects. | D13: Each person's availability % for that year x 3 months per quarter (x4 for a full year), summed across the team. | E13: =Dashboard!$F$10 -> 24.163043 | F13: The ceiling. Actual MM above this means overtime or the data is wrong; far below means the team was on other work.
A14: Utilisation | B14: Selected Period band | C14: How busy the team was: how much of the available capacity was actually booked to projects. | D14: Actual MM divided by Capacity MM. | E14: =Dashboard!$G$10 -> 0.74113628 | F14: Low utilisation usually means unlogged time or non-project work, not idleness. Check before drawing conclusions.
A15: Plan Adherence | B15: Selected Period band | C15: Did we burn the effort we said we would this period? | D15: Actual MM divided by Planned MM. | E15: =Dashboard!$H$10 -> 0.54727687 | F15: Below 100% means the plan assumed more effort than was spent — either you are behind, or the phasing dates need correcting.
A16: Efficiency (CPI) — in period | B16: Selected Period band | C16: Value delivered per man-month spent, IN THIS PERIOD ONLY. Above 1.00 means the period converted effort into progress well. | D16: Earned MM in period divided by Actual MM in period. | E16: =Dashboard!$I$10 -> 0.79216281 | F16: A snapshot of recent performance. Volatile — one quarter with little logged time can swing it wildly.
A19: SECTION 3 — READING EFFICIENCY CORRECTLY
A20: There is now one efficiency figure on the dashboard: Earned MM divided by Actual MM, for the period you selected. It answers a single question — did the effort spent in this window convert into delivered value? Above 1.00 is good. The traps below are the reason it sometimes looks wrong.
A21: What you see | C21: Why it happens | E21: What to do about it
A22: Reads n/a, or a dash | C22: No time was booked to any project in the period, so there is nothing to divide. | E22: Treat the period as unmeasured, not efficient. Check the actuals grid on Phasing for those quarters.
A23: Far above 1.00 (say over 2.00x) | C23: A project is marked well advanced on very little booked time, so earned value dwarfs actual effort. | E23: Almost always missing actuals or an overstated budget. Compare Actual to Date against Budget in Project Detail.
A24: Below 1.00 | C24: More effort has been spent than value delivered. This is a genuine overrun. | E24: Real signal. Look at Cost at Completion versus Budget per project in Project Detail to find which contract is causing it.
A25: Swings hard between quarters | C25: Period figures are volatile by nature — one quarter of light logging moves them a long way. | E25: Switch the filter to Year, or scan several quarters, before concluding anything about a trend.
A27: ="For the period currently selected ("&Dashboard!$H$5&") efficiency reads "&IF(Dashboard!$C$10=0,"n/a — no time booked",TEXT(Dashboard!$I$10,"0.00")&"x, from "&TEXT(Dashboard!$D$10,"0.00")&" MM of value delivered against "&TEXT(Dashboard!$C$10,"0.00")&" MM of effort booked.") -> For the period currently selected (Full year 2026) efficiency reads 0.79x, from 14.19 MM of value delivered against 17.91 MM of effort booked.
A31: SECTION 4 — BEFORE YOU TRUST ANY OF THESE NUMBERS
A32: 1. Efficiency is only as good as the logged time. A project marked 100% complete with almost no booked MM will show an impossibly high CPI and flatter the portfolio. Check Actual to Date against Budget on the Inputs sheet before believing a number above about 2.00x.
A33: 2. Planned MM depends entirely on the Start and End dates. If a date is wrong, that project's effort lands in the wrong quarters and Plan Adherence becomes meaningless.
A34: 3. % Complete drives Earned MM and Forecast at Completion. It is a judgement you type in — if it is stale, both the efficiency and the forecast loss are stale too.
A35: 4. Effort booked before quarterly tracking began sits in the Opening column on Phasing. It counts toward a project's total booked time but falls inside no quarter, so it never appears in any period figure.

Sheet Dashboard
A1: PROJECT PORTFOLIO DASHBOARD
A2: ="All effort in Man-Months (MM) | "&TEXT(Inputs!$M$86,"0")&" projects in scope of "&TEXT(COUNTA(Inputs!$A$6:$A$85),"0")&" | Team of "&TEXT(COUNTA(Inputs!$A$91:$A$93),"0")&" | Reported "&TEXT(TODAY(),"dd mmm yyyy") -> All effort in Man-Months (MM) | 9 projects in scope of 40 | Team of 3 | Reported 01 Sep 2026
A4: PERIOD FILTER — choose how you want to look at the portfolio
A5: View by: | B5: Year | C5: Year: | D5: 2026 | E5: Quarter: | F5: Q1 | G5: Showing: | H5: =IF($B$5="All Time","All periods, including opening balances",IF($B$5="Year","Full year "&TEXT($D$5,"0"),$F$5&" "&TEXT($D$5,"0")&" ("&TEXT($D$6,"dd mmm")&" to "&TEXT($F$6,"dd mmm yyyy")&")")) -> Full year 2026
A6: Resolved period → | B6: =$F$5&"-"&TEXT(MOD($D$5,100),"00") -> Q1-26 | C6: from | D6: =IF($B$5="All Time",DATE(1900,1,1),IF($B$5="Year",DATE($D$5,1,1),DATE($D$5,(VALUE(MID($F$5,2,1))-1)*3+1,1))) -> 46023 | E6: to | F6: =IF($B$5="All Time",DATE(2099,12,31),IF($B$5="Year",DATE($D$5,12,31),EOMONTH($D$6,2))) -> 46387 | G6: As at: | H6: =Inputs!$B$96 -> 46266 | I6: Elapsed: | J6: =IF(IF($B$5="All Time",Analysis!$Y$24,IF($B$5="Year",SUMIF(Analysis!$E$3:$X$3,$D$5,Analysis!$E$24:$X$24),SUMIF(Analysis!$E$4:$X$4,$B$6,Analysis!$E$24:$X$24)))=0,"",$F$10/(IF($B$5="All Time",Analysis!$Y$24,IF($B$5="Year",SUMIF(Analysis!$E$3:$X$3,$D$5,Analysis!$E$24:$X$24),SUMIF(Analysis!$E$4:$X$4,$B$6,Analysis!$E$24:$X$24))))) -> 0.67119565 | K6: Planned to date: | L6: =IF($B$5="All Time",Analysis!$Y$33,IF($B$5="Year",SUMIF(Analysis!$E$3:$X$3,$D$5,Analysis!$E$33:$X$33),SUMIF(Analysis!$E$4:$X$4,$B$6,Analysis!$E$33:$X$33))) -> 32.722209
A8: SELECTED PERIOD — PERFORMANCE IN THE PERIOD YOU CHOSE ABOVE
B9: Planned MM (full period) | C9: Actual MM | D9: Earned MM | E9: Profit / (Loss) | F9: Capacity to Date | G9: Utilisation | H9: Plan Adherence to Date | I9: Efficiency (CPI) | J9: Projects Active
B10: =IF($B$5="All Time",Analysis!$Y$17,IF($B$5="Year",SUMIF(Analysis!$E$3:$X$3,$D$5,Analysis!$E$17:$X$17),SUMIF(Analysis!$E$4:$X$4,$B$6,Analysis!$E$17:$X$17))) -> 44.829171 | C10: =IF($B$5="All Time",Analysis!$Y$18,IF($B$5="Year",SUMIF(Analysis!$E$3:$X$3,$D$5,Analysis!$E$18:$X$18),SUMIF(Analysis!$E$4:$X$4,$B$6,Analysis!$E$18:$X$18))) -> 17.908108 | D10: =IF($B$5="All Time",Analysis!$Y$19,IF($B$5="Year",SUMIF(Analysis!$E$3:$X$3,$D$5,Analysis!$E$19:$X$19),SUMIF(Analysis!$E$4:$X$4,$B$6,Analysis!$E$19:$X$19))) -> 14.186137 | E10: =D10-C10 -> -3.7219708 | F10: =IF($B$5="All Time",Analysis!$Y$32,IF($B$5="Year",SUMIF(Analysis!$E$3:$X$3,$D$5,Analysis!$E$32:$X$32),SUMIF(Analysis!$E$4:$X$4,$B$6,Analysis!$E$32:$X$32))) -> 24.163043 | G10: =IF(F10=0,"n/a",C10/F10) -> 0.74113628 | H10: =IF($L$6=0,"n/a",C10/$L$6) -> 0.54727687 | I10: =IF(C10=0,"n/a",D10/C10) -> 0.79216281 | J10: {=SUMPRODUCT((Inputs!$A$6:$A$85<>"")*(Inputs!$D$6:$D$85<=$F$6)*(Inputs!$E$6:$E$85>=$D$6))} -> 16
B11: ="full period plan" -> full period plan | C11: ="what we actually burned" -> what we actually burned | D11: ="value delivered" -> value delivered | E11: ="earned minus actual" -> earned minus actual | F11: ="pro-rated to "&TEXT($H$6,"dd mmm") -> pro-rated to 01 Sep | G11: ="actual vs capacity to date" -> actual vs capacity to date | H11: ="vs "&TEXT($L$6,"0.00")&" MM planned to date" -> vs 32.72 MM planned to date | I11: ="above 1.00 is good" -> above 1.00 is good | J11: ="live in this period" -> live in this period
A13: WHAT IS ACTUALLY BEING WORKED — PORTFOLIO BY STATUS
A14: Status | B14: Projects | C14: Budget | D14: Planned in Period | E14: Actual in Period | F14: Remaining on Hand | G14: Cost at Compl. | H14: Profit / (Loss) | I14: In Scope?
A15: Active | B15: {=SUMPRODUCT((Inputs!$F$6:$F$85=$A15)*$M$173:$M$252)} -> 6 | C15: {=SUMPRODUCT((Inputs!$F$6:$F$85=$A15)*$M$173:$M$252*$B$173:$B$252)} -> 35.55 | D15: {=SUMPRODUCT((Inputs!$F$6:$F$85=$A15)*$M$173:$M$252*$K$173:$K$252)} -> 28.315241 | E15: {=SUMPRODUCT((Inputs!$F$6:$F$85=$A15)*$M$173:$M$252*$L$173:$L$252)} -> 14.166216 | F15: {=SUMPRODUCT((Inputs!$F$6:$F$85=$A15)*$M$173:$M$252*$I$173:$I$252)} -> 48.568178 | G15: {=SUMPRODUCT((Inputs!$F$6:$F$85=$A15)*$M$173:$M$252*$H$173:$H$252)} -> 68.214124 | H15: {=SUMPRODUCT((Inputs!$F$6:$F$85=$A15)*$M$173:$M$252*$J$173:$J$252)} -> -32.664124 | I15: =IF(OR($A15="Active",$A15="Not Started"),"Yes","No") -> Yes
A16: Not Started | B16: {=SUMPRODUCT((Inputs!$F$6:$F$85=$A16)*$M$173:$M$252)} -> 1 | C16: {=SUMPRODUCT((Inputs!$F$6:$F$85=$A16)*$M$173:$M$252*$B$173:$B$252)} -> 5 | D16: {=SUMPRODUCT((Inputs!$F$6:$F$85=$A16)*$M$173:$M$252*$K$173:$K$252)} -> 1.2585499 | E16: {=SUMPRODUCT((Inputs!$F$6:$F$85=$A16)*$M$173:$M$252*$L$173:$L$252)} -> 0 | F16: {=SUMPRODUCT((Inputs!$F$6:$F$85=$A16)*$M$173:$M$252*$I$173:$I$252)} -> 5 | G16: {=SUMPRODUCT((Inputs!$F$6:$F$85=$A16)*$M$173:$M$252*$H$173:$H$252)} -> 5 | H16: {=SUMPRODUCT((Inputs!$F$6:$F$85=$A16)*$M$173:$M$252*$J$173:$J$252)} -> 0 | I16: =IF(OR($A16="Active",$A16="Not Started"),"Yes","No") -> Yes
A17: On Hold | B17: {=SUMPRODUCT((Inputs!$F$6:$F$85=$A17)*$M$173:$M$252)} -> 7 | C17: {=SUMPRODUCT((Inputs!$F$6:$F$85=$A17)*$M$173:$M$252*$B$173:$B$252)} -> 18.4 | D17: {=SUMPRODUCT((Inputs!$F$6:$F$85=$A17)*$M$173:$M$252*$K$173:$K$252)} -> 9.5972454 | E17: {=SUMPRODUCT((Inputs!$F$6:$F$85=$A17)*$M$173:$M$252*$L$173:$L$252)} -> 1.3540541 | F17: {=SUMPRODUCT((Inputs!$F$6:$F$85=$A17)*$M$173:$M$252*$I$173:$I$252)} -> 26.772302 | G17: {=SUMPRODUCT((Inputs!$F$6:$F$85=$A17)*$M$173:$M$252*$H$173:$H$252)} -> 35.793923 | H17: {=SUMPRODUCT((Inputs!$F$6:$F$85=$A17)*$M$173:$M$252*$J$173:$J$252)} -> -17.393923 | I17: =IF(OR($A17="Active",$A17="Not Started"),"Yes","No") -> No
A18: Finalized | B18: {=SUMPRODUCT((Inputs!$F$6:$F$85=$A18)*$M$173:$M$252)} -> 2 | C18: {=SUMPRODUCT((Inputs!$F$6:$F$85=$A18)*$M$173:$M$252*$B$173:$B$252)} -> 9 | D18: {=SUMPRODUCT((Inputs!$F$6:$F$85=$A18)*$M$173:$M$252*$K$173:$K$252)} -> 5.6581353 | E18: {=SUMPRODUCT((Inputs!$F$6:$F$85=$A18)*$M$173:$M$252*$L$173:$L$252)} -> 1.9472973 | F18: {=SUMPRODUCT((Inputs!$F$6:$F$85=$A18)*$M$173:$M$252*$I$173:$I$252)} -> 0 | G18: {=SUMPRODUCT((Inputs!$F$6:$F$85=$A18)*$M$173:$M$252*$H$173:$H$252)} -> 4.8905405 | H18: {=SUMPRODUCT((Inputs!$F$6:$F$85=$A18)*$M$173:$M$252*$J$173:$J$252)} -> 4.1094595 | I18: =IF(OR($A18="Active",$A18="Not Started"),"Yes","No") -> No
A19: Proposal | B19: {=SUMPRODUCT((Inputs!$F$6:$F$85=$A19)*$M$173:$M$252)} -> 0 | C19: {=SUMPRODUCT((Inputs!$F$6:$F$85=$A19)*$M$173:$M$252*$B$173:$B$252)} -> 0 | D19: {=SUMPRODUCT((Inputs!$F$6:$F$85=$A19)*$M$173:$M$252*$K$173:$K$252)} -> 0 | E19: {=SUMPRODUCT((Inputs!$F$6:$F$85=$A19)*$M$173:$M$252*$L$173:$L$252)} -> 0 | F19: {=SUMPRODUCT((Inputs!$F$6:$F$85=$A19)*$M$173:$M$252*$I$173:$I$252)} -> 0 | G19: {=SUMPRODUCT((Inputs!$F$6:$F$85=$A19)*$M$173:$M$252*$H$173:$H$252)} -> 0 | H19: {=SUMPRODUCT((Inputs!$F$6:$F$85=$A19)*$M$173:$M$252*$J$173:$J$252)} -> 0 | I19: =IF(OR($A19="Active",$A19="Not Started"),"Yes","No") -> No
A20: Cancelled | B20: {=SUMPRODUCT((Inputs!$F$6:$F$85=$A20)*$M$173:$M$252)} -> 0 | C20: {=SUMPRODUCT((Inputs!$F$6:$F$85=$A20)*$M$173:$M$252*$B$173:$B$252)} -> 0 | D20: {=SUMPRODUCT((Inputs!$F$6:$F$85=$A20)*$M$173:$M$252*$K$173:$K$252)} -> 0 | E20: {=SUMPRODUCT((Inputs!$F$6:$F$85=$A20)*$M$173:$M$252*$L$173:$L$252)} -> 0 | F20: {=SUMPRODUCT((Inputs!$F$6:$F$85=$A20)*$M$173:$M$252*$I$173:$I$252)} -> 0 | G20: {=SUMPRODUCT((Inputs!$F$6:$F$85=$A20)*$M$173:$M$252*$H$173:$H$252)} -> 0 | H20: {=SUMPRODUCT((Inputs!$F$6:$F$85=$A20)*$M$173:$M$252*$J$173:$J$252)} -> 0 | I20: =IF(OR($A20="Active",$A20="Not Started"),"Yes","No") -> No
A21: ALL LIVE IN PERIOD | B21: =SUM(B15:B20) -> 16 | C21: =SUM(C15:C20) -> 67.95 | D21: =SUM(D15:D20) -> 44.829171 | E21: =SUM(E15:E20) -> 17.467568 | F21: =SUM(F15:F20) -> 80.34048 | G21: =SUM(G15:G20) -> 113.89859 | H21: =SUM(H15:H20) -> -45.948588 | I21: =""
A22: IN DELIVERY SCOPE | B22: =SUM(B15:B16) -> 7 | C22: =SUM(C15:C16) -> 40.55 | D22: =SUM(D15:D16) -> 29.573791 | E22: =SUM(E15:E16) -> 14.166216 | F22: =SUM(F15:F16) -> 53.568178 | G22: =SUM(G15:G16) -> 73.214124 | H22: =SUM(H15:H16) -> -32.664124 | I22: =""
A24: PROJECT DETAIL — only projects live in the selected period
A25: Project | B25: Budget | C25: Start | D25: End | E25: Status | F25: % Compl. | G25: Actual to Date | H25: Cost at Compl. | I25: Remaining | J25: Profit / (Loss) | K25: Planned in Period | L25: Actual in Period | M25: % of Period Plan
A26: =IFERROR(INDEX($A$173:$A$252,MATCH(ROW()-25,$N$173:$N$252,0)),"") -> N25178-0100D | B26: =IF($A26="","",INDEX($B$173:$B$252,MATCH(ROW()-25,$N$173:$N$252,0))) -> 2.4 | C26: =IF($A26="","",INDEX($C$173:$C$252,MATCH(ROW()-25,$N$173:$N$252,0))) -> 46204 | D26: =IF($A26="","",INDEX($D$173:$D$252,MATCH(ROW()-25,$N$173:$N$252,0))) -> 46295 | E26: =IF($A26="","",INDEX($E$173:$E$252,MATCH(ROW()-25,$N$173:$N$252,0))) -> Active | F26: =IF($A26="","",INDEX($F$173:$F$252,MATCH(ROW()-25,$N$173:$N$252,0))) -> 0.65 | G26: =IF($A26="","",INDEX($G$173:$G$252,MATCH(ROW()-25,$N$173:$N$252,0))) -> 0 | H26: =IF($A26="","",INDEX($H$173:$H$252,MATCH(ROW()-25,$N$173:$N$252,0))) -> 2.4 | I26: =IF($A26="","",INDEX($I$173:$I$252,MATCH(ROW()-25,$N$173:$N$252,0))) -> 2.4 | J26: =IF($A26="","",INDEX($J$173:$J$252,MATCH(ROW()-25,$N$173:$N$252,0))) -> 0 | K26: =IF($A26="","",INDEX($K$173:$K$252,MATCH(ROW()-25,$N$173:$N$252,0))) -> 2.4 | L26: =IF($A26="","",INDEX($L$173:$L$252,MATCH(ROW()-25,$N$173:$N$252,0))) -> 0 | M26: =IF($A26="","",IF($K$106=0,"",$K26/$K$106)) -> 0.053536568
A27: =IFERROR(INDEX($A$173:$A$252,MATCH(ROW()-25,$N$173:$N$252,0)),"") -> E26084-0100D | B27: =IF($A27="","",INDEX($B$173:$B$252,MATCH(ROW()-25,$N$173:$N$252,0))) -> 3 | C27: =IF($A27="","",INDEX($C$173:$C$252,MATCH(ROW()-25,$N$173:$N$252,0))) -> 45839 | D27: =IF($A27="","",INDEX($D$173:$D$252,MATCH(ROW()-25,$N$173:$N$252,0))) -> 46295 | E27: =IF($A27="","",INDEX($E$173:$E$252,MATCH(ROW()-25,$N$173:$N$252,0))) -> Active | F27: =IF($A27="","",INDEX($F$173:$F$252,MATCH(ROW()-25,$N$173:$N$252,0))) -> 0.1625 | G27: =IF($A27="","",INDEX($G$173:$G$252,MATCH(ROW()-25,$N$173:$N$252,0))) -> 0.22567568 | H27: =IF($A27="","",INDEX($H$173:$H$252,MATCH(ROW()-25,$N$173:$N$252,0))) -> 1.3887734 | I27: =IF($A27="","",INDEX($I$173:$I$252,MATCH(ROW()-25,$N$173:$N$252,0))) -> 1.1630977 | J27: =IF($A27="","",INDEX($J$173:$J$252,MATCH(ROW()-25,$N$173:$N$252,0))) -> 1.6112266 | K27: =IF($A27="","",INDEX($K$173:$K$252,MATCH(ROW()-25,$N$173:$N$252,0))) -> 1.7921225 | L27: =IF($A27="","",INDEX($L$173:$L$252,MATCH(ROW()-25,$N$173:$N$252,0))) -> 0.22567568 | M27: =IF($A27="","",IF($K$106=0,"",$K27/$K$106)) -> 0.039976705
A28: =IFERROR(INDEX($A$173:$A$252,MATCH(ROW()-25,$N$173:$N$252,0)),"") -> N25185-0100D | B28: =IF($A28="","",INDEX($B$173:$B$252,MATCH(ROW()-25,$N$173:$N$252,0))) -> 26 | C28: =IF($A28="","",INDEX($C$173:$C$252,MATCH(ROW()-25,$N$173:$N$252,0))) -> 45931 | D28: =IF($A28="","",INDEX($D$173:$D$252,MATCH(ROW()-25,$N$173:$N$252,0))) -> 46387 | E28: =IF($A28="","",INDEX($E$173:$E$252,MATCH(ROW()-25,$N$173:$N$252,0))) -> Active | F28: =IF($A28="","",INDEX($F$173:$F$252,MATCH(ROW()-25,$N$173:$N$252,0))) -> 0.316 | G28: =IF($A28="","",INDEX($G$173:$G$252,MATCH(ROW()-25,$N$173:$N$252,0))) -> 18.516216 | H28: =IF($A28="","",INDEX($H$173:$H$252,MATCH(ROW()-25,$N$173:$N$252,0))) -> 58.595621 | I28: =IF($A28="","",INDEX($I$173:$I$252,MATCH(ROW()-25,$N$173:$N$252,0))) -> 40.079405 | J28: =IF($A28="","",INDEX($J$173:$J$252,MATCH(ROW()-25,$N$173:$N$252,0))) -> -32.595621 | K28: =IF($A28="","",INDEX($K$173:$K$252,MATCH(ROW()-25,$N$173:$N$252,0))) -> 20.765864 | L28: =IF($A28="","",INDEX($L$173:$L$252,MATCH(ROW()-25,$N$173:$N$252,0))) -> 13.517568 | M28: =IF($A28="","",IF($K$106=0,"",$K28/$K$106)) -> 0.46322213
A29: =IFERROR(INDEX($A$173:$A$252,MATCH(ROW()-25,$N$173:$N$252,0)),"") -> D26058-0100D | B29: =IF($A29="","",INDEX($B$173:$B$252,MATCH(ROW()-25,$N$173:$N$252,0))) -> 5 | C29: =IF($A29="","",INDEX($C$173:$C$252,MATCH(ROW()-25,$N$173:$N$252,0))) -> 46204 | D29: =IF($A29="","",INDEX($D$173:$D$252,MATCH(ROW()-25,$N$173:$N$252,0))) -> 46934 | E29: =IF($A29="","",INDEX($E$173:$E$252,MATCH(ROW()-25,$N$173:$N$252,0))) -> Not Started | F29: =IF($A29="","",INDEX($F$173:$F$252,MATCH(ROW()-25,$N$173:$N$252,0))) -> 0 | G29: =IF($A29="","",INDEX($G$173:$G$252,MATCH(ROW()-25,$N$173:$N$252,0))) -> 0 | H29: =IF($A29="","",INDEX($H$173:$H$252,MATCH(ROW()-25,$N$173:$N$252,0))) -> 5 | I29: =IF($A29="","",INDEX($I$173:$I$252,MATCH(ROW()-25,$N$173:$N$252,0))) -> 5 | J29: =IF($A29="","",INDEX($J$173:$J$252,MATCH(ROW()-25,$N$173:$N$252,0))) -> 0 | K29: =IF($A29="","",INDEX($K$173:$K$252,MATCH(ROW()-25,$N$173:$N$252,0))) -> 1.2585499 | L29: =IF($A29="","",INDEX($L$173:$L$252,MATCH(ROW()-25,$N$173:$N$252,0))) -> 0 | M29: =IF($A29="","",IF($K$106=0,"",$K29/$K$106)) -> 0.028074352
A30: =IFERROR(INDEX($A$173:$A$252,MATCH(ROW()-25,$N$173:$N$252,0)),"") -> AN23207-0500D | B30: =IF($A30="","",INDEX($B$173:$B$252,MATCH(ROW()-25,$N$173:$N$252,0))) -> 1.15 | C30: =IF($A30="","",INDEX($C$173:$C$252,MATCH(ROW()-25,$N$173:$N$252,0))) -> 46023 | D30: =IF($A30="","",INDEX($D$173:$D$252,MATCH(ROW()-25,$N$173:$N$252,0))) -> 46112 | E30: =IF($A30="","",INDEX($E$173:$E$252,MATCH(ROW()-25,$N$173:$N$252,0))) -> On Hold | F30: =IF($A30="","",INDEX($F$173:$F$252,MATCH(ROW()-25,$N$173:$N$252,0))) -> 0.65 | G30: =IF($A30="","",INDEX($G$173:$G$252,MATCH(ROW()-25,$N$173:$N$252,0))) -> 0 | H30: =IF($A30="","",INDEX($H$173:$H$252,MATCH(ROW()-25,$N$173:$N$252,0))) -> 1.15 | I30: =IF($A30="","",INDEX($I$173:$I$252,MATCH(ROW()-25,$N$173:$N$252,0))) -> 1.15 | J30: =IF($A30="","",INDEX($J$173:$J$252,MATCH(ROW()-25,$N$173:$N$252,0))) -> 0 | K30: =IF($A30="","",INDEX($K$173:$K$252,MATCH(ROW()-25,$N$173:$N$252,0))) -> 1.15 | L30: =IF($A30="","",INDEX($L$173:$L$252,MATCH(ROW()-25,$N$173:$N$252,0))) -> 0 | M30: =IF($A30="","",IF($K$106=0,"",$K30/$K$106)) -> 0.025652939
A31: =IFERROR(INDEX($A$173:$A$252,MATCH(ROW()-25,$N$173:$N$252,0)),"") -> AN23276-0100D | B31: =IF($A31="","",INDEX($B$173:$B$252,MATCH(ROW()-25,$N$173:$N$252,0))) -> 5 | C31: =IF($A31="","",INDEX($C$173:$C$252,MATCH(ROW()-25,$N$173:$N$252,0))) -> 45474 | D31: =IF($A31="","",INDEX($D$173:$D$252,MATCH(ROW()-25,$N$173:$N$252,0))) -> 46295 | E31: =IF($A31="","",INDEX($E$173:$E$252,MATCH(ROW()-25,$N$173:$N$252,0))) -> On Hold | F31: =IF($A31="","",INDEX($F$173:$F$252,MATCH(ROW()-25,$N$173:$N$252,0))) -> 0.9 | G31: =IF($A31="","",INDEX($G$173:$G$252,MATCH(ROW()-25,$N$173:$N$252,0))) -> 0.88918919 | H31: =IF($A31="","",INDEX($H$173:$H$252,MATCH(ROW()-25,$N$173:$N$252,0))) -> 0.98798799 | I31: =IF($A31="","",INDEX($I$173:$I$252,MATCH(ROW()-25,$N$173:$N$252,0))) -> 0.098798799 | J31: =IF($A31="","",INDEX($J$173:$J$252,MATCH(ROW()-25,$N$173:$N$252,0))) -> 4.012012 | K31: =IF($A31="","",INDEX($K$173:$K$252,MATCH(ROW()-25,$N$173:$N$252,0))) -> 1.6605839 | L31: =IF($A31="","",INDEX($L$173:$L$252,MATCH(ROW()-25,$N$173:$N$252,0))) -> 0 | M31: =IF($A31="","",IF($K$106=0,"",$K31/$K$106)) -> 0.037042486
A32: =IFERROR(INDEX($A$173:$A$252,MATCH(ROW()-25,$N$173:$N$252,0)),"") -> AN24073-0100D | B32: =IF($A32="","",INDEX($B$173:$B$252,MATCH(ROW()-25,$N$173:$N$252,0))) -> 1.25 | C32: =IF($A32="","",INDEX($C$173:$C$252,MATCH(ROW()-25,$N$173:$N$252,0))) -> 45839 | D32: =IF($A32="","",INDEX($D$173:$D$252,MATCH(ROW()-25,$N$173:$N$252,0))) -> 46295 | E32: =IF($A32="","",INDEX($E$173:$E$252,MATCH(ROW()-25,$N$173:$N$252,0))) -> On Hold | F32: =IF($A32="","",INDEX($F$173:$F$252,MATCH(ROW()-25,$N$173:$N$252,0))) -> 0.9 | G32: =IF($A32="","",INDEX($G$173:$G$252,MATCH(ROW()-25,$N$173:$N$252,0))) -> 0.92432432 | H32: =IF($A32="","",INDEX($H$173:$H$252,MATCH(ROW()-25,$N$173:$N$252,0))) -> 1.027027 | I32: =IF($A32="","",INDEX($I$173:$I$252,MATCH(ROW()-25,$N$173:$N$252,0))) -> 0.1027027 | J32: =IF($A32="","",INDEX($J$173:$J$252,MATCH(ROW()-25,$N$173:$N$252,0))) -> 0.22297297 | K32: =IF($A32="","",INDEX($K$173:$K$252,MATCH(ROW()-25,$N$173:$N$252,0))) -> 0.74671772 | L32: =IF($A32="","",INDEX($L$173:$L$252,MATCH(ROW()-25,$N$173:$N$252,0))) -> 0 | M32: =IF($A32="","",IF($K$106=0,"",$K32/$K$106)) -> 0.01665696
A33: =IFERROR(INDEX($A$173:$A$252,MATCH(ROW()-25,$N$173:$N$252,0)),"") -> AN24140-0100R | B33: =IF($A33="","",INDEX($B$173:$B$252,MATCH(ROW()-25,$N$173:$N$252,0))) -> 1.5 | C33: =IF($A33="","",INDEX($C$173:$C$252,MATCH(ROW()-25,$N$173:$N$252,0))) -> 45717 | D33: =IF($A33="","",INDEX($D$173:$D$252,MATCH(ROW()-25,$N$173:$N$252,0))) -> 46295 | E33: =IF($A33="","",INDEX($E$173:$E$252,MATCH(ROW()-25,$N$173:$N$252,0))) -> Active | F33: =IF($A33="","",INDEX($F$173:$F$252,MATCH(ROW()-25,$N$173:$N$252,0))) -> 0.1 | G33: =IF($A33="","",INDEX($G$173:$G$252,MATCH(ROW()-25,$N$173:$N$252,0))) -> 0.5027027 | H33: =IF($A33="","",INDEX($H$173:$H$252,MATCH(ROW()-25,$N$173:$N$252,0))) -> 5.027027 | I33: =IF($A33="","",INDEX($I$173:$I$252,MATCH(ROW()-25,$N$173:$N$252,0))) -> 4.5243243 | J33: =IF($A33="","",INDEX($J$173:$J$252,MATCH(ROW()-25,$N$173:$N$252,0))) -> -3.527027 | K33: =IF($A33="","",INDEX($K$173:$K$252,MATCH(ROW()-25,$N$173:$N$252,0))) -> 0.70725389 | L33: =IF($A33="","",INDEX($L$173:$L$252,MATCH(ROW()-25,$N$173:$N$252,0))) -> 0.021621622 | M33: =IF($A33="","",IF($K$106=0,"",$K33/$K$106)) -> 0.015776644
A34: =IFERROR(INDEX($A$173:$A$252,MATCH(ROW()-25,$N$173:$N$252,0)),"") -> CS24035-0100D | B34: =IF($A34="","",INDEX($B$173:$B$252,MATCH(ROW()-25,$N$173:$N$252,0))) -> 4 | C34: =IF($A34="","",INDEX($C$173:$C$252,MATCH(ROW()-25,$N$173:$N$252,0))) -> 45931 | D34: =IF($A34="","",INDEX($D$173:$D$252,MATCH(ROW()-25,$N$173:$N$252,0))) -> 46387 | E34: =IF($A34="","",INDEX($E$173:$E$252,MATCH(ROW()-25,$N$173:$N$252,0))) -> On Hold | F34: =IF($A34="","",INDEX($F$173:$F$252,MATCH(ROW()-25,$N$173:$N$252,0))) -> 0.85 | G34: =IF($A34="","",INDEX($G$173:$G$252,MATCH(ROW()-25,$N$173:$N$252,0))) -> 3.1324324 | H34: =IF($A34="","",INDEX($H$173:$H$252,MATCH(ROW()-25,$N$173:$N$252,0))) -> 3.6852146 | I34: =IF($A34="","",INDEX($I$173:$I$252,MATCH(ROW()-25,$N$173:$N$252,0))) -> 0.55278219 | J34: =IF($A34="","",INDEX($J$173:$J$252,MATCH(ROW()-25,$N$173:$N$252,0))) -> 0.31478537 | K34: =IF($A34="","",INDEX($K$173:$K$252,MATCH(ROW()-25,$N$173:$N$252,0))) -> 3.1947484 | L34: =IF($A34="","",INDEX($L$173:$L$252,MATCH(ROW()-25,$N$173:$N$252,0))) -> 0.57027027 | M34: =IF($A34="","",IF($K$106=0,"",$K34/$K$106)) -> 0.071264943
A35: =IFERROR(INDEX($A$173:$A$252,MATCH(ROW()-25,$N$173:$N$252,0)),"") -> Q25008-0100D | B35: =IF($A35="","",INDEX($B$173:$B$252,MATCH(ROW()-25,$N$173:$N$252,0))) -> 5 | C35: =IF($A35="","",INDEX($C$173:$C$252,MATCH(ROW()-25,$N$173:$N$252,0))) -> 46023 | D35: =IF($A35="","",INDEX($D$173:$D$252,MATCH(ROW()-25,$N$173:$N$252,0))) -> 46235 | E35: =IF($A35="","",INDEX($E$173:$E$252,MATCH(ROW()-25,$N$173:$N$252,0))) -> Finalized | F35: =IF($A35="","",INDEX($F$173:$F$252,MATCH(ROW()-25,$N$173:$N$252,0))) -> 1 | G35: =IF($A35="","",INDEX($G$173:$G$252,MATCH(ROW()-25,$N$173:$N$252,0))) -> 1.9297297 | H35: =IF($A35="","",INDEX($H$173:$H$252,MATCH(ROW()-25,$N$173:$N$252,0))) -> 1.9297297 | I35: =IF($A35="","",INDEX($I$173:$I$252,MATCH(ROW()-25,$N$173:$N$252,0))) -> 0 | J35: =IF($A35="","",INDEX($J$173:$J$252,MATCH(ROW()-25,$N$173:$N$252,0))) -> 3.0702703 | K35: =IF($A35="","",INDEX($K$173:$K$252,MATCH(ROW()-25,$N$173:$N$252,0))) -> 5 | L35: =IF($A35="","",INDEX($L$173:$L$252,MATCH(ROW()-25,$N$173:$N$252,0))) -> 1.8135135 | M35: =IF($A35="","",IF($K$106=0,"",$K35/$K$106)) -> 0.11153452
A36: =IFERROR(INDEX($A$173:$A$252,MATCH(ROW()-25,$N$173:$N$252,0)),"") -> AN24185-0100R | B36: =IF($A36="","",INDEX($B$173:$B$252,MATCH(ROW()-25,$N$173:$N$252,0))) -> 4 | C36: =IF($A36="","",INDEX($C$173:$C$252,MATCH(ROW()-25,$N$173:$N$252,0))) -> 45566 | D36: =IF($A36="","",INDEX($D$173:$D$252,MATCH(ROW()-25,$N$173:$N$252,0))) -> 46112 | E36: =IF($A36="","",INDEX($E$173:$E$252,MATCH(ROW()-25,$N$173:$N$252,0))) -> Finalized | F36: =IF($A36="","",INDEX($F$173:$F$252,MATCH(ROW()-25,$N$173:$N$252,0))) -> 1 | G36: =IF($A36="","",INDEX($G$173:$G$252,MATCH(ROW()-25,$N$173:$N$252,0))) -> 2.9608108 | H36: =IF($A36="","",INDEX($H$173:$H$252,MATCH(ROW()-25,$N$173:$N$252,0))) -> 2.9608108 | I36: =IF($A36="","",INDEX($I$173:$I$252,MATCH(ROW()-25,$N$173:$N$252,0))) -> 0 | J36: =IF($A36="","",INDEX($J$173:$J$252,MATCH(ROW()-25,$N$173:$N$252,0))) -> 1.0391892 | K36: =IF($A36="","",INDEX($K$173:$K$252,MATCH(ROW()-25,$N$173:$N$252,0))) -> 0.65813528 | L36: =IF($A36="","",INDEX($L$173:$L$252,MATCH(ROW()-25,$N$173:$N$252,0))) -> 0.13378378 | M36: =IF($A36="","",IF($K$106=0,"",$K36/$K$106)) -> 0.01468096
A37: =IFERROR(INDEX($A$173:$A$252,MATCH(ROW()-25,$N$173:$N$252,0)),"") -> AN24135-0100R | B37: =IF($A37="","",INDEX($B$173:$B$252,MATCH(ROW()-25,$N$173:$N$252,0))) -> 4 | C37: =IF($A37="","",INDEX($C$173:$C$252,MATCH(ROW()-25,$N$173:$N$252,0))) -> 45566 | D37: =IF($A37="","",INDEX($D$173:$D$252,MATCH(ROW()-25,$N$173:$N$252,0))) -> 46477 | E37: =IF($A37="","",INDEX($E$173:$E$252,MATCH(ROW()-25,$N$173:$N$252,0))) -> On Hold | F37: =IF($A37="","",INDEX($F$173:$F$252,MATCH(ROW()-25,$N$173:$N$252,0))) -> 0.1 | G37: =IF($A37="","",INDEX($G$173:$G$252,MATCH(ROW()-25,$N$173:$N$252,0))) -> 1.8310811 | H37: =IF($A37="","",INDEX($H$173:$H$252,MATCH(ROW()-25,$N$173:$N$252,0))) -> 18.310811 | I37: =IF($A37="","",INDEX($I$173:$I$252,MATCH(ROW()-25,$N$173:$N$252,0))) -> 16.47973 | J37: =IF($A37="","",INDEX($J$173:$J$252,MATCH(ROW()-25,$N$173:$N$252,0))) -> -14.310811 | K37: =IF($A37="","",INDEX($K$173:$K$252,MATCH(ROW()-25,$N$173:$N$252,0))) -> 1.6008772 | L37: =IF($A37="","",INDEX($L$173:$L$252,MATCH(ROW()-25,$N$173:$N$252,0))) -> 0 | M37: =IF($A37="","",IF($K$106=0,"",$K37/$K$106)) -> 0.035710613
... A105: =IFERROR(INDEX($A$173:$A$252,MATCH(ROW()-25,$N$173:$N$252,0)),"") | B105: =IF($A105="","",INDEX($B$173:$B$252,MATCH(ROW()-25,$N$173:$N$252,0))) | C105: =IF($A105="","",INDEX($C$173:$C$252,MATCH(ROW()-25,$N$173:$N$252,0))) | D105: =IF($A105="","",INDEX($D$173:$D$252,MATCH(ROW()-25,$N$173:$N$252,0))) | E105: =IF($A105="","",INDEX($E$173:$E$252,MATCH(ROW()-25,$N$173:$N$252,0))) | F105: =IF($A105="","",INDEX($F$173:$F$252,MATCH(ROW()-25,$N$173:$N$252,0))) | G105: =IF($A105="","",INDEX($G$173:$G$252,MATCH(ROW()-25,$N$173:$N$252,0))) | H105: =IF($A105="","",INDEX($H$173:$H$252,MATCH(ROW()-25,$N$173:$N$252,0))) | I105: =IF($A105="","",INDEX($I$173:$I$252,MATCH(ROW()-25,$N$173:$N$252,0))) | J105: =IF($A105="","",INDEX($J$173:$J$252,MATCH(ROW()-25,$N$173:$N$252,0))) | K105: =IF($A105="","",INDEX($K$173:$K$252,MATCH(ROW()-25,$N$173:$N$252,0))) | L105: =IF($A105="","",INDEX($L$173:$L$252,MATCH(ROW()-25,$N$173:$N$252,0))) | M105: =IF($A105="","",IF($K$106=0,"",$K105/$K$106))
A106: ="TOTAL — "&COUNTIF($A$26:$A$105,"?*")&" project(s) live in period" -> TOTAL — 16 project(s) live in period | B106: =SUM(B26:B105) -> 67.95 | F106: {=IF(B106=0,"",SUMPRODUCT($B$26:$B$105,IF($F$26:$F$105="",0,$F$26:$F$105))/B106)} -> 0.46668138 | G106: =SUM(G26:G105) -> 33.558108 | H106: =SUM(H26:H105) -> 113.89859 | I106: =SUM(I26:I105) -> 80.34048 | J106: =SUM(J26:J105) -> -45.948588 | K106: =SUM(K26:K105) -> 44.829171 | L106: =SUM(L26:L105) -> 17.467568 | M106: =IF($K$106=0,"",1) -> 1
A108: RESOURCE DETAIL — BY ENGINEER (selected period)
A109: Metric | B109: =Inputs!$A$91 -> Ahmed | C109: =Inputs!$A$92 -> Osama | D109: =Inputs!$A$93 -> Kirolos | E109: Total
A110: Actual MM booked in period | B110: =IF($B$5="All Time",Phasing!$Y$680,IF($B$5="Year",SUMIF(Phasing!$E$3:$X$3,$D$5,Phasing!$E$680:$X$680),SUMIF(Phasing!$E$4:$X$4,$B$6,Phasing!$E$680:$X$680))) -> 5.7216216 | C110: =IF($B$5="All Time",Phasing!$Y$681,IF($B$5="Year",SUMIF(Phasing!$E$3:$X$3,$D$5,Phasing!$E$681:$X$681),SUMIF(Phasing!$E$4:$X$4,$B$6,Phasing!$E$681:$X$681))) -> 5.9945946 | D110: =IF($B$5="All Time",Phasing!$Y$682,IF($B$5="Year",SUMIF(Phasing!$E$3:$X$3,$D$5,Phasing!$E$682:$X$682),SUMIF(Phasing!$E$4:$X$4,$B$6,Phasing!$E$682:$X$682))) -> 6.1918919 | E110: =SUM(B110:D110) -> 17.908108
A111: Share of team time in period | B111: =IF($E$110=0,"",B110/$E$110) -> 0.31949894 | C111: =IF($E$110=0,"",C110/$E$110) -> 0.33474193 | D111: =IF($E$110=0,"",D110/$E$110) -> 0.34575913 | E111: =IF(E110=0,"",SUM(B111:D111)) -> 1
A112: Remaining on hand allocated (MM) | B112: =SUMPRODUCT($I$173:$I$252,Inputs!$M$6:$M$85,$M$173:$M$252,Inputs!$I$6:$I$85) -> 22.961746 | C112: =SUMPRODUCT($I$173:$I$252,Inputs!$M$6:$M$85,$M$173:$M$252,Inputs!$J$6:$J$85) -> 24.440535 | D112: =SUMPRODUCT($I$173:$I$252,Inputs!$M$6:$M$85,$M$173:$M$252,Inputs!$K$6:$K$85) -> 6.1658979 | E112: =SUM(B112:D112) -> 53.568178
A113: Capacity in period (MM) | B113: =IF($B$5="All Time",SUM(Inputs!$B$91:$F$91)*4*Inputs!$B$94,IF($B$5="Year",SUMIF(Inputs!$B$90:$F$90,$D$5,Inputs!$B$91:$F$91)*4*Inputs!$B$94,SUMIF(Inputs!$B$90:$F$90,$D$5,Inputs!$B$91:$F$91)*Inputs!$B$94)) -> 12 | C113: =IF($B$5="All Time",SUM(Inputs!$B$92:$F$92)*4*Inputs!$B$94,IF($B$5="Year",SUMIF(Inputs!$B$90:$F$90,$D$5,Inputs!$B$92:$F$92)*4*Inputs!$B$94,SUMIF(Inputs!$B$90:$F$90,$D$5,Inputs!$B$92:$F$92)*Inputs!$B$94)) -> 12 | D113: =IF($B$5="All Time",SUM(Inputs!$B$93:$F$93)*4*Inputs!$B$94,IF($B$5="Year",SUMIF(Inputs!$B$90:$F$90,$D$5,Inputs!$B$93:$F$93)*4*Inputs!$B$94,SUMIF(Inputs!$B$90:$F$90,$D$5,Inputs!$B$93:$F$93)*Inputs!$B$94)) -> 12 | E113: =SUM(B113:D113) -> 36
A114: Utilisation in period | B114: =IF(B113=0,"",B110/B113) -> 0.4768018 | C114: =IF(C113=0,"",C110/C113) -> 0.49954955 | D114: =IF(D113=0,"",D110/D113) -> 0.51599099 | E114: =IF(E113=0,"",E110/E113) -> 0.49744745
A115: Years of work outstanding | B115: =IF(SUMIF(Inputs!$B$90:$F$90,$D$5,Inputs!$B$91:$F$91)*4*Inputs!$B$94=0,"",B112/(SUMIF(Inputs!$B$90:$F$90,$D$5,Inputs!$B$91:$F$91)*4*Inputs!$B$94)) -> 1.9134788 | C115: =IF(SUMIF(Inputs!$B$90:$F$90,$D$5,Inputs!$B$92:$F$92)*4*Inputs!$B$94=0,"",C112/(SUMIF(Inputs!$B$90:$F$90,$D$5,Inputs!$B$92:$F$92)*4*Inputs!$B$94)) -> 2.0367112 | D115: =IF(SUMIF(Inputs!$B$90:$F$90,$D$5,Inputs!$B$93:$F$93)*4*Inputs!$B$94=0,"",D112/(SUMIF(Inputs!$B$90:$F$90,$D$5,Inputs!$B$93:$F$93)*4*Inputs!$B$94)) -> 0.51382482 | E115: =IF($E$113=0,"",$E$112/($E$113*IF($B$5="Quarter",4,IF($B$5="Year",1,0.2)))) -> 1.4880049
A139: Chart data — by quarter
A140: Quarter | B140: Planned MM | C140: Actual MM | D140: Earned MM
A141: =Analysis!E$4 -> Q1-24 | B141: =Analysis!E$17 -> 6.151677 | C141: =Analysis!E$18 -> 3.7364865 | D141: =Analysis!E$19 -> 13.904223
A142: =Analysis!F$4 -> Q2-24 | B142: =Analysis!F$17 -> 21.278277 | C142: =Analysis!F$18 -> 3.4824324 | D142: =Analysis!F$19 -> 13.484699
A143: =Analysis!G$4 -> Q3-24 | B143: =Analysis!G$17 -> 16.690901 | C143: =Analysis!G$18 -> 5.9310811 | D143: =Analysis!G$19 -> 16.051781
A144: =Analysis!H$4 -> Q4-24 | B144: =Analysis!H$17 -> 11.243859 | C144: =Analysis!H$18 -> 8.0783784 | D144: =Analysis!H$19 -> 14.157122
A145: =Analysis!I$4 -> Q1-25 | B145: =Analysis!I$17 -> 9.4582061 | C145: =Analysis!I$18 -> 7.2337838 | D145: =Analysis!I$19 -> 7.5015239
A146: =Analysis!J$4 -> Q2-25 | B146: =Analysis!J$17 -> 11.276314 | C146: =Analysis!J$18 -> 5.9608108 | D146: =Analysis!J$19 -> 11.631745
A147: =Analysis!K$4 -> Q3-25 | B147: =Analysis!K$17 -> 15.336632 | C147: =Analysis!K$18 -> 8.7851351 | D147: =Analysis!K$19 -> 13.165997
A148: =Analysis!L$4 -> Q4-25 | B148: =Analysis!L$17 -> 9.5617296 | C148: =Analysis!L$18 -> 8.1783784 | D148: =Analysis!L$19 -> 5.7657842
A149: =Analysis!M$4 -> Q1-26 | B149: =Analysis!M$17 -> 12.801473 | C149: =Analysis!M$18 -> 6.6445946 | D149: =Analysis!M$19 -> 6.379813
A150: =Analysis!N$4 -> Q2-26 | B150: =Analysis!N$17 -> 11.115486 | C150: =Analysis!N$18 -> 7.7986486 | D150: =Analysis!N$19 -> 5.5491442
A151: =Analysis!O$4 -> Q3-26 | B151: =Analysis!O$17 -> 12.858459 | C151: =Analysis!O$18 -> 3.4648649 | D151: =Analysis!O$19 -> 2.2571802
A152: =Analysis!P$4 -> Q4-26 | B152: =Analysis!P$17 -> 8.0537526 | C152: =Analysis!P$18 -> 0 | D152: =Analysis!P$19 -> 0
A153: =Analysis!Q$4 -> Q1-27 | B153: =Analysis!Q$17 -> 4.3984986 | C153: =Analysis!Q$18 -> 0 | D153: =Analysis!Q$19 -> 0
A154: =Analysis!R$4 -> Q2-27 | B154: =Analysis!R$17 -> 4.048248 | C154: =Analysis!R$18 -> 0 | D154: =Analysis!R$19 -> 0
A155: =Analysis!S$4 -> Q3-27 | B155: =Analysis!S$17 -> 3.7790979 | C155: =Analysis!S$18 -> 0 | D155: =Analysis!S$19 -> 0
A156: =Analysis!T$4 -> Q4-27 | B156: =Analysis!T$17 -> 3.7790979 | C156: =Analysis!T$18 -> 0 | D156: =Analysis!T$19 -> 0
A157: =Analysis!U$4 -> Q1-28 | B157: =Analysis!U$17 -> 1.24487 | C157: =Analysis!U$18 -> 0 | D157: =Analysis!U$19 -> 0
A158: =Analysis!V$4 -> Q2-28 | B158: =Analysis!V$17 -> 1.24487 | C158: =Analysis!V$18 -> 0 | D158: =Analysis!V$19 -> 0
A159: =Analysis!W$4 -> Q3-28 | B159: =Analysis!W$17 -> 0.62927497 | C159: =Analysis!W$18 -> 0 | D159: =Analysis!W$19 -> 0
A160: =Analysis!X$4 -> Q4-28 | B160: =Analysis!X$17 -> 0.62927497 | C160: =Analysis!X$18 -> 0 | D160: =Analysis!X$19 -> 0
A162: Chart data — by year
A163: Year | B163: Planned MM | C163: Actual MM | D163: Capacity MM
A164: =TEXT(Analysis!E$36,"0") -> 2024 | B164: =Analysis!E$37 -> 55.364714 | C164: =Analysis!E$38 -> 21.228378 | D164: =Analysis!E$41 -> 28.2
A165: =TEXT(Analysis!F$36,"0") -> 2025 | B165: =Analysis!F$37 -> 45.632882 | C165: =Analysis!F$38 -> 30.158108 | D165: =Analysis!F$41 -> 36
A166: =TEXT(Analysis!G$36,"0") -> 2026 | B166: =Analysis!G$37 -> 44.829171 | C166: =Analysis!G$38 -> 17.908108 | D166: =Analysis!G$41 -> 36
A167: =TEXT(Analysis!H$36,"0") -> 2027 | B167: =Analysis!H$37 -> 16.004942 | C167: =Analysis!H$38 -> 0 | D167: =Analysis!H$41 -> 36
A168: =TEXT(Analysis!I$36,"0") -> 2028 | B168: =Analysis!I$37 -> 3.74829 | C168: =Analysis!I$38 -> 0 | D168: =Analysis!I$41 -> 36
A171: Filter helper — resolves which projects are live in the selected period. Do not edit.
A172: Code | B172: Budget | C172: Start | D172: End | E172: Status | F172: % Compl. | G172: Actual to Date | H172: Cost at Compl. | I172: Remaining | J172: Profit | K172: Planned in Period | L172: Actual in Period | M172: Live? | N172: Rank | O172: Earned in Period | P172: Planned to Date in Period
A173: =IF(Inputs!$A6="","",Inputs!$A6) -> N25178-0100D | B173: =IF($A173="",0,Inputs!$C6) -> 2.4 | C173: =IF($A173="","",Inputs!$D6) -> 46204 | D173: =IF($A173="","",Inputs!$E6) -> 46295 | E173: =IF($A173="","",Inputs!$F6) -> Active | F173: =IF($A173="",0,Inputs!$G6) -> 0.65 | G173: =IF($A173="",0,Inputs!$P6) -> 0 | H173: =IF($A173="",0,Inputs!$Q6) -> 2.4 | I173: =IF($A173="",0,Inputs!$R6) -> 2.4 | J173: =IF($A173="",0,Inputs!$T6) -> 0 | K173: =IF($A173="",0,IF($B$5="All Time",Phasing!$Y180,IF($B$5="Year",SUMIF(Phasing!$E$3:$X$3,$D$5,Phasing!$E180:$X180),SUMIF(Phasing!$E$4:$X$4,$B$6,Phasing!$E180:$X180)))) -> 2.4 | L173: =IF($A173="",0,IF($B$5="All Time",Phasing!$Y510,IF($B$5="Year",SUMIF(Phasing!$E$3:$X$3,$D$5,Phasing!$E510:$X510),SUMIF(Phasing!$E$4:$X$4,$B$6,Phasing!$E510:$X510)))) -> 0 | M173: =IF($A173="",0,IF(AND(Inputs!$D6<=$F$6,Inputs!$E6>=$D$6),1,0)) -> 1 | N173: =IF($M173=0,"",SUM($M$173:$M173)) -> 1 | O173: =IF($A173="",0,IF($B$5="All Time",Phasing!$Y595,IF($B$5="Year",SUMIF(Phasing!$E$3:$X$3,$D$5,Phasing!$E595:$X595),SUMIF(Phasing!$E$4:$X$4,$B$6,Phasing!$E595:$X595)))) -> 0 | P173: {=IF($A173="",0,IF($B$5="All Time",SUMPRODUCT(Phasing!$D180:$X180,Analysis!$D$31:$X$31),IF($B$5="Year",SUMPRODUCT((Analysis!$E$3:$X$3=$D$5)*Phasing!$E180:$X180*Analysis!$E$31:$X$31),SUMPRODUCT((Analysis!$E$4:$X$4=$B$6)*Phasing!$E180:$X180*Analysis!$E$31:$X$31))))} -> 1.6434783
A174: =IF(Inputs!$A7="","",Inputs!$A7) -> E26084-0100D | B174: =IF($A174="",0,Inputs!$C7) -> 3 | C174: =IF($A174="","",Inputs!$D7) -> 45839 | D174: =IF($A174="","",Inputs!$E7) -> 46295 | E174: =IF($A174="","",Inputs!$F7) -> Active | F174: =IF($A174="",0,Inputs!$G7) -> 0.1625 | G174: =IF($A174="",0,Inputs!$P7) -> 0.22567568 | H174: =IF($A174="",0,Inputs!$Q7) -> 1.3887734 | I174: =IF($A174="",0,Inputs!$R7) -> 1.1630977 | J174: =IF($A174="",0,Inputs!$T7) -> 1.6112266 | K174: =IF($A174="",0,IF($B$5="All Time",Phasing!$Y181,IF($B$5="Year",SUMIF(Phasing!$E$3:$X$3,$D$5,Phasing!$E181:$X181),SUMIF(Phasing!$E$4:$X$4,$B$6,Phasing!$E181:$X181)))) -> 1.7921225 | L174: =IF($A174="",0,IF($B$5="All Time",Phasing!$Y511,IF($B$5="Year",SUMIF(Phasing!$E$3:$X$3,$D$5,Phasing!$E511:$X511),SUMIF(Phasing!$E$4:$X$4,$B$6,Phasing!$E511:$X511)))) -> 0.22567568 | M174: =IF($A174="",0,IF(AND(Inputs!$D7<=$F$6,Inputs!$E7>=$D$6),1,0)) -> 1 | N174: =IF($M174=0,"",SUM($M$173:$M174)) -> 2 | O174: =IF($A174="",0,IF($B$5="All Time",Phasing!$Y596,IF($B$5="Year",SUMIF(Phasing!$E$3:$X$3,$D$5,Phasing!$E596:$X596),SUMIF(Phasing!$E$4:$X$4,$B$6,Phasing!$E596:$X596)))) -> 0.4875 | P174: {=IF($A174="",0,IF($B$5="All Time",SUMPRODUCT(Phasing!$D181:$X181,Analysis!$D$31:$X$31),IF($B$5="Year",SUMPRODUCT((Analysis!$E$3:$X$3=$D$5)*Phasing!$E181:$X181*Analysis!$E$31:$X$31),SUMPRODUCT((Analysis!$E$4:$X$4=$B$6)*Phasing!$E181:$X181*Analysis!$E$31:$X$31))))} -> 1.6017505
A175: =IF(Inputs!$A8="","",Inputs!$A8) -> N25185-0100D | B175: =IF($A175="",0,Inputs!$C8) -> 26 | C175: =IF($A175="","",Inputs!$D8) -> 45931 | D175: =IF($A175="","",Inputs!$E8) -> 46387 | E175: =IF($A175="","",Inputs!$F8) -> Active | F175: =IF($A175="",0,Inputs!$G8) -> 0.316 | G175: =IF($A175="",0,Inputs!$P8) -> 18.516216 | H175: =IF($A175="",0,Inputs!$Q8) -> 58.595621 | I175: =IF($A175="",0,Inputs!$R8) -> 40.079405 | J175: =IF($A175="",0,Inputs!$T8) -> -32.595621 | K175: =IF($A175="",0,IF($B$5="All Time",Phasing!$Y182,IF($B$5="Year",SUMIF(Phasing!$E$3:$X$3,$D$5,Phasing!$E182:$X182),SUMIF(Phasing!$E$4:$X$4,$B$6,Phasing!$E182:$X182)))) -> 20.765864 | L175: =IF($A175="",0,IF($B$5="All Time",Phasing!$Y512,IF($B$5="Year",SUMIF(Phasing!$E$3:$X$3,$D$5,Phasing!$E512:$X512),SUMIF(Phasing!$E$4:$X$4,$B$6,Phasing!$E512:$X512)))) -> 13.517568 | M175: =IF($A175="",0,IF(AND(Inputs!$D8<=$F$6,Inputs!$E8>=$D$6),1,0)) -> 1 | N175: =IF($M175=0,"",SUM($M$173:$M175)) -> 3 | O175: =IF($A175="",0,IF($B$5="All Time",Phasing!$Y597,IF($B$5="Year",SUMIF(Phasing!$E$3:$X$3,$D$5,Phasing!$E597:$X597),SUMIF(Phasing!$E$4:$X$4,$B$6,Phasing!$E597:$X597)))) -> 5.9980038 | P175: {=IF($A175="",0,IF($B$5="All Time",SUMPRODUCT(Phasing!$D182:$X182,Analysis!$D$31:$X$31),IF($B$5="Year",SUMPRODUCT((Analysis!$E$3:$X$3=$D$5)*Phasing!$E182:$X182*Analysis!$E$31:$X$31),SUMPRODUCT((Analysis!$E$4:$X$4=$B$6)*Phasing!$E182:$X182*Analysis!$E$31:$X$31))))} -> 13.881838
A176: =IF(Inputs!$A9="","",Inputs!$A9) -> AN22137-0100D | B176: =IF($A176="",0,Inputs!$C9) -> 5 | C176: =IF($A176="","",Inputs!$D9) -> 46388 | D176: =IF($A176="","",Inputs!$E9) -> 47118 | E176: =IF($A176="","",Inputs!$F9) -> Not Started | F176: =IF($A176="",0,Inputs!$G9) -> 0 | G176: =IF($A176="",0,Inputs!$P9) -> 1.4013514 | H176: =IF($A176="",0,Inputs!$Q9) -> 5 | I176: =IF($A176="",0,Inputs!$R9) -> 3.5986486 | J176: =IF($A176="",0,Inputs!$T9) -> 0 | K176: =IF($A176="",0,IF($B$5="All Time",Phasing!$Y183,IF($B$5="Year",SUMIF(Phasing!$E$3:$X$3,$D$5,Phasing!$E183:$X183),SUMIF(Phasing!$E$4:$X$4,$B$6,Phasing!$E183:$X183)))) -> 0 | L176: =IF($A176="",0,IF($B$5="All Time",Phasing!$Y513,IF($B$5="Year",SUMIF(Phasing!$E$3:$X$3,$D$5,Phasing!$E513:$X513),SUMIF(Phasing!$E$4:$X$4,$B$6,Phasing!$E513:$X513)))) -> 0 | M176: =IF($A176="",0,IF(AND(Inputs!$D9<=$F$6,Inputs!$E9>=$D$6),1,0)) -> 0 | N176: =IF($M176=0,"",SUM($M$173:$M176)) | O176: =IF($A176="",0,IF($B$5="All Time",Phasing!$Y598,IF($B$5="Year",SUMIF(Phasing!$E$3:$X$3,$D$5,Phasing!$E598:$X598),SUMIF(Phasing!$E$4:$X$4,$B$6,Phasing!$E598:$X598)))) -> 0 | P176: {=IF($A176="",0,IF($B$5="All Time",SUMPRODUCT(Phasing!$D183:$X183,Analysis!$D$31:$X$31),IF($B$5="Year",SUMPRODUCT((Analysis!$E$3:$X$3=$D$5)*Phasing!$E183:$X183*Analysis!$E$31:$X$31),SUMPRODUCT((Analysis!$E$4:$X$4=$B$6)*Phasing!$E183:$X183*Analysis!$E$31:$X$31))))} -> 0
A177: =IF(Inputs!$A10="","",Inputs!$A10) -> D26058-0100D | B177: =IF($A177="",0,Inputs!$C10) -> 5 | C177: =IF($A177="","",Inputs!$D10) -> 46204 | D177: =IF($A177="","",Inputs!$E10) -> 46934 | E177: =IF($A177="","",Inputs!$F10) -> Not Started | F177: =IF($A177="",0,Inputs!$G10) -> 0 | G177: =IF($A177="",0,Inputs!$P10) -> 0 | H177: =IF($A177="",0,Inputs!$Q10) -> 5 | I177: =IF($A177="",0,Inputs!$R10) -> 5 | J177: =IF($A177="",0,Inputs!$T10) -> 0 | K177: =IF($A177="",0,IF($B$5="All Time",Phasing!$Y184,IF($B$5="Year",SUMIF(Phasing!$E$3:$X$3,$D$5,Phasing!$E184:$X184),SUMIF(Phasing!$E$4:$X$4,$B$6,Phasing!$E184:$X184)))) -> 1.2585499 | L177: =IF($A177="",0,IF($B$5="All Time",Phasing!$Y514,IF($B$5="Year",SUMIF(Phasing!$E$3:$X$3,$D$5,Phasing!$E514:$X514),SUMIF(Phasing!$E$4:$X$4,$B$6,Phasing!$E514:$X514)))) -> 0 | M177: =IF($A177="",0,IF(AND(Inputs!$D10<=$F$6,Inputs!$E10>=$D$6),1,0)) -> 1 | N177: =IF($M177=0,"",SUM($M$173:$M177)) -> 4 | O177: =IF($A177="",0,IF($B$5="All Time",Phasing!$Y599,IF($B$5="Year",SUMIF(Phasing!$E$3:$X$3,$D$5,Phasing!$E599:$X599),SUMIF(Phasing!$E$4:$X$4,$B$6,Phasing!$E599:$X599)))) -> 0 | P177: {=IF($A177="",0,IF($B$5="All Time",SUMPRODUCT(Phasing!$D184:$X184,Analysis!$D$31:$X$31),IF($B$5="Year",SUMPRODUCT((Analysis!$E$3:$X$3=$D$5)*Phasing!$E184:$X184*Analysis!$E$31:$X$31),SUMPRODUCT((Analysis!$E$4:$X$4=$B$6)*Phasing!$E184:$X184*Analysis!$E$31:$X$31))))} -> 0.43091655
A178: =IF(Inputs!$A11="","",Inputs!$A11) -> AD24217-0100D | B178: =IF($A178="",0,Inputs!$C11) -> 3 | C178: =IF($A178="","",Inputs!$D11) -> 45809 | D178: =IF($A178="","",Inputs!$E11) -> 45870 | E178: =IF($A178="","",Inputs!$F11) -> Finalized | F178: =IF($A178="",0,Inputs!$G11) -> 1 | G178: =IF($A178="",0,Inputs!$P11) -> 2.6 | H178: =IF($A178="",0,Inputs!$Q11) -> 2.6 | I178: =IF($A178="",0,Inputs!$R11) -> 0 | J178: =IF($A178="",0,Inputs!$T11) -> 0.4 | K178: =IF($A178="",0,IF($B$5="All Time",Phasing!$Y185,IF($B$5="Year",SUMIF(Phasing!$E$3:$X$3,$D$5,Phasing!$E185:$X185),SUMIF(Phasing!$E$4:$X$4,$B$6,Phasing!$E185:$X185)))) -> 0 | L178: =IF($A178="",0,IF($B$5="All Time",Phasing!$Y515,IF($B$5="Year",SUMIF(Phasing!$E$3:$X$3,$D$5,Phasing!$E515:$X515),SUMIF(Phasing!$E$4:$X$4,$B$6,Phasing!$E515:$X515)))) -> 0 | M178: =IF($A178="",0,IF(AND(Inputs!$D11<=$F$6,Inputs!$E11>=$D$6),1,0)) -> 0 | N178: =IF($M178=0,"",SUM($M$173:$M178)) | O178: =IF($A178="",0,IF($B$5="All Time",Phasing!$Y600,IF($B$5="Year",SUMIF(Phasing!$E$3:$X$3,$D$5,Phasing!$E600:$X600),SUMIF(Phasing!$E$4:$X$4,$B$6,Phasing!$E600:$X600)))) -> 0 | P178: {=IF($A178="",0,IF($B$5="All Time",SUMPRODUCT(Phasing!$D185:$X185,Analysis!$D$31:$X$31),IF($B$5="Year",SUMPRODUCT((Analysis!$E$3:$X$3=$D$5)*Phasing!$E185:$X185*Analysis!$E$31:$X$31),SUMPRODUCT((Analysis!$E$4:$X$4=$B$6)*Phasing!$E185:$X185*Analysis!$E$31:$X$31))))} -> 0
A179: =IF(Inputs!$A12="","",Inputs!$A12) -> AN23207-0500D | B179: =IF($A179="",0,Inputs!$C12) -> 1.15 | C179: =IF($A179="","",Inputs!$D12) -> 46023 | D179: =IF($A179="","",Inputs!$E12) -> 46112 | E179: =IF($A179="","",Inputs!$F12) -> On Hold | F179: =IF($A179="",0,Inputs!$G12) -> 0.65 | G179: =IF($A179="",0,Inputs!$P12) -> 0 | H179: =IF($A179="",0,Inputs!$Q12) -> 1.15 | I179: =IF($A179="",0,Inputs!$R12) -> 1.15 | J179: =IF($A179="",0,Inputs!$T12) -> 0 | K179: =IF($A179="",0,IF($B$5="All Time",Phasing!$Y186,IF($B$5="Year",SUMIF(Phasing!$E$3:$X$3,$D$5,Phasing!$E186:$X186),SUMIF(Phasing!$E$4:$X$4,$B$6,Phasing!$E186:$X186)))) -> 1.15 | L179: =IF($A179="",0,IF($B$5="All Time",Phasing!$Y516,IF($B$5="Year",SUMIF(Phasing!$E$3:$X$3,$D$5,Phasing!$E516:$X516),SUMIF(Phasing!$E$4:$X$4,$B$6,Phasing!$E516:$X516)))) -> 0 | M179: =IF($A179="",0,IF(AND(Inputs!$D12<=$F$6,Inputs!$E12>=$D$6),1,0)) -> 1 | N179: =IF($M179=0,"",SUM($M$173:$M179)) -> 5 | O179: =IF($A179="",0,IF($B$5="All Time",Phasing!$Y601,IF($B$5="Year",SUMIF(Phasing!$E$3:$X$3,$D$5,Phasing!$E601:$X601),SUMIF(Phasing!$E$4:$X$4,$B$6,Phasing!$E601:$X601)))) -> 0 | P179: {=IF($A179="",0,IF($B$5="All Time",SUMPRODUCT(Phasing!$D186:$X186,Analysis!$D$31:$X$31),IF($B$5="Year",SUMPRODUCT((Analysis!$E$3:$X$3=$D$5)*Phasing!$E186:$X186*Analysis!$E$31:$X$31),SUMPRODUCT((Analysis!$E$4:$X$4=$B$6)*Phasing!$E186:$X186*Analysis!$E$31:$X$31))))} -> 1.15
A180: =IF(Inputs!$A13="","",Inputs!$A13) -> AN23276-0100D | B180: =IF($A180="",0,Inputs!$C13) -> 5 | C180: =IF($A180="","",Inputs!$D13) -> 45474 | D180: =IF($A180="","",Inputs!$E13) -> 46295 | E180: =IF($A180="","",Inputs!$F13) -> On Hold | F180: =IF($A180="",0,Inputs!$G13) -> 0.9 | G180: =IF($A180="",0,Inputs!$P13) -> 0.88918919 | H180: =IF($A180="",0,Inputs!$Q13) -> 0.98798799 | I180: =IF($A180="",0,Inputs!$R13) -> 0.098798799 | J180: =IF($A180="",0,Inputs!$T13) -> 4.012012 | K180: =IF($A180="",0,IF($B$5="All Time",Phasing!$Y187,IF($B$5="Year",SUMIF(Phasing!$E$3:$X$3,$D$5,Phasing!$E187:$X187),SUMIF(Phasing!$E$4:$X$4,$B$6,Phasing!$E187:$X187)))) -> 1.6605839 | L180: =IF($A180="",0,IF($B$5="All Time",Phasing!$Y517,IF($B$5="Year",SUMIF(Phasing!$E$3:$X$3,$D$5,Phasing!$E517:$X517),SUMIF(Phasing!$E$4:$X$4,$B$6,Phasing!$E517:$X517)))) -> 0 | M180: =IF($A180="",0,IF(AND(Inputs!$D13<=$F$6,Inputs!$E13>=$D$6),1,0)) -> 1 | N180: =IF($M180=0,"",SUM($M$173:$M180)) -> 6 | O180: =IF($A180="",0,IF($B$5="All Time",Phasing!$Y602,IF($B$5="Year",SUMIF(Phasing!$E$3:$X$3,$D$5,Phasing!$E602:$X602),SUMIF(Phasing!$E$4:$X$4,$B$6,Phasing!$E602:$X602)))) -> 0 | P180: {=IF($A180="",0,IF($B$5="All Time",SUMPRODUCT(Phasing!$D187:$X187,Analysis!$D$31:$X$31),IF($B$5="Year",SUMPRODUCT((Analysis!$E$3:$X$3=$D$5)*Phasing!$E187:$X187*Analysis!$E$31:$X$31),SUMPRODUCT((Analysis!$E$4:$X$4=$B$6)*Phasing!$E187:$X187*Analysis!$E$31:$X$31))))} -> 1.4841849
A181: =IF(Inputs!$A14="","",Inputs!$A14) -> AN24073-0100D | B181: =IF($A181="",0,Inputs!$C14) -> 1.25 | C181: =IF($A181="","",Inputs!$D14) -> 45839 | D181: =IF($A181="","",Inputs!$E14) -> 46295 | E181: =IF($A181="","",Inputs!$F14) -> On Hold | F181: =IF($A181="",0,Inputs!$G14) -> 0.9 | G181: =IF($A181="",0,Inputs!$P14) -> 0.92432432 | H181: =IF($A181="",0,Inputs!$Q14) -> 1.027027 | I181: =IF($A181="",0,Inputs!$R14) -> 0.1027027 | J181: =IF($A181="",0,Inputs!$T14) -> 0.22297297 | K181: =IF($A181="",0,IF($B$5="All Time",Phasing!$Y188,IF($B$5="Year",SUMIF(Phasing!$E$3:$X$3,$D$5,Phasing!$E188:$X188),SUMIF(Phasing!$E$4:$X$4,$B$6,Phasing!$E188:$X188)))) -> 0.74671772 | L181: =IF($A181="",0,IF($B$5="All Time",Phasing!$Y518,IF($B$5="Year",SUMIF(Phasing!$E$3:$X$3,$D$5,Phasing!$E518:$X518),SUMIF(Phasing!$E$4:$X$4,$B$6,Phasing!$E518:$X518)))) -> 0 | M181: =IF($A181="",0,IF(AND(Inputs!$D14<=$F$6,Inputs!$E14>=$D$6),1,0)) -> 1 | N181: =IF($M181=0,"",SUM($M$173:$M181)) -> 7 | O181: =IF($A181="",0,IF($B$5="All Time",Phasing!$Y603,IF($B$5="Year",SUMIF(Phasing!$E$3:$X$3,$D$5,Phasing!$E603:$X603),SUMIF(Phasing!$E$4:$X$4,$B$6,Phasing!$E603:$X603)))) -> 0 | P181: {=IF($A181="",0,IF($B$5="All Time",SUMPRODUCT(Phasing!$D188:$X188,Analysis!$D$31:$X$31),IF($B$5="Year",SUMPRODUCT((Analysis!$E$3:$X$3=$D$5)*Phasing!$E188:$X188*Analysis!$E$31:$X$31),SUMPRODUCT((Analysis!$E$4:$X$4=$B$6)*Phasing!$E188:$X188*Analysis!$E$31:$X$31))))} -> 0.66739606
A182: =IF(Inputs!$A15="","",Inputs!$A15) -> AN24140-0100R | B182: =IF($A182="",0,Inputs!$C15) -> 1.5 | C182: =IF($A182="","",Inputs!$D15) -> 45717 | D182: =IF($A182="","",Inputs!$E15) -> 46295 | E182: =IF($A182="","",Inputs!$F15) -> Active | F182: =IF($A182="",0,Inputs!$G15) -> 0.1 | G182: =IF($A182="",0,Inputs!$P15) -> 0.5027027 | H182: =IF($A182="",0,Inputs!$Q15) -> 5.027027 | I182: =IF($A182="",0,Inputs!$R15) -> 4.5243243 | J182: =IF($A182="",0,Inputs!$T15) -> -3.527027 | K182: =IF($A182="",0,IF($B$5="All Time",Phasing!$Y189,IF($B$5="Year",SUMIF(Phasing!$E$3:$X$3,$D$5,Phasing!$E189:$X189),SUMIF(Phasing!$E$4:$X$4,$B$6,Phasing!$E189:$X189)))) -> 0.70725389 | L182: =IF($A182="",0,IF($B$5="All Time",Phasing!$Y519,IF($B$5="Year",SUMIF(Phasing!$E$3:$X$3,$D$5,Phasing!$E519:$X519),SUMIF(Phasing!$E$4:$X$4,$B$6,Phasing!$E519:$X519)))) -> 0.021621622 | M182: =IF($A182="",0,IF(AND(Inputs!$D15<=$F$6,Inputs!$E15>=$D$6),1,0)) -> 1 | N182: =IF($M182=0,"",SUM($M$173:$M182)) -> 8 | O182: =IF($A182="",0,IF($B$5="All Time",Phasing!$Y604,IF($B$5="Year",SUMIF(Phasing!$E$3:$X$3,$D$5,Phasing!$E604:$X604),SUMIF(Phasing!$E$4:$X$4,$B$6,Phasing!$E604:$X604)))) -> 0.0064516129 | P182: {=IF($A182="",0,IF($B$5="All Time",SUMPRODUCT(Phasing!$D189:$X189,Analysis!$D$31:$X$31),IF($B$5="Year",SUMPRODUCT((Analysis!$E$3:$X$3=$D$5)*Phasing!$E189:$X189*Analysis!$E$31:$X$31),SUMPRODUCT((Analysis!$E$4:$X$4=$B$6)*Phasing!$E189:$X189*Analysis!$E$31:$X$31))))} -> 0.63212435
A183: =IF(Inputs!$A16="","",Inputs!$A16) -> CS24035-0100D | B183: =IF($A183="",0,Inputs!$C16) -> 4 | C183: =IF($A183="","",Inputs!$D16) -> 45931 | D183: =IF($A183="","",Inputs!$E16) -> 46387 | E183: =IF($A183="","",Inputs!$F16) -> On Hold | F183: =IF($A183="",0,Inputs!$G16) -> 0.85 | G183: =IF($A183="",0,Inputs!$P16) -> 3.1324324 | H183: =IF($A183="",0,Inputs!$Q16) -> 3.6852146 | I183: =IF($A183="",0,Inputs!$R16) -> 0.55278219 | J183: =IF($A183="",0,Inputs!$T16) -> 0.31478537 | K183: =IF($A183="",0,IF($B$5="All Time",Phasing!$Y190,IF($B$5="Year",SUMIF(Phasing!$E$3:$X$3,$D$5,Phasing!$E190:$X190),SUMIF(Phasing!$E$4:$X$4,$B$6,Phasing!$E190:$X190)))) -> 3.1947484 | L183: =IF($A183="",0,IF($B$5="All Time",Phasing!$Y520,IF($B$5="Year",SUMIF(Phasing!$E$3:$X$3,$D$5,Phasing!$E520:$X520),SUMIF(Phasing!$E$4:$X$4,$B$6,Phasing!$E520:$X520)))) -> 0.57027027 | M183: =IF($A183="",0,IF(AND(Inputs!$D16<=$F$6,Inputs!$E16>=$D$6),1,0)) -> 1 | N183: =IF($M183=0,"",SUM($M$173:$M183)) -> 9 | O183: =IF($A183="",0,IF($B$5="All Time",Phasing!$Y605,IF($B$5="Year",SUMIF(Phasing!$E$3:$X$3,$D$5,Phasing!$E605:$X605),SUMIF(Phasing!$E$4:$X$4,$B$6,Phasing!$E605:$X605)))) -> 0.61898188 | P183: {=IF($A183="",0,IF($B$5="All Time",SUMPRODUCT(Phasing!$D190:$X190,Analysis!$D$31:$X$31),IF($B$5="Year",SUMPRODUCT((Analysis!$E$3:$X$3=$D$5)*Phasing!$E190:$X190*Analysis!$E$31:$X$31),SUMPRODUCT((Analysis!$E$4:$X$4=$B$6)*Phasing!$E190:$X190*Analysis!$E$31:$X$31))))} -> 2.1356674
A184: =IF(Inputs!$A17="","",Inputs!$A17) -> E24181-0100D | B184: =IF($A184="",0,Inputs!$C17) -> 0.5 | C184: =IF($A184="","",Inputs!$D17) -> 45505 | D184: =IF($A184="","",Inputs!$E17) -> 45505 | E184: =IF($A184="","",Inputs!$F17) -> Finalized | F184: =IF($A184="",0,Inputs!$G17) -> 1 | G184: =IF($A184="",0,Inputs!$P17) -> 0 | H184: =IF($A184="",0,Inputs!$Q17) -> 0.5 | I184: =IF($A184="",0,Inputs!$R17) -> 0.5 | J184: =IF($A184="",0,Inputs!$T17) -> 0 | K184: =IF($A184="",0,IF($B$5="All Time",Phasing!$Y191,IF($B$5="Year",SUMIF(Phasing!$E$3:$X$3,$D$5,Phasing!$E191:$X191),SUMIF(Phasing!$E$4:$X$4,$B$6,Phasing!$E191:$X191)))) -> 0 | L184: =IF($A184="",0,IF($B$5="All Time",Phasing!$Y521,IF($B$5="Year",SUMIF(Phasing!$E$3:$X$3,$D$5,Phasing!$E521:$X521),SUMIF(Phasing!$E$4:$X$4,$B$6,Phasing!$E521:$X521)))) -> 0 | M184: =IF($A184="",0,IF(AND(Inputs!$D17<=$F$6,Inputs!$E17>=$D$6),1,0)) -> 0 | N184: =IF($M184=0,"",SUM($M$173:$M184)) | O184: =IF($A184="",0,IF($B$5="All Time",Phasing!$Y606,IF($B$5="Year",SUMIF(Phasing!$E$3:$X$3,$D$5,Phasing!$E606:$X606),SUMIF(Phasing!$E$4:$X$4,$B$6,Phasing!$E606:$X606)))) -> 0 | P184: {=IF($A184="",0,IF($B$5="All Time",SUMPRODUCT(Phasing!$D191:$X191,Analysis!$D$31:$X$31),IF($B$5="Year",SUMPRODUCT((Analysis!$E$3:$X$3=$D$5)*Phasing!$E191:$X191*Analysis!$E$31:$X$31),SUMPRODUCT((Analysis!$E$4:$X$4=$B$6)*Phasing!$E191:$X191*Analysis!$E$31:$X$31))))} -> 0
... A252: =IF(Inputs!$A85="","",Inputs!$A85) | B252: =IF($A252="",0,Inputs!$C85) -> 0 | C252: =IF($A252="","",Inputs!$D85) | D252: =IF($A252="","",Inputs!$E85) | E252: =IF($A252="","",Inputs!$F85) | F252: =IF($A252="",0,Inputs!$G85) -> 0 | G252: =IF($A252="",0,Inputs!$P85) -> 0 | H252: =IF($A252="",0,Inputs!$Q85) -> 0 | I252: =IF($A252="",0,Inputs!$R85) -> 0 | J252: =IF($A252="",0,Inputs!$T85) -> 0 | K252: =IF($A252="",0,IF($B$5="All Time",Phasing!$Y259,IF($B$5="Year",SUMIF(Phasing!$E$3:$X$3,$D$5,Phasing!$E259:$X259),SUMIF(Phasing!$E$4:$X$4,$B$6,Phasing!$E259:$X259)))) -> 0 | L252: =IF($A252="",0,IF($B$5="All Time",Phasing!$Y589,IF($B$5="Year",SUMIF(Phasing!$E$3:$X$3,$D$5,Phasing!$E589:$X589),SUMIF(Phasing!$E$4:$X$4,$B$6,Phasing!$E589:$X589)))) -> 0 | M252: =IF($A252="",0,IF(AND(Inputs!$D85<=$F$6,Inputs!$E85>=$D$6),1,0)) -> 0 | N252: =IF($M252=0,"",SUM($M$173:$M252)) | O252: =IF($A252="",0,IF($B$5="All Time",Phasing!$Y674,IF($B$5="Year",SUMIF(Phasing!$E$3:$X$3,$D$5,Phasing!$E674:$X674),SUMIF(Phasing!$E$4:$X$4,$B$6,Phasing!$E674:$X674)))) -> 0 | P252: {=IF($A252="",0,IF($B$5="All Time",SUMPRODUCT(Phasing!$D259:$X259,Analysis!$D$31:$X$31),IF($B$5="Year",SUMPRODUCT((Analysis!$E$3:$X$3=$D$5)*Phasing!$E259:$X259*Analysis!$E$31:$X$31),SUMPRODUCT((Analysis!$E$4:$X$4=$B$6)*Phasing!$E259:$X259*Analysis!$E$31:$X$31))))} -> 0

Sheet Mgmt Review
A1: MANAGEMENT REVIEW — TEAM PERFORMANCE
A2: ="Viewing: "&Dashboard!$H$5&" | All effort in Man-Months (MM) | Reported "&TEXT(TODAY(),"dd mmm yyyy") -> Viewing: Full year 2026 | All effort in Man-Months (MM) | Reported 01 Sep 2026
A4: To change the period, use the View by / Year / Quarter selectors at the top of the Dashboard sheet — this sheet follows them automatically.
A5: ="As at "&TEXT(Dashboard!$H$6,"dd mmm yyyy")&" — "&TEXT(Dashboard!$J$6,"0.0%")&" of the selected period has elapsed. Capacity and plan adherence are pro-rated accordingly, so a part-finished year is not compared against a full year of capacity." -> As at 01 Sep 2026 — 67.1% of the selected period has elapsed. Capacity and plan adherence are pro-rated accordingly, so a part-finished year is not compared against a full year of capacity.
A6: PERFORMANCE IN THE SELECTED PERIOD
A7: Team totals | B7: Planned MM (full period) | C7: Actual MM | D7: Earned MM | E7: Profit / (Loss) | F7: Capacity to Date | G7: Utilisation | H7: Plan Adherence to Date | I7: Efficiency (CPI) | J7: Projects Active
B8: =Dashboard!$B$10 -> 44.829171 | C8: =Dashboard!$C$10 -> 17.908108 | D8: =Dashboard!$D$10 -> 14.186137 | E8: =Dashboard!$E$10 -> -3.7219708 | F8: =Dashboard!$F$10 -> 24.163043 | G8: =Dashboard!$G$10 -> 0.74113628 | H8: =Dashboard!$H$10 -> 0.54727687 | I8: =Dashboard!$I$10 -> 0.79216281 | J8: =Dashboard!$J$10 -> 16
B9: ="what we said we would burn" -> what we said we would burn | C9: ="what we actually burned" -> what we actually burned | D9: ="value delivered" -> value delivered | E9: ="earned minus actual" -> earned minus actual | F9: ="pro-rated to "&TEXT(Dashboard!$H$6,"dd mmm") -> pro-rated to 01 Sep | G9: ="actual vs capacity" -> actual vs capacity | H9: ="vs "&TEXT(Dashboard!$L$6,"0.00")&" MM planned to date" -> vs 32.72 MM planned to date | I9: ="above 1.00 is good" -> above 1.00 is good | J9: ="live in this period" -> live in this period
A11: TEAM KPIs BY ENGINEER — SELECTED PERIOD
A12: KPI | B12: =Inputs!$A$91 -> Ahmed | C12: =Inputs!$A$92 -> Osama | D12: =Inputs!$A$93 -> Kirolos | E12: Team Total
A13: Actual MM booked | B13: =IF(Dashboard!$B$5="All Time",Phasing!$Y$680,IF(Dashboard!$B$5="Year",SUMIF(Phasing!$E$3:$X$3,Dashboard!$D$5,Phasing!$E$680:$X$680),SUMIF(Phasing!$E$4:$X$4,Dashboard!$B$6,Phasing!$E$680:$X$680))) -> 5.7216216 | C13: =IF(Dashboard!$B$5="All Time",Phasing!$Y$681,IF(Dashboard!$B$5="Year",SUMIF(Phasing!$E$3:$X$3,Dashboard!$D$5,Phasing!$E$681:$X$681),SUMIF(Phasing!$E$4:$X$4,Dashboard!$B$6,Phasing!$E$681:$X$681))) -> 5.9945946 | D13: =IF(Dashboard!$B$5="All Time",Phasing!$Y$682,IF(Dashboard!$B$5="Year",SUMIF(Phasing!$E$3:$X$3,Dashboard!$D$5,Phasing!$E$682:$X$682),SUMIF(Phasing!$E$4:$X$4,Dashboard!$B$6,Phasing!$E$682:$X$682))) -> 6.1918919 | E13: =SUM(B13:D13) -> 17.908108
A14: Planned MM to date (by allocation) | B14: =SUMPRODUCT(Dashboard!$P$173:$P$252,Inputs!$I$6:$I$85) -> 12.228239 | C14: =SUMPRODUCT(Dashboard!$P$173:$P$252,Inputs!$J$6:$J$85) -> 9.3573832 | D14: =SUMPRODUCT(Dashboard!$P$173:$P$252,Inputs!$K$6:$K$85) -> 11.136587 | E14: =SUM(B14:D14) -> 32.722209
A15: Earned MM (by allocation) | B15: =SUMPRODUCT(Dashboard!$O$173:$O$252,Inputs!$I$6:$I$85) -> 5.1198091 | C15: =SUMPRODUCT(Dashboard!$O$173:$O$252,Inputs!$J$6:$J$85) -> 3.781334 | D15: =SUMPRODUCT(Dashboard!$O$173:$O$252,Inputs!$K$6:$K$85) -> 5.2849942 | E15: =SUM(B15:D15) -> 14.186137
A16: Profit / (Loss) contribution | B16: =B15-B13 -> -0.60181251 | C16: =C15-C13 -> -2.2132606 | D16: =D15-D13 -> -0.9068977 | E16: =E15-E13 -> -3.7219708
A17: Capacity MM to date | B17: =(IF(Dashboard!$B$5="All Time",SUM(Inputs!$B$91:$F$91)*4*Inputs!$B$94,IF(Dashboard!$B$5="Year",SUMIF(Inputs!$B$90:$F$90,Dashboard!$D$5,Inputs!$B$91:$F$91)*4*Inputs!$B$94,SUMIF(Inputs!$B$90:$F$90,Dashboard!$D$5,Inputs!$B$91:$F$91)*Inputs!$B$94)))*IF(Dashboard!$J$6="",0,Dashboard!$J$6) -> 8.0543478 | C17: =(IF(Dashboard!$B$5="All Time",SUM(Inputs!$B$92:$F$92)*4*Inputs!$B$94,IF(Dashboard!$B$5="Year",SUMIF(Inputs!$B$90:$F$90,Dashboard!$D$5,Inputs!$B$92:$F$92)*4*Inputs!$B$94,SUMIF(Inputs!$B$90:$F$90,Dashboard!$D$5,Inputs!$B$92:$F$92)*Inputs!$B$94)))*IF(Dashboard!$J$6="",0,Dashboard!$J$6) -> 8.0543478 | D17: =(IF(Dashboard!$B$5="All Time",SUM(Inputs!$B$93:$F$93)*4*Inputs!$B$94,IF(Dashboard!$B$5="Year",SUMIF(Inputs!$B$90:$F$90,Dashboard!$D$5,Inputs!$B$93:$F$93)*4*Inputs!$B$94,SUMIF(Inputs!$B$90:$F$90,Dashboard!$D$5,Inputs!$B$93:$F$93)*Inputs!$B$94)))*IF(Dashboard!$J$6="",0,Dashboard!$J$6) -> 8.0543478 | E17: =SUM(B17:D17) -> 24.163043
A18: Utilisation vs capacity to date | B18: =IF(B17=0,"n/a",B13/B17) -> 0.71037677 | C18: =IF(C17=0,"n/a",C13/C17) -> 0.74426815 | D18: =IF(D17=0,"n/a",D13/D17) -> 0.76876391 | E18: =IF(E17=0,"n/a",E13/E17) -> 0.74113628
A19: Plan adherence to date | B19: =IF(B14=0,"n/a",B13/B14) -> 0.46790235 | C19: =IF(C14=0,"n/a",C13/C14) -> 0.64062724 | D19: =IF(D14=0,"n/a",D13/D14) -> 0.55599547 | E19: =IF(E14=0,"n/a",E13/E14) -> 0.54727687
A20: Efficiency (CPI) | B20: =IF(B13=0,"n/a",B15/B13) -> 0.89481784 | C20: =IF(C13=0,"n/a",C15/C13) -> 0.63079062 | D20: =IF(D13=0,"n/a",D15/D13) -> 0.85353464 | E20: =IF(E13=0,"n/a",E15/E13) -> 0.79216281
A21: Share of team time booked | B21: =IF($E$13=0,"",B13/$E$13) -> 0.31949894 | C21: =IF($E$13=0,"",C13/$E$13) -> 0.33474193 | D21: =IF($E$13=0,"",D13/$E$13) -> 0.34575913 | E21: =IF(E13=0,"",SUM(B21:D21)) -> 1
A22: Remaining on hand allocated | B22: =SUMPRODUCT(Dashboard!$I$173:$I$252,Inputs!$M$6:$M$85,Dashboard!$M$173:$M$252,Inputs!$I$6:$I$85) -> 22.961746 | C22: =SUMPRODUCT(Dashboard!$I$173:$I$252,Inputs!$M$6:$M$85,Dashboard!$M$173:$M$252,Inputs!$J$6:$J$85) -> 24.440535 | D22: =SUMPRODUCT(Dashboard!$I$173:$I$252,Inputs!$M$6:$M$85,Dashboard!$M$173:$M$252,Inputs!$K$6:$K$85) -> 6.1658979 | E22: =SUM(B22:D22) -> 53.568178
A24: TYPE-WEIGHTED VIEW — PERSONAL SCORING ONLY (never applied to project financials)
A25: Type-weighted Earned MM (KPI only) | B25: =SUMPRODUCT(Dashboard!$O$173:$O$252,Inputs!$V$6:$V$85,Inputs!$I$6:$I$85) -> 4.7902585 | C25: =SUMPRODUCT(Dashboard!$O$173:$O$252,Inputs!$V$6:$V$85,Inputs!$J$6:$J$85) -> 3.8375137 | D25: =SUMPRODUCT(Dashboard!$O$173:$O$252,Inputs!$V$6:$V$85,Inputs!$K$6:$K$85) -> 4.531845 | E25: =SUM(B25:D25) -> 13.159617
A26: Type-weighted Efficiency (CPI, KPI only) | B26: =IF(B13=0,"n/a",B25/B13) -> 0.83722042 | C26: =IF(C13=0,"n/a",C25/C13) -> 0.64016234 | D26: =IF(D13=0,"n/a",D25/D13) -> 0.73189989 | E26: =IF(E13=0,"n/a",E25/E13) -> 0.73484129
A27: Average type factor of work delivered | B27: =IF(B15=0,"n/a",B25/B15) -> 0.93563224 | C27: =IF(C15=0,"n/a",C25/C15) -> 1.0148571 | D27: =IF(D15=0,"n/a",D25/D15) -> 0.8574929 | E27: =IF(E15=0,"n/a",E25/E15) -> 0.92763921
A30: TEAM PERFORMANCE DEPENDENCY - DRAFTSMEN AND BENGALURU
A31: Cairo hours come from the timesheet. Bengaluru and draftsman hours are entered per deliverable on the Support Plan sheet. Until those are filled in, delivery reads as 100% Cairo.
A33: DELIVERY MIX | B33: Hours | C33: Share | D33: Man-months
A34: Cairo team (from timesheet) | B34: =SUM('Support Plan'!$K$5:$K$68) -> 11970 | C34: =IF($B$37=0,"",$B34/$B$37) -> 1 | D34: =$B34/'Profit Plan'!$B$5 -> 64.702703
A35: Bengaluru support | B35: =SUM('Support Plan'!$I$5:$I$68) -> 0 | C35: =IF($B$37=0,"",$B35/$B$37) -> 0 | D35: =$B35/'Profit Plan'!$B$5 -> 0
A36: Draftsman support | B36: =SUM('Support Plan'!$J$5:$J$68) -> 0 | C36: =IF($B$37=0,"",$B36/$B$37) -> 0 | D36: =$B36/'Profit Plan'!$B$5 -> 0
A37: Total delivered | B37: =SUM($B$34:$B$36) -> 11970 | C37: =IF($B$37=0,"",1) -> 1 | D37: =$B37/'Profit Plan'!$B$5 -> 64.702703
A39: BENGALURU: PLAN VERSUS REALITY
A40: Planned Bengaluru hours | B40: ='Support Plan'!$T$7 -> 0
A41: Actual Bengaluru hours | B41: ='Support Plan'!$T$8 -> 0
A42: Shortfall absorbed by Cairo (hours) | B42: ='Support Plan'!$T$9 -> 0
A43: Shortfall absorbed by Cairo (man-months) | B43: ='Support Plan'!$T$10 -> 0
A44: As a share of Cairo capacity left this year | B44: =IF('Profit Plan'!$B$11=0,"",$B$43/'Profit Plan'!$B$11) -> 0
A45: Deliverables shifted away from the planned office | B45: ='Support Plan'!$T$6 -> 0
A47: DRAFTSMAN DEPENDENCY
A48: Planned draftsman hours | B48: ='Support Plan'!$T$11 -> 0
A49: Actual draftsman hours | B49: ='Support Plan'!$T$12 -> 0
A50: Draftsman share of delivery | B50: =$C$36 -> 0
A51: Deliverables relying on a draftsman | B51: =COUNTIF('Support Plan'!$J$5:$J$68,">0") -> 0
A53: VERDICT | B53: =IF($B$40+$B$48=0,"No support plan entered yet - fill the blue columns on the Support Plan sheet and this section becomes live.",IF($B$42>0,"Cairo absorbed "&TEXT($B$43,"0.00")&" MM of work planned for Bengaluru across "&TEXT($B$45,"0")&" deliverable(s). That is "&TEXT($B$44,"0.0%")&" of the capacity left this year and is a direct hit to CPI.","Bengaluru delivered at or above plan; no unplanned load on Cairo.")) -> No support plan entered yet - fill the blue columns on the Support Plan sheet and this section becomes live.
A70: Chart data
A71: Engineer | B71: Actual MM | C71: Capacity to Date
A72: =$B$12 -> Ahmed | B72: =B$13 -> 5.7216216 | C72: =B$17 -> 8.0543478
A73: =$C$12 -> Osama | B73: =C$13 -> 5.9945946 | C73: =C$17 -> 8.0543478
A74: =$D$12 -> Kirolos | B74: =D$13 -> 6.1918919 | C74: =D$17 -> 8.0543478
A77: Engineer | B77: Planned MM | C77: Actual MM | D77: Earned MM
A78: =$B$12 -> Ahmed | B78: =B$14 -> 12.228239 | C78: =B$13 -> 5.7216216 | D78: =B$15 -> 5.1198091
A79: =$C$12 -> Osama | B79: =C$14 -> 9.3573832 | C79: =C$13 -> 5.9945946 | D79: =C$15 -> 3.781334
A80: =$D$12 -> Kirolos | B80: =D$14 -> 11.136587 | C80: =D$13 -> 6.1918919 | D80: =D$15 -> 5.2849942
A83: Engineer | B83: Utilisation | C83: Plan Adherence
A84: =$B$12 -> Ahmed | B84: =B$18 -> 0.71037677 | C84: =B$19 -> 0.46790235
A85: =$C$12 -> Osama | B85: =C$18 -> 0.74426815 | C85: =C$19 -> 0.64062724
A86: =$D$12 -> Kirolos | B86: =D$18 -> 0.76876391 | C86: =D$19 -> 0.55599547

Sheet Engineer KPIs
A1: ENGINEER KPIs — SELECTED PERIOD
A2: ="Viewing: "&Dashboard!$H$5&" | All effort in Man-Months (MM) | Reported "&TEXT(TODAY(),"dd mmm yyyy") -> Viewing: Full year 2026 | All effort in Man-Months (MM) | Reported 01 Sep 2026
A4: Period is controlled from the Dashboard sheet. This sheet and the Management Review sheet both follow it.
A5: ="As at "&TEXT(Dashboard!$H$6,"dd mmm yyyy")&" — "&TEXT(Dashboard!$J$6,"0.0%")&" of the selected period has elapsed. Capacity and plan adherence are pro-rated accordingly." -> As at 01 Sep 2026 — 67.1% of the selected period has elapsed. Capacity and plan adherence are pro-rated accordingly.
A6: KPI SUMMARY BY ENGINEER
A7: KPI | B7: =Inputs!$A$91 -> Ahmed | C7: =Inputs!$A$92 -> Osama | D7: =Inputs!$A$93 -> Kirolos | E7: Team Total
A8: Actual MM booked | B8: ='Mgmt Review'!B13 -> 5.7216216 | C8: ='Mgmt Review'!C13 -> 5.9945946 | D8: ='Mgmt Review'!D13 -> 6.1918919 | E8: ='Mgmt Review'!E13 -> 17.908108
A9: Planned MM to date (by allocation) | B9: ='Mgmt Review'!B14 -> 12.228239 | C9: ='Mgmt Review'!C14 -> 9.3573832 | D9: ='Mgmt Review'!D14 -> 11.136587 | E9: ='Mgmt Review'!E14 -> 32.722209
A10: Earned MM (by allocation) | B10: ='Mgmt Review'!B15 -> 5.1198091 | C10: ='Mgmt Review'!C15 -> 3.781334 | D10: ='Mgmt Review'!D15 -> 5.2849942 | E10: ='Mgmt Review'!E15 -> 14.186137
A11: Profit / (Loss) contribution | B11: ='Mgmt Review'!B16 -> -0.60181251 | C11: ='Mgmt Review'!C16 -> -2.2132606 | D11: ='Mgmt Review'!D16 -> -0.9068977 | E11: ='Mgmt Review'!E16 -> -3.7219708
A12: Capacity MM to date | B12: ='Mgmt Review'!B17 -> 8.0543478 | C12: ='Mgmt Review'!C17 -> 8.0543478 | D12: ='Mgmt Review'!D17 -> 8.0543478 | E12: ='Mgmt Review'!E17 -> 24.163043
A13: Utilisation vs capacity to date | B13: ='Mgmt Review'!B18 -> 0.71037677 | C13: ='Mgmt Review'!C18 -> 0.74426815 | D13: ='Mgmt Review'!D18 -> 0.76876391 | E13: ='Mgmt Review'!E18 -> 0.74113628
A14: Plan adherence to date | B14: ='Mgmt Review'!B19 -> 0.46790235 | C14: ='Mgmt Review'!C19 -> 0.64062724 | D14: ='Mgmt Review'!D19 -> 0.55599547 | E14: ='Mgmt Review'!E19 -> 0.54727687
A15: Efficiency (CPI) | B15: ='Mgmt Review'!B20 -> 0.89481784 | C15: ='Mgmt Review'!C20 -> 0.63079062 | D15: ='Mgmt Review'!D20 -> 0.85353464 | E15: ='Mgmt Review'!E20 -> 0.79216281
A16: Share of team time booked | B16: ='Mgmt Review'!B21 -> 0.31949894 | C16: ='Mgmt Review'!C21 -> 0.33474193 | D16: ='Mgmt Review'!D21 -> 0.34575913 | E16: ='Mgmt Review'!E21 -> 1
A17: Remaining on hand allocated | B17: ='Mgmt Review'!B22 -> 22.961746 | C17: ='Mgmt Review'!C22 -> 24.440535 | D17: ='Mgmt Review'!D22 -> 6.1658979 | E17: ='Mgmt Review'!E22 -> 53.568178
A18: Projects worked in period | B18: =COUNTIF($C$181:$C$260,">0") -> 6 | C18: =COUNTIF($D$181:$D$260,">0") -> 4 | D18: =COUNTIF($E$181:$E$260,">0") -> 7 | E18: =COUNTIF($F$181:$F$260,">0") -> 11
A19: Average MM per project worked | B19: =IF(B18=0,"n/a",B8/B18) -> 0.9536036 | C19: =IF(C18=0,"n/a",C8/C18) -> 1.4986486 | D19: =IF(D18=0,"n/a",D8/D18) -> 0.88455598 | E19: =IF(E18=0,"n/a",E8/E18) -> 1.6280098
A20: Months of work outstanding | B20: =IF(SUMIF(Inputs!$B$90:$F$90,Dashboard!$D$5,Inputs!$B$91:$F$91)*4*Inputs!$B$94=0,"n/a",B17/(SUMIF(Inputs!$B$90:$F$90,Dashboard!$D$5,Inputs!$B$91:$F$91)*4*Inputs!$B$94)*12) -> 22.961746 | C20: =IF(SUMIF(Inputs!$B$90:$F$90,Dashboard!$D$5,Inputs!$B$92:$F$92)*4*Inputs!$B$94=0,"n/a",C17/(SUMIF(Inputs!$B$90:$F$90,Dashboard!$D$5,Inputs!$B$92:$F$92)*4*Inputs!$B$94)*12) -> 24.440535 | D20: =IF(SUMIF(Inputs!$B$90:$F$90,Dashboard!$D$5,Inputs!$B$93:$F$93)*4*Inputs!$B$94=0,"n/a",D17/(SUMIF(Inputs!$B$90:$F$90,Dashboard!$D$5,Inputs!$B$93:$F$93)*4*Inputs!$B$94)*12) -> 6.1658979 | E20: =IF(SUM(Inputs!$B$91:$B$93)=0,"n/a",E17/(SUMIF(Inputs!$B$90:$F$90,Dashboard!$D$5,Inputs!$B$91:$F$91)*4*Inputs!$B$94+SUMIF(Inputs!$B$90:$F$90,Dashboard!$D$5,Inputs!$B$92:$F$92)*4*Inputs!$B$94+SUMIF(Inputs!$B$90:$F$90,Dashboard!$D$5,Inputs!$B$93:$F$93)*4*Inputs!$B$94)*12) -> 17.856059
A22: WHO WORKED ON WHAT — ACTUAL MM IN THE SELECTED PERIOD
A23: Project | B23: Status | C23: =Inputs!$A$91 -> Ahmed | D23: =Inputs!$A$92 -> Osama | E23: =Inputs!$A$93 -> Kirolos | F23: Total
A24: =IFERROR(INDEX($A$181:$A$260,MATCH(ROW()-23,$G$181:$G$260,0)),"") -> E26084-0100D | B24: =IF($A24="","",INDEX($B$181:$B$260,MATCH(ROW()-23,$G$181:$G$260,0))) -> Active | C24: =IF($A24="","",INDEX($C$181:$C$260,MATCH(ROW()-23,$G$181:$G$260,0))) -> 0 | D24: =IF($A24="","",INDEX($D$181:$D$260,MATCH(ROW()-23,$G$181:$G$260,0))) -> 0.22567568 | E24: =IF($A24="","",INDEX($E$181:$E$260,MATCH(ROW()-23,$G$181:$G$260,0))) -> 0 | F24: =IF($A24="","",INDEX($F$181:$F$260,MATCH(ROW()-23,$G$181:$G$260,0))) -> 0.22567568
A25: =IFERROR(INDEX($A$181:$A$260,MATCH(ROW()-23,$G$181:$G$260,0)),"") -> N25185-0100D | B25: =IF($A25="","",INDEX($B$181:$B$260,MATCH(ROW()-23,$G$181:$G$260,0))) -> Active | C25: =IF($A25="","",INDEX($C$181:$C$260,MATCH(ROW()-23,$G$181:$G$260,0))) -> 5.1 | D25: =IF($A25="","",INDEX($D$181:$D$260,MATCH(ROW()-23,$G$181:$G$260,0))) -> 5.4189189 | E25: =IF($A25="","",INDEX($E$181:$E$260,MATCH(ROW()-23,$G$181:$G$260,0))) -> 2.9986486 | F25: =IF($A25="","",INDEX($F$181:$F$260,MATCH(ROW()-23,$G$181:$G$260,0))) -> 13.517568
A26: =IFERROR(INDEX($A$181:$A$260,MATCH(ROW()-23,$G$181:$G$260,0)),"") -> AN24140-0100R | B26: =IF($A26="","",INDEX($B$181:$B$260,MATCH(ROW()-23,$G$181:$G$260,0))) -> Active | C26: =IF($A26="","",INDEX($C$181:$C$260,MATCH(ROW()-23,$G$181:$G$260,0))) -> 0 | D26: =IF($A26="","",INDEX($D$181:$D$260,MATCH(ROW()-23,$G$181:$G$260,0))) -> 0 | E26: =IF($A26="","",INDEX($E$181:$E$260,MATCH(ROW()-23,$G$181:$G$260,0))) -> 0.021621622 | F26: =IF($A26="","",INDEX($F$181:$F$260,MATCH(ROW()-23,$G$181:$G$260,0))) -> 0.021621622
A27: =IFERROR(INDEX($A$181:$A$260,MATCH(ROW()-23,$G$181:$G$260,0)),"") -> CS24035-0100D | B27: =IF($A27="","",INDEX($B$181:$B$260,MATCH(ROW()-23,$G$181:$G$260,0))) -> On Hold | C27: =IF($A27="","",INDEX($C$181:$C$260,MATCH(ROW()-23,$G$181:$G$260,0))) -> 0.10675676 | D27: =IF($A27="","",INDEX($D$181:$D$260,MATCH(ROW()-23,$G$181:$G$260,0))) -> 0 | E27: =IF($A27="","",INDEX($E$181:$E$260,MATCH(ROW()-23,$G$181:$G$260,0))) -> 0.46351351 | F27: =IF($A27="","",INDEX($F$181:$F$260,MATCH(ROW()-23,$G$181:$G$260,0))) -> 0.57027027
A28: =IFERROR(INDEX($A$181:$A$260,MATCH(ROW()-23,$G$181:$G$260,0)),"") -> Q25008-0100D | B28: =IF($A28="","",INDEX($B$181:$B$260,MATCH(ROW()-23,$G$181:$G$260,0))) -> Finalized | C28: =IF($A28="","",INDEX($C$181:$C$260,MATCH(ROW()-23,$G$181:$G$260,0))) -> 0.14594595 | D28: =IF($A28="","",INDEX($D$181:$D$260,MATCH(ROW()-23,$G$181:$G$260,0))) -> 0 | E28: =IF($A28="","",INDEX($E$181:$E$260,MATCH(ROW()-23,$G$181:$G$260,0))) -> 1.6675676 | F28: =IF($A28="","",INDEX($F$181:$F$260,MATCH(ROW()-23,$G$181:$G$260,0))) -> 1.8135135
A29: =IFERROR(INDEX($A$181:$A$260,MATCH(ROW()-23,$G$181:$G$260,0)),"") -> AN24185-0100R | B29: =IF($A29="","",INDEX($B$181:$B$260,MATCH(ROW()-23,$G$181:$G$260,0))) -> Finalized | C29: =IF($A29="","",INDEX($C$181:$C$260,MATCH(ROW()-23,$G$181:$G$260,0))) -> 0 | D29: =IF($A29="","",INDEX($D$181:$D$260,MATCH(ROW()-23,$G$181:$G$260,0))) -> 0 | E29: =IF($A29="","",INDEX($E$181:$E$260,MATCH(ROW()-23,$G$181:$G$260,0))) -> 0.13378378 | F29: =IF($A29="","",INDEX($F$181:$F$260,MATCH(ROW()-23,$G$181:$G$260,0))) -> 0.13378378
A30: =IFERROR(INDEX($A$181:$A$260,MATCH(ROW()-23,$G$181:$G$260,0)),"") -> AN23108-0100R | B30: =IF($A30="","",INDEX($B$181:$B$260,MATCH(ROW()-23,$G$181:$G$260,0))) -> On Hold | C30: =IF($A30="","",INDEX($C$181:$C$260,MATCH(ROW()-23,$G$181:$G$260,0))) -> 0 | D30: =IF($A30="","",INDEX($D$181:$D$260,MATCH(ROW()-23,$G$181:$G$260,0))) -> 0 | E30: =IF($A30="","",INDEX($E$181:$E$260,MATCH(ROW()-23,$G$181:$G$260,0))) -> 0.68513514 | F30: =IF($A30="","",INDEX($F$181:$F$260,MATCH(ROW()-23,$G$181:$G$260,0))) -> 0.68513514
A31: =IFERROR(INDEX($A$181:$A$260,MATCH(ROW()-23,$G$181:$G$260,0)),"") -> TA24246-0200R | B31: =IF($A31="","",INDEX($B$181:$B$260,MATCH(ROW()-23,$G$181:$G$260,0))) -> On Hold | C31: =IF($A31="","",INDEX($C$181:$C$260,MATCH(ROW()-23,$G$181:$G$260,0))) -> 0 | D31: =IF($A31="","",INDEX($D$181:$D$260,MATCH(ROW()-23,$G$181:$G$260,0))) -> 0.098648649 | E31: =IF($A31="","",INDEX($E$181:$E$260,MATCH(ROW()-23,$G$181:$G$260,0))) -> 0 | F31: =IF($A31="","",INDEX($F$181:$F$260,MATCH(ROW()-23,$G$181:$G$260,0))) -> 0.098648649
A32: =IFERROR(INDEX($A$181:$A$260,MATCH(ROW()-23,$G$181:$G$260,0)),"") -> N23106-0100D | B32: =IF($A32="","",INDEX($B$181:$B$260,MATCH(ROW()-23,$G$181:$G$260,0))) -> Finalized | C32: =IF($A32="","",INDEX($C$181:$C$260,MATCH(ROW()-23,$G$181:$G$260,0))) -> 0.18918919 | D32: =IF($A32="","",INDEX($D$181:$D$260,MATCH(ROW()-23,$G$181:$G$260,0))) -> 0.25135135 | E32: =IF($A32="","",INDEX($E$181:$E$260,MATCH(ROW()-23,$G$181:$G$260,0))) -> 0 | F32: =IF($A32="","",INDEX($F$181:$F$260,MATCH(ROW()-23,$G$181:$G$260,0))) -> 0.44054054
A33: =IFERROR(INDEX($A$181:$A$260,MATCH(ROW()-23,$G$181:$G$260,0)),"") -> Chargable Proposals 26 | B33: =IF($A33="","",INDEX($B$181:$B$260,MATCH(ROW()-23,$G$181:$G$260,0))) -> Active | C33: =IF($A33="","",INDEX($C$181:$C$260,MATCH(ROW()-23,$G$181:$G$260,0))) -> 0.10945946 | D33: =IF($A33="","",INDEX($D$181:$D$260,MATCH(ROW()-23,$G$181:$G$260,0))) -> 0 | E33: =IF($A33="","",INDEX($E$181:$E$260,MATCH(ROW()-23,$G$181:$G$260,0))) -> 0.22162162 | F33: =IF($A33="","",INDEX($F$181:$F$260,MATCH(ROW()-23,$G$181:$G$260,0))) -> 0.33108108
A34: =IFERROR(INDEX($A$181:$A$260,MATCH(ROW()-23,$G$181:$G$260,0)),"") -> Proposals 26 | B34: =IF($A34="","",INDEX($B$181:$B$260,MATCH(ROW()-23,$G$181:$G$260,0))) -> Active | C34: =IF($A34="","",INDEX($C$181:$C$260,MATCH(ROW()-23,$G$181:$G$260,0))) -> 0.07027027 | D34: =IF($A34="","",INDEX($D$181:$D$260,MATCH(ROW()-23,$G$181:$G$260,0))) -> 0 | E34: =IF($A34="","",INDEX($E$181:$E$260,MATCH(ROW()-23,$G$181:$G$260,0))) -> 0 | F34: =IF($A34="","",INDEX($F$181:$F$260,MATCH(ROW()-23,$G$181:$G$260,0))) -> 0.07027027
A35: =IFERROR(INDEX($A$181:$A$260,MATCH(ROW()-23,$G$181:$G$260,0)),"") | B35: =IF($A35="","",INDEX($B$181:$B$260,MATCH(ROW()-23,$G$181:$G$260,0))) | C35: =IF($A35="","",INDEX($C$181:$C$260,MATCH(ROW()-23,$G$181:$G$260,0))) | D35: =IF($A35="","",INDEX($D$181:$D$260,MATCH(ROW()-23,$G$181:$G$260,0))) | E35: =IF($A35="","",INDEX($E$181:$E$260,MATCH(ROW()-23,$G$181:$G$260,0))) | F35: =IF($A35="","",INDEX($F$181:$F$260,MATCH(ROW()-23,$G$181:$G$260,0)))
... A63: =IFERROR(INDEX($A$181:$A$260,MATCH(ROW()-23,$G$181:$G$260,0)),"") | B63: =IF($A63="","",INDEX($B$181:$B$260,MATCH(ROW()-23,$G$181:$G$260,0))) | C63: =IF($A63="","",INDEX($C$181:$C$260,MATCH(ROW()-23,$G$181:$G$260,0))) | D63: =IF($A63="","",INDEX($D$181:$D$260,MATCH(ROW()-23,$G$181:$G$260,0))) | E63: =IF($A63="","",INDEX($E$181:$E$260,MATCH(ROW()-23,$G$181:$G$260,0))) | F63: =IF($A63="","",INDEX($F$181:$F$260,MATCH(ROW()-23,$G$181:$G$260,0)))
A64: ="TOTAL — "&COUNTIF($A$24:$A$63,"?*")&" project(s) with time booked" -> TOTAL — 11 project(s) with time booked | C64: =SUM(C24:C63) -> 5.7216216 | D64: =SUM(D24:D63) -> 5.9945946 | E64: =SUM(E24:E63) -> 6.1918919 | F64: =SUM(F24:F63) -> 17.908108
A179: Helper — actual MM by project and engineer for the selected period. Do not edit.
A180: Code | B180: Status | C180: Ahmed | D180: Osama | E180: Kirolos | F180: Total | G180: Rank
A181: =IF(Inputs!$A6="","",Inputs!$A6) -> N25178-0100D | B181: =IF($A181="","",Inputs!$F6) -> Active | C181: =IF($A181="",0,IF(Dashboard!$B$5="All Time",Phasing!$Y265,IF(Dashboard!$B$5="Year",SUMIF(Phasing!$E$3:$X$3,Dashboard!$D$5,Phasing!$E265:$X265),SUMIF(Phasing!$E$4:$X$4,Dashboard!$B$6,Phasing!$E265:$X265)))) -> 0 | D181: =IF($A181="",0,IF(Dashboard!$B$5="All Time",Phasing!$Y266,IF(Dashboard!$B$5="Year",SUMIF(Phasing!$E$3:$X$3,Dashboard!$D$5,Phasing!$E266:$X266),SUMIF(Phasing!$E$4:$X$4,Dashboard!$B$6,Phasing!$E266:$X266)))) -> 0 | E181: =IF($A181="",0,IF(Dashboard!$B$5="All Time",Phasing!$Y267,IF(Dashboard!$B$5="Year",SUMIF(Phasing!$E$3:$X$3,Dashboard!$D$5,Phasing!$E267:$X267),SUMIF(Phasing!$E$4:$X$4,Dashboard!$B$6,Phasing!$E267:$X267)))) -> 0 | F181: =SUM($C181:$E181) -> 0 | G181: =IF($F181<=0,"",COUNTIF($F$181:$F181,">0"))
A182: =IF(Inputs!$A7="","",Inputs!$A7) -> E26084-0100D | B182: =IF($A182="","",Inputs!$F7) -> Active | C182: =IF($A182="",0,IF(Dashboard!$B$5="All Time",Phasing!$Y268,IF(Dashboard!$B$5="Year",SUMIF(Phasing!$E$3:$X$3,Dashboard!$D$5,Phasing!$E268:$X268),SUMIF(Phasing!$E$4:$X$4,Dashboard!$B$6,Phasing!$E268:$X268)))) -> 0 | D182: =IF($A182="",0,IF(Dashboard!$B$5="All Time",Phasing!$Y269,IF(Dashboard!$B$5="Year",SUMIF(Phasing!$E$3:$X$3,Dashboard!$D$5,Phasing!$E269:$X269),SUMIF(Phasing!$E$4:$X$4,Dashboard!$B$6,Phasing!$E269:$X269)))) -> 0.22567568 | E182: =IF($A182="",0,IF(Dashboard!$B$5="All Time",Phasing!$Y270,IF(Dashboard!$B$5="Year",SUMIF(Phasing!$E$3:$X$3,Dashboard!$D$5,Phasing!$E270:$X270),SUMIF(Phasing!$E$4:$X$4,Dashboard!$B$6,Phasing!$E270:$X270)))) -> 0 | F182: =SUM($C182:$E182) -> 0.22567568 | G182: =IF($F182<=0,"",COUNTIF($F$181:$F182,">0")) -> 1
A183: =IF(Inputs!$A8="","",Inputs!$A8) -> N25185-0100D | B183: =IF($A183="","",Inputs!$F8) -> Active | C183: =IF($A183="",0,IF(Dashboard!$B$5="All Time",Phasing!$Y271,IF(Dashboard!$B$5="Year",SUMIF(Phasing!$E$3:$X$3,Dashboard!$D$5,Phasing!$E271:$X271),SUMIF(Phasing!$E$4:$X$4,Dashboard!$B$6,Phasing!$E271:$X271)))) -> 5.1 | D183: =IF($A183="",0,IF(Dashboard!$B$5="All Time",Phasing!$Y272,IF(Dashboard!$B$5="Year",SUMIF(Phasing!$E$3:$X$3,Dashboard!$D$5,Phasing!$E272:$X272),SUMIF(Phasing!$E$4:$X$4,Dashboard!$B$6,Phasing!$E272:$X272)))) -> 5.4189189 | E183: =IF($A183="",0,IF(Dashboard!$B$5="All Time",Phasing!$Y273,IF(Dashboard!$B$5="Year",SUMIF(Phasing!$E$3:$X$3,Dashboard!$D$5,Phasing!$E273:$X273),SUMIF(Phasing!$E$4:$X$4,Dashboard!$B$6,Phasing!$E273:$X273)))) -> 2.9986486 | F183: =SUM($C183:$E183) -> 13.517568 | G183: =IF($F183<=0,"",COUNTIF($F$181:$F183,">0")) -> 2
A184: =IF(Inputs!$A9="","",Inputs!$A9) -> AN22137-0100D | B184: =IF($A184="","",Inputs!$F9) -> Not Started | C184: =IF($A184="",0,IF(Dashboard!$B$5="All Time",Phasing!$Y274,IF(Dashboard!$B$5="Year",SUMIF(Phasing!$E$3:$X$3,Dashboard!$D$5,Phasing!$E274:$X274),SUMIF(Phasing!$E$4:$X$4,Dashboard!$B$6,Phasing!$E274:$X274)))) -> 0 | D184: =IF($A184="",0,IF(Dashboard!$B$5="All Time",Phasing!$Y275,IF(Dashboard!$B$5="Year",SUMIF(Phasing!$E$3:$X$3,Dashboard!$D$5,Phasing!$E275:$X275),SUMIF(Phasing!$E$4:$X$4,Dashboard!$B$6,Phasing!$E275:$X275)))) -> 0 | E184: =IF($A184="",0,IF(Dashboard!$B$5="All Time",Phasing!$Y276,IF(Dashboard!$B$5="Year",SUMIF(Phasing!$E$3:$X$3,Dashboard!$D$5,Phasing!$E276:$X276),SUMIF(Phasing!$E$4:$X$4,Dashboard!$B$6,Phasing!$E276:$X276)))) -> 0 | F184: =SUM($C184:$E184) -> 0 | G184: =IF($F184<=0,"",COUNTIF($F$181:$F184,">0"))
A185: =IF(Inputs!$A10="","",Inputs!$A10) -> D26058-0100D | B185: =IF($A185="","",Inputs!$F10) -> Not Started | C185: =IF($A185="",0,IF(Dashboard!$B$5="All Time",Phasing!$Y277,IF(Dashboard!$B$5="Year",SUMIF(Phasing!$E$3:$X$3,Dashboard!$D$5,Phasing!$E277:$X277),SUMIF(Phasing!$E$4:$X$4,Dashboard!$B$6,Phasing!$E277:$X277)))) -> 0 | D185: =IF($A185="",0,IF(Dashboard!$B$5="All Time",Phasing!$Y278,IF(Dashboard!$B$5="Year",SUMIF(Phasing!$E$3:$X$3,Dashboard!$D$5,Phasing!$E278:$X278),SUMIF(Phasing!$E$4:$X$4,Dashboard!$B$6,Phasing!$E278:$X278)))) -> 0 | E185: =IF($A185="",0,IF(Dashboard!$B$5="All Time",Phasing!$Y279,IF(Dashboard!$B$5="Year",SUMIF(Phasing!$E$3:$X$3,Dashboard!$D$5,Phasing!$E279:$X279),SUMIF(Phasing!$E$4:$X$4,Dashboard!$B$6,Phasing!$E279:$X279)))) -> 0 | F185: =SUM($C185:$E185) -> 0 | G185: =IF($F185<=0,"",COUNTIF($F$181:$F185,">0"))
A186: =IF(Inputs!$A11="","",Inputs!$A11) -> AD24217-0100D | B186: =IF($A186="","",Inputs!$F11) -> Finalized | C186: =IF($A186="",0,IF(Dashboard!$B$5="All Time",Phasing!$Y280,IF(Dashboard!$B$5="Year",SUMIF(Phasing!$E$3:$X$3,Dashboard!$D$5,Phasing!$E280:$X280),SUMIF(Phasing!$E$4:$X$4,Dashboard!$B$6,Phasing!$E280:$X280)))) -> 0 | D186: =IF($A186="",0,IF(Dashboard!$B$5="All Time",Phasing!$Y281,IF(Dashboard!$B$5="Year",SUMIF(Phasing!$E$3:$X$3,Dashboard!$D$5,Phasing!$E281:$X281),SUMIF(Phasing!$E$4:$X$4,Dashboard!$B$6,Phasing!$E281:$X281)))) -> 0 | E186: =IF($A186="",0,IF(Dashboard!$B$5="All Time",Phasing!$Y282,IF(Dashboard!$B$5="Year",SUMIF(Phasing!$E$3:$X$3,Dashboard!$D$5,Phasing!$E282:$X282),SUMIF(Phasing!$E$4:$X$4,Dashboard!$B$6,Phasing!$E282:$X282)))) -> 0 | F186: =SUM($C186:$E186) -> 0 | G186: =IF($F186<=0,"",COUNTIF($F$181:$F186,">0"))
A187: =IF(Inputs!$A12="","",Inputs!$A12) -> AN23207-0500D | B187: =IF($A187="","",Inputs!$F12) -> On Hold | C187: =IF($A187="",0,IF(Dashboard!$B$5="All Time",Phasing!$Y283,IF(Dashboard!$B$5="Year",SUMIF(Phasing!$E$3:$X$3,Dashboard!$D$5,Phasing!$E283:$X283),SUMIF(Phasing!$E$4:$X$4,Dashboard!$B$6,Phasing!$E283:$X283)))) -> 0 | D187: =IF($A187="",0,IF(Dashboard!$B$5="All Time",Phasing!$Y284,IF(Dashboard!$B$5="Year",SUMIF(Phasing!$E$3:$X$3,Dashboard!$D$5,Phasing!$E284:$X284),SUMIF(Phasing!$E$4:$X$4,Dashboard!$B$6,Phasing!$E284:$X284)))) -> 0 | E187: =IF($A187="",0,IF(Dashboard!$B$5="All Time",Phasing!$Y285,IF(Dashboard!$B$5="Year",SUMIF(Phasing!$E$3:$X$3,Dashboard!$D$5,Phasing!$E285:$X285),SUMIF(Phasing!$E$4:$X$4,Dashboard!$B$6,Phasing!$E285:$X285)))) -> 0 | F187: =SUM($C187:$E187) -> 0 | G187: =IF($F187<=0,"",COUNTIF($F$181:$F187,">0"))
A188: =IF(Inputs!$A13="","",Inputs!$A13) -> AN23276-0100D | B188: =IF($A188="","",Inputs!$F13) -> On Hold | C188: =IF($A188="",0,IF(Dashboard!$B$5="All Time",Phasing!$Y286,IF(Dashboard!$B$5="Year",SUMIF(Phasing!$E$3:$X$3,Dashboard!$D$5,Phasing!$E286:$X286),SUMIF(Phasing!$E$4:$X$4,Dashboard!$B$6,Phasing!$E286:$X286)))) -> 0 | D188: =IF($A188="",0,IF(Dashboard!$B$5="All Time",Phasing!$Y287,IF(Dashboard!$B$5="Year",SUMIF(Phasing!$E$3:$X$3,Dashboard!$D$5,Phasing!$E287:$X287),SUMIF(Phasing!$E$4:$X$4,Dashboard!$B$6,Phasing!$E287:$X287)))) -> 0 | E188: =IF($A188="",0,IF(Dashboard!$B$5="All Time",Phasing!$Y288,IF(Dashboard!$B$5="Year",SUMIF(Phasing!$E$3:$X$3,Dashboard!$D$5,Phasing!$E288:$X288),SUMIF(Phasing!$E$4:$X$4,Dashboard!$B$6,Phasing!$E288:$X288)))) -> 0 | F188: =SUM($C188:$E188) -> 0 | G188: =IF($F188<=0,"",COUNTIF($F$181:$F188,">0"))
A189: =IF(Inputs!$A14="","",Inputs!$A14) -> AN24073-0100D | B189: =IF($A189="","",Inputs!$F14) -> On Hold | C189: =IF($A189="",0,IF(Dashboard!$B$5="All Time",Phasing!$Y289,IF(Dashboard!$B$5="Year",SUMIF(Phasing!$E$3:$X$3,Dashboard!$D$5,Phasing!$E289:$X289),SUMIF(Phasing!$E$4:$X$4,Dashboard!$B$6,Phasing!$E289:$X289)))) -> 0 | D189: =IF($A189="",0,IF(Dashboard!$B$5="All Time",Phasing!$Y290,IF(Dashboard!$B$5="Year",SUMIF(Phasing!$E$3:$X$3,Dashboard!$D$5,Phasing!$E290:$X290),SUMIF(Phasing!$E$4:$X$4,Dashboard!$B$6,Phasing!$E290:$X290)))) -> 0 | E189: =IF($A189="",0,IF(Dashboard!$B$5="All Time",Phasing!$Y291,IF(Dashboard!$B$5="Year",SUMIF(Phasing!$E$3:$X$3,Dashboard!$D$5,Phasing!$E291:$X291),SUMIF(Phasing!$E$4:$X$4,Dashboard!$B$6,Phasing!$E291:$X291)))) -> 0 | F189: =SUM($C189:$E189) -> 0 | G189: =IF($F189<=0,"",COUNTIF($F$181:$F189,">0"))
A190: =IF(Inputs!$A15="","",Inputs!$A15) -> AN24140-0100R | B190: =IF($A190="","",Inputs!$F15) -> Active | C190: =IF($A190="",0,IF(Dashboard!$B$5="All Time",Phasing!$Y292,IF(Dashboard!$B$5="Year",SUMIF(Phasing!$E$3:$X$3,Dashboard!$D$5,Phasing!$E292:$X292),SUMIF(Phasing!$E$4:$X$4,Dashboard!$B$6,Phasing!$E292:$X292)))) -> 0 | D190: =IF($A190="",0,IF(Dashboard!$B$5="All Time",Phasing!$Y293,IF(Dashboard!$B$5="Year",SUMIF(Phasing!$E$3:$X$3,Dashboard!$D$5,Phasing!$E293:$X293),SUMIF(Phasing!$E$4:$X$4,Dashboard!$B$6,Phasing!$E293:$X293)))) -> 0 | E190: =IF($A190="",0,IF(Dashboard!$B$5="All Time",Phasing!$Y294,IF(Dashboard!$B$5="Year",SUMIF(Phasing!$E$3:$X$3,Dashboard!$D$5,Phasing!$E294:$X294),SUMIF(Phasing!$E$4:$X$4,Dashboard!$B$6,Phasing!$E294:$X294)))) -> 0.021621622 | F190: =SUM($C190:$E190) -> 0.021621622 | G190: =IF($F190<=0,"",COUNTIF($F$181:$F190,">0")) -> 3
A191: =IF(Inputs!$A16="","",Inputs!$A16) -> CS24035-0100D | B191: =IF($A191="","",Inputs!$F16) -> On Hold | C191: =IF($A191="",0,IF(Dashboard!$B$5="All Time",Phasing!$Y295,IF(Dashboard!$B$5="Year",SUMIF(Phasing!$E$3:$X$3,Dashboard!$D$5,Phasing!$E295:$X295),SUMIF(Phasing!$E$4:$X$4,Dashboard!$B$6,Phasing!$E295:$X295)))) -> 0.10675676 | D191: =IF($A191="",0,IF(Dashboard!$B$5="All Time",Phasing!$Y296,IF(Dashboard!$B$5="Year",SUMIF(Phasing!$E$3:$X$3,Dashboard!$D$5,Phasing!$E296:$X296),SUMIF(Phasing!$E$4:$X$4,Dashboard!$B$6,Phasing!$E296:$X296)))) -> 0 | E191: =IF($A191="",0,IF(Dashboard!$B$5="All Time",Phasing!$Y297,IF(Dashboard!$B$5="Year",SUMIF(Phasing!$E$3:$X$3,Dashboard!$D$5,Phasing!$E297:$X297),SUMIF(Phasing!$E$4:$X$4,Dashboard!$B$6,Phasing!$E297:$X297)))) -> 0.46351351 | F191: =SUM($C191:$E191) -> 0.57027027 | G191: =IF($F191<=0,"",COUNTIF($F$181:$F191,">0")) -> 4
A192: =IF(Inputs!$A17="","",Inputs!$A17) -> E24181-0100D | B192: =IF($A192="","",Inputs!$F17) -> Finalized | C192: =IF($A192="",0,IF(Dashboard!$B$5="All Time",Phasing!$Y298,IF(Dashboard!$B$5="Year",SUMIF(Phasing!$E$3:$X$3,Dashboard!$D$5,Phasing!$E298:$X298),SUMIF(Phasing!$E$4:$X$4,Dashboard!$B$6,Phasing!$E298:$X298)))) -> 0 | D192: =IF($A192="",0,IF(Dashboard!$B$5="All Time",Phasing!$Y299,IF(Dashboard!$B$5="Year",SUMIF(Phasing!$E$3:$X$3,Dashboard!$D$5,Phasing!$E299:$X299),SUMIF(Phasing!$E$4:$X$4,Dashboard!$B$6,Phasing!$E299:$X299)))) -> 0 | E192: =IF($A192="",0,IF(Dashboard!$B$5="All Time",Phasing!$Y300,IF(Dashboard!$B$5="Year",SUMIF(Phasing!$E$3:$X$3,Dashboard!$D$5,Phasing!$E300:$X300),SUMIF(Phasing!$E$4:$X$4,Dashboard!$B$6,Phasing!$E300:$X300)))) -> 0 | F192: =SUM($C192:$E192) -> 0 | G192: =IF($F192<=0,"",COUNTIF($F$181:$F192,">0"))
A193: =IF(Inputs!$A18="","",Inputs!$A18) -> J23152-0100D | B193: =IF($A193="","",Inputs!$F18) -> Finalized | C193: =IF($A193="",0,IF(Dashboard!$B$5="All Time",Phasing!$Y301,IF(Dashboard!$B$5="Year",SUMIF(Phasing!$E$3:$X$3,Dashboard!$D$5,Phasing!$E301:$X301),SUMIF(Phasing!$E$4:$X$4,Dashboard!$B$6,Phasing!$E301:$X301)))) -> 0 | D193: =IF($A193="",0,IF(Dashboard!$B$5="All Time",Phasing!$Y302,IF(Dashboard!$B$5="Year",SUMIF(Phasing!$E$3:$X$3,Dashboard!$D$5,Phasing!$E302:$X302),SUMIF(Phasing!$E$4:$X$4,Dashboard!$B$6,Phasing!$E302:$X302)))) -> 0 | E193: =IF($A193="",0,IF(Dashboard!$B$5="All Time",Phasing!$Y303,IF(Dashboard!$B$5="Year",SUMIF(Phasing!$E$3:$X$3,Dashboard!$D$5,Phasing!$E303:$X303),SUMIF(Phasing!$E$4:$X$4,Dashboard!$B$6,Phasing!$E303:$X303)))) -> 0 | F193: =SUM($C193:$E193) -> 0 | G193: =IF($F193<=0,"",COUNTIF($F$181:$F193,">0"))
A194: =IF(Inputs!$A19="","",Inputs!$A19) -> Q25008-0100D | B194: =IF($A194="","",Inputs!$F19) -> Finalized | C194: =IF($A194="",0,IF(Dashboard!$B$5="All Time",Phasing!$Y304,IF(Dashboard!$B$5="Year",SUMIF(Phasing!$E$3:$X$3,Dashboard!$D$5,Phasing!$E304:$X304),SUMIF(Phasing!$E$4:$X$4,Dashboard!$B$6,Phasing!$E304:$X304)))) -> 0.14594595 | D194: =IF($A194="",0,IF(Dashboard!$B$5="All Time",Phasing!$Y305,IF(Dashboard!$B$5="Year",SUMIF(Phasing!$E$3:$X$3,Dashboard!$D$5,Phasing!$E305:$X305),SUMIF(Phasing!$E$4:$X$4,Dashboard!$B$6,Phasing!$E305:$X305)))) -> 0 | E194: =IF($A194="",0,IF(Dashboard!$B$5="All Time",Phasing!$Y306,IF(Dashboard!$B$5="Year",SUMIF(Phasing!$E$3:$X$3,Dashboard!$D$5,Phasing!$E306:$X306),SUMIF(Phasing!$E$4:$X$4,Dashboard!$B$6,Phasing!$E306:$X306)))) -> 1.6675676 | F194: =SUM($C194:$E194) -> 1.8135135 | G194: =IF($F194<=0,"",COUNTIF($F$181:$F194,">0")) -> 5
A195: =IF(Inputs!$A20="","",Inputs!$A20) -> S24014-0101D | B195: =IF($A195="","",Inputs!$F20) -> Finalized | C195: =IF($A195="",0,IF(Dashboard!$B$5="All Time",Phasing!$Y307,IF(Dashboard!$B$5="Year",SUMIF(Phasing!$E$3:$X$3,Dashboard!$D$5,Phasing!$E307:$X307),SUMIF(Phasing!$E$4:$X$4,Dashboard!$B$6,Phasing!$E307:$X307)))) -> 0 | D195: =IF($A195="",0,IF(Dashboard!$B$5="All Time",Phasing!$Y308,IF(Dashboard!$B$5="Year",SUMIF(Phasing!$E$3:$X$3,Dashboard!$D$5,Phasing!$E308:$X308),SUMIF(Phasing!$E$4:$X$4,Dashboard!$B$6,Phasing!$E308:$X308)))) -> 0 | E195: =IF($A195="",0,IF(Dashboard!$B$5="All Time",Phasing!$Y309,IF(Dashboard!$B$5="Year",SUMIF(Phasing!$E$3:$X$3,Dashboard!$D$5,Phasing!$E309:$X309),SUMIF(Phasing!$E$4:$X$4,Dashboard!$B$6,Phasing!$E309:$X309)))) -> 0 | F195: =SUM($C195:$E195) -> 0 | G195: =IF($F195<=0,"",COUNTIF($F$181:$F195,">0"))
A196: =IF(Inputs!$A21="","",Inputs!$A21) -> S24014-0102D | B196: =IF($A196="","",Inputs!$F21) -> Finalized | C196: =IF($A196="",0,IF(Dashboard!$B$5="All Time",Phasing!$Y310,IF(Dashboard!$B$5="Year",SUMIF(Phasing!$E$3:$X$3,Dashboard!$D$5,Phasing!$E310:$X310),SUMIF(Phasing!$E$4:$X$4,Dashboard!$B$6,Phasing!$E310:$X310)))) -> 0 | D196: =IF($A196="",0,IF(Dashboard!$B$5="All Time",Phasing!$Y311,IF(Dashboard!$B$5="Year",SUMIF(Phasing!$E$3:$X$3,Dashboard!$D$5,Phasing!$E311:$X311),SUMIF(Phasing!$E$4:$X$4,Dashboard!$B$6,Phasing!$E311:$X311)))) -> 0 | E196: =IF($A196="",0,IF(Dashboard!$B$5="All Time",Phasing!$Y312,IF(Dashboard!$B$5="Year",SUMIF(Phasing!$E$3:$X$3,Dashboard!$D$5,Phasing!$E312:$X312),SUMIF(Phasing!$E$4:$X$4,Dashboard!$B$6,Phasing!$E312:$X312)))) -> 0 | F196: =SUM($C196:$E196) -> 0 | G196: =IF($F196<=0,"",COUNTIF($F$181:$F196,">0"))
A197: =IF(Inputs!$A22="","",Inputs!$A22) -> S24014-0103D | B197: =IF($A197="","",Inputs!$F22) -> Finalized | C197: =IF($A197="",0,IF(Dashboard!$B$5="All Time",Phasing!$Y313,IF(Dashboard!$B$5="Year",SUMIF(Phasing!$E$3:$X$3,Dashboard!$D$5,Phasing!$E313:$X313),SUMIF(Phasing!$E$4:$X$4,Dashboard!$B$6,Phasing!$E313:$X313)))) -> 0 | D197: =IF($A197="",0,IF(Dashboard!$B$5="All Time",Phasing!$Y314,IF(Dashboard!$B$5="Year",SUMIF(Phasing!$E$3:$X$3,Dashboard!$D$5,Phasing!$E314:$X314),SUMIF(Phasing!$E$4:$X$4,Dashboard!$B$6,Phasing!$E314:$X314)))) -> 0 | E197: =IF($A197="",0,IF(Dashboard!$B$5="All Time",Phasing!$Y315,IF(Dashboard!$B$5="Year",SUMIF(Phasing!$E$3:$X$3,Dashboard!$D$5,Phasing!$E315:$X315),SUMIF(Phasing!$E$4:$X$4,Dashboard!$B$6,Phasing!$E315:$X315)))) -> 0 | F197: =SUM($C197:$E197) -> 0 | G197: =IF($F197<=0,"",COUNTIF($F$181:$F197,">0"))
A198: =IF(Inputs!$A23="","",Inputs!$A23) -> S24014-0104D | B198: =IF($A198="","",Inputs!$F23) -> Finalized | C198: =IF($A198="",0,IF(Dashboard!$B$5="All Time",Phasing!$Y316,IF(Dashboard!$B$5="Year",SUMIF(Phasing!$E$3:$X$3,Dashboard!$D$5,Phasing!$E316:$X316),SUMIF(Phasing!$E$4:$X$4,Dashboard!$B$6,Phasing!$E316:$X316)))) -> 0 | D198: =IF($A198="",0,IF(Dashboard!$B$5="All Time",Phasing!$Y317,IF(Dashboard!$B$5="Year",SUMIF(Phasing!$E$3:$X$3,Dashboard!$D$5,Phasing!$E317:$X317),SUMIF(Phasing!$E$4:$X$4,Dashboard!$B$6,Phasing!$E317:$X317)))) -> 0 | E198: =IF($A198="",0,IF(Dashboard!$B$5="All Time",Phasing!$Y318,IF(Dashboard!$B$5="Year",SUMIF(Phasing!$E$3:$X$3,Dashboard!$D$5,Phasing!$E318:$X318),SUMIF(Phasing!$E$4:$X$4,Dashboard!$B$6,Phasing!$E318:$X318)))) -> 0 | F198: =SUM($C198:$E198) -> 0 | G198: =IF($F198<=0,"",COUNTIF($F$181:$F198,">0"))
A199: =IF(Inputs!$A24="","",Inputs!$A24) -> S22058-0700D | B199: =IF($A199="","",Inputs!$F24) -> Finalized | C199: =IF($A199="",0,IF(Dashboard!$B$5="All Time",Phasing!$Y319,IF(Dashboard!$B$5="Year",SUMIF(Phasing!$E$3:$X$3,Dashboard!$D$5,Phasing!$E319:$X319),SUMIF(Phasing!$E$4:$X$4,Dashboard!$B$6,Phasing!$E319:$X319)))) -> 0 | D199: =IF($A199="",0,IF(Dashboard!$B$5="All Time",Phasing!$Y320,IF(Dashboard!$B$5="Year",SUMIF(Phasing!$E$3:$X$3,Dashboard!$D$5,Phasing!$E320:$X320),SUMIF(Phasing!$E$4:$X$4,Dashboard!$B$6,Phasing!$E320:$X320)))) -> 0 | E199: =IF($A199="",0,IF(Dashboard!$B$5="All Time",Phasing!$Y321,IF(Dashboard!$B$5="Year",SUMIF(Phasing!$E$3:$X$3,Dashboard!$D$5,Phasing!$E321:$X321),SUMIF(Phasing!$E$4:$X$4,Dashboard!$B$6,Phasing!$E321:$X321)))) -> 0 | F199: =SUM($C199:$E199) -> 0 | G199: =IF($F199<=0,"",COUNTIF($F$181:$F199,">0"))
A200: =IF(Inputs!$A25="","",Inputs!$A25) -> AN24185-0100R | B200: =IF($A200="","",Inputs!$F25) -> Finalized | C200: =IF($A200="",0,IF(Dashboard!$B$5="All Time",Phasing!$Y322,IF(Dashboard!$B$5="Year",SUMIF(Phasing!$E$3:$X$3,Dashboard!$D$5,Phasing!$E322:$X322),SUMIF(Phasing!$E$4:$X$4,Dashboard!$B$6,Phasing!$E322:$X322)))) -> 0 | D200: =IF($A200="",0,IF(Dashboard!$B$5="All Time",Phasing!$Y323,IF(Dashboard!$B$5="Year",SUMIF(Phasing!$E$3:$X$3,Dashboard!$D$5,Phasing!$E323:$X323),SUMIF(Phasing!$E$4:$X$4,Dashboard!$B$6,Phasing!$E323:$X323)))) -> 0 | E200: =IF($A200="",0,IF(Dashboard!$B$5="All Time",Phasing!$Y324,IF(Dashboard!$B$5="Year",SUMIF(Phasing!$E$3:$X$3,Dashboard!$D$5,Phasing!$E324:$X324),SUMIF(Phasing!$E$4:$X$4,Dashboard!$B$6,Phasing!$E324:$X324)))) -> 0.13378378 | F200: =SUM($C200:$E200) -> 0.13378378 | G200: =IF($F200<=0,"",COUNTIF($F$181:$F200,">0")) -> 6
A201: =IF(Inputs!$A26="","",Inputs!$A26) -> AN24135-0100R | B201: =IF($A201="","",Inputs!$F26) -> On Hold | C201: =IF($A201="",0,IF(Dashboard!$B$5="All Time",Phasing!$Y325,IF(Dashboard!$B$5="Year",SUMIF(Phasing!$E$3:$X$3,Dashboard!$D$5,Phasing!$E325:$X325),SUMIF(Phasing!$E$4:$X$4,Dashboard!$B$6,Phasing!$E325:$X325)))) -> 0 | D201: =IF($A201="",0,IF(Dashboard!$B$5="All Time",Phasing!$Y326,IF(Dashboard!$B$5="Year",SUMIF(Phasing!$E$3:$X$3,Dashboard!$D$5,Phasing!$E326:$X326),SUMIF(Phasing!$E$4:$X$4,Dashboard!$B$6,Phasing!$E326:$X326)))) -> 0 | E201: =IF($A201="",0,IF(Dashboard!$B$5="All Time",Phasing!$Y327,IF(Dashboard!$B$5="Year",SUMIF(Phasing!$E$3:$X$3,Dashboard!$D$5,Phasing!$E327:$X327),SUMIF(Phasing!$E$4:$X$4,Dashboard!$B$6,Phasing!$E327:$X327)))) -> 0 | F201: =SUM($C201:$E201) -> 0 | G201: =IF($F201<=0,"",COUNTIF($F$181:$F201,">0"))
A202: =IF(Inputs!$A27="","",Inputs!$A27) -> AN23232-0100D | B202: =IF($A202="","",Inputs!$F27) -> Finalized | C202: =IF($A202="",0,IF(Dashboard!$B$5="All Time",Phasing!$Y328,IF(Dashboard!$B$5="Year",SUMIF(Phasing!$E$3:$X$3,Dashboard!$D$5,Phasing!$E328:$X328),SUMIF(Phasing!$E$4:$X$4,Dashboard!$B$6,Phasing!$E328:$X328)))) -> 0 | D202: =IF($A202="",0,IF(Dashboard!$B$5="All Time",Phasing!$Y329,IF(Dashboard!$B$5="Year",SUMIF(Phasing!$E$3:$X$3,Dashboard!$D$5,Phasing!$E329:$X329),SUMIF(Phasing!$E$4:$X$4,Dashboard!$B$6,Phasing!$E329:$X329)))) -> 0 | E202: =IF($A202="",0,IF(Dashboard!$B$5="All Time",Phasing!$Y330,IF(Dashboard!$B$5="Year",SUMIF(Phasing!$E$3:$X$3,Dashboard!$D$5,Phasing!$E330:$X330),SUMIF(Phasing!$E$4:$X$4,Dashboard!$B$6,Phasing!$E330:$X330)))) -> 0 | F202: =SUM($C202:$E202) -> 0 | G202: =IF($F202<=0,"",COUNTIF($F$181:$F202,">0"))
A203: =IF(Inputs!$A28="","",Inputs!$A28) -> AN23108-0100R | B203: =IF($A203="","",Inputs!$F28) -> On Hold | C203: =IF($A203="",0,IF(Dashboard!$B$5="All Time",Phasing!$Y331,IF(Dashboard!$B$5="Year",SUMIF(Phasing!$E$3:$X$3,Dashboard!$D$5,Phasing!$E331:$X331),SUMIF(Phasing!$E$4:$X$4,Dashboard!$B$6,Phasing!$E331:$X331)))) -> 0 | D203: =IF($A203="",0,IF(Dashboard!$B$5="All Time",Phasing!$Y332,IF(Dashboard!$B$5="Year",SUMIF(Phasing!$E$3:$X$3,Dashboard!$D$5,Phasing!$E332:$X332),SUMIF(Phasing!$E$4:$X$4,Dashboard!$B$6,Phasing!$E332:$X332)))) -> 0 | E203: =IF($A203="",0,IF(Dashboard!$B$5="All Time",Phasing!$Y333,IF(Dashboard!$B$5="Year",SUMIF(Phasing!$E$3:$X$3,Dashboard!$D$5,Phasing!$E333:$X333),SUMIF(Phasing!$E$4:$X$4,Dashboard!$B$6,Phasing!$E333:$X333)))) -> 0.68513514 | F203: =SUM($C203:$E203) -> 0.68513514 | G203: =IF($F203<=0,"",COUNTIF($F$181:$F203,">0")) -> 7
A204: =IF(Inputs!$A29="","",Inputs!$A29) -> TA24246-0200R | B204: =IF($A204="","",Inputs!$F29) -> On Hold | C204: =IF($A204="",0,IF(Dashboard!$B$5="All Time",Phasing!$Y334,IF(Dashboard!$B$5="Year",SUMIF(Phasing!$E$3:$X$3,Dashboard!$D$5,Phasing!$E334:$X334),SUMIF(Phasing!$E$4:$X$4,Dashboard!$B$6,Phasing!$E334:$X334)))) -> 0 | D204: =IF($A204="",0,IF(Dashboard!$B$5="All Time",Phasing!$Y335,IF(Dashboard!$B$5="Year",SUMIF(Phasing!$E$3:$X$3,Dashboard!$D$5,Phasing!$E335:$X335),SUMIF(Phasing!$E$4:$X$4,Dashboard!$B$6,Phasing!$E335:$X335)))) -> 0.098648649 | E204: =IF($A204="",0,IF(Dashboard!$B$5="All Time",Phasing!$Y336,IF(Dashboard!$B$5="Year",SUMIF(Phasing!$E$3:$X$3,Dashboard!$D$5,Phasing!$E336:$X336),SUMIF(Phasing!$E$4:$X$4,Dashboard!$B$6,Phasing!$E336:$X336)))) -> 0 | F204: =SUM($C204:$E204) -> 0.098648649 | G204: =IF($F204<=0,"",COUNTIF($F$181:$F204,">0")) -> 8
A205: =IF(Inputs!$A30="","",Inputs!$A30) -> S22058-0900D | B205: =IF($A205="","",Inputs!$F30) -> Cancelled | C205: =IF($A205="",0,IF(Dashboard!$B$5="All Time",Phasing!$Y337,IF(Dashboard!$B$5="Year",SUMIF(Phasing!$E$3:$X$3,Dashboard!$D$5,Phasing!$E337:$X337),SUMIF(Phasing!$E$4:$X$4,Dashboard!$B$6,Phasing!$E337:$X337)))) -> 0 | D205: =IF($A205="",0,IF(Dashboard!$B$5="All Time",Phasing!$Y338,IF(Dashboard!$B$5="Year",SUMIF(Phasing!$E$3:$X$3,Dashboard!$D$5,Phasing!$E338:$X338),SUMIF(Phasing!$E$4:$X$4,Dashboard!$B$6,Phasing!$E338:$X338)))) -> 0 | E205: =IF($A205="",0,IF(Dashboard!$B$5="All Time",Phasing!$Y339,IF(Dashboard!$B$5="Year",SUMIF(Phasing!$E$3:$X$3,Dashboard!$D$5,Phasing!$E339:$X339),SUMIF(Phasing!$E$4:$X$4,Dashboard!$B$6,Phasing!$E339:$X339)))) -> 0 | F205: =SUM($C205:$E205) -> 0 | G205: =IF($F205<=0,"",COUNTIF($F$181:$F205,">0"))
A206: =IF(Inputs!$A31="","",Inputs!$A31) -> S22058-0400D | B206: =IF($A206="","",Inputs!$F31) -> Finalized | C206: =IF($A206="",0,IF(Dashboard!$B$5="All Time",Phasing!$Y340,IF(Dashboard!$B$5="Year",SUMIF(Phasing!$E$3:$X$3,Dashboard!$D$5,Phasing!$E340:$X340),SUMIF(Phasing!$E$4:$X$4,Dashboard!$B$6,Phasing!$E340:$X340)))) -> 0 | D206: =IF($A206="",0,IF(Dashboard!$B$5="All Time",Phasing!$Y341,IF(Dashboard!$B$5="Year",SUMIF(Phasing!$E$3:$X$3,Dashboard!$D$5,Phasing!$E341:$X341),SUMIF(Phasing!$E$4:$X$4,Dashboard!$B$6,Phasing!$E341:$X341)))) -> 0 | E206: =IF($A206="",0,IF(Dashboard!$B$5="All Time",Phasing!$Y342,IF(Dashboard!$B$5="Year",SUMIF(Phasing!$E$3:$X$3,Dashboard!$D$5,Phasing!$E342:$X342),SUMIF(Phasing!$E$4:$X$4,Dashboard!$B$6,Phasing!$E342:$X342)))) -> 0 | F206: =SUM($C206:$E206) -> 0 | G206: =IF($F206<=0,"",COUNTIF($F$181:$F206,">0"))
A207: =IF(Inputs!$A32="","",Inputs!$A32) -> Proposals 25 | B207: =IF($A207="","",Inputs!$F32) -> Finalized | C207: =IF($A207="",0,IF(Dashboard!$B$5="All Time",Phasing!$Y343,IF(Dashboard!$B$5="Year",SUMIF(Phasing!$E$3:$X$3,Dashboard!$D$5,Phasing!$E343:$X343),SUMIF(Phasing!$E$4:$X$4,Dashboard!$B$6,Phasing!$E343:$X343)))) -> 0 | D207: =IF($A207="",0,IF(Dashboard!$B$5="All Time",Phasing!$Y344,IF(Dashboard!$B$5="Year",SUMIF(Phasing!$E$3:$X$3,Dashboard!$D$5,Phasing!$E344:$X344),SUMIF(Phasing!$E$4:$X$4,Dashboard!$B$6,Phasing!$E344:$X344)))) -> 0 | E207: =IF($A207="",0,IF(Dashboard!$B$5="All Time",Phasing!$Y345,IF(Dashboard!$B$5="Year",SUMIF(Phasing!$E$3:$X$3,Dashboard!$D$5,Phasing!$E345:$X345),SUMIF(Phasing!$E$4:$X$4,Dashboard!$B$6,Phasing!$E345:$X345)))) -> 0 | F207: =SUM($C207:$E207) -> 0 | G207: =IF($F207<=0,"",COUNTIF($F$181:$F207,">0"))
A208: =IF(Inputs!$A33="","",Inputs!$A33) -> Chargable Proposals 25 | B208: =IF($A208="","",Inputs!$F33) -> Finalized | C208: =IF($A208="",0,IF(Dashboard!$B$5="All Time",Phasing!$Y346,IF(Dashboard!$B$5="Year",SUMIF(Phasing!$E$3:$X$3,Dashboard!$D$5,Phasing!$E346:$X346),SUMIF(Phasing!$E$4:$X$4,Dashboard!$B$6,Phasing!$E346:$X346)))) -> 0 | D208: =IF($A208="",0,IF(Dashboard!$B$5="All Time",Phasing!$Y347,IF(Dashboard!$B$5="Year",SUMIF(Phasing!$E$3:$X$3,Dashboard!$D$5,Phasing!$E347:$X347),SUMIF(Phasing!$E$4:$X$4,Dashboard!$B$6,Phasing!$E347:$X347)))) -> 0 | E208: =IF($A208="",0,IF(Dashboard!$B$5="All Time",Phasing!$Y348,IF(Dashboard!$B$5="Year",SUMIF(Phasing!$E$3:$X$3,Dashboard!$D$5,Phasing!$E348:$X348),SUMIF(Phasing!$E$4:$X$4,Dashboard!$B$6,Phasing!$E348:$X348)))) -> 0 | F208: =SUM($C208:$E208) -> 0 | G208: =IF($F208<=0,"",COUNTIF($F$181:$F208,">0"))
A209: =IF(Inputs!$A34="","",Inputs!$A34) -> AD23051-0101D | B209: =IF($A209="","",Inputs!$F34) -> Cancelled | C209: =IF($A209="",0,IF(Dashboard!$B$5="All Time",Phasing!$Y349,IF(Dashboard!$B$5="Year",SUMIF(Phasing!$E$3:$X$3,Dashboard!$D$5,Phasing!$E349:$X349),SUMIF(Phasing!$E$4:$X$4,Dashboard!$B$6,Phasing!$E349:$X349)))) -> 0 | D209: =IF($A209="",0,IF(Dashboard!$B$5="All Time",Phasing!$Y350,IF(Dashboard!$B$5="Year",SUMIF(Phasing!$E$3:$X$3,Dashboard!$D$5,Phasing!$E350:$X350),SUMIF(Phasing!$E$4:$X$4,Dashboard!$B$6,Phasing!$E350:$X350)))) -> 0 | E209: =IF($A209="",0,IF(Dashboard!$B$5="All Time",Phasing!$Y351,IF(Dashboard!$B$5="Year",SUMIF(Phasing!$E$3:$X$3,Dashboard!$D$5,Phasing!$E351:$X351),SUMIF(Phasing!$E$4:$X$4,Dashboard!$B$6,Phasing!$E351:$X351)))) -> 0 | F209: =SUM($C209:$E209) -> 0 | G209: =IF($F209<=0,"",COUNTIF($F$181:$F209,">0"))
A210: =IF(Inputs!$A35="","",Inputs!$A35) -> AN21146-0100R | B210: =IF($A210="","",Inputs!$F35) -> Finalized | C210: =IF($A210="",0,IF(Dashboard!$B$5="All Time",Phasing!$Y352,IF(Dashboard!$B$5="Year",SUMIF(Phasing!$E$3:$X$3,Dashboard!$D$5,Phasing!$E352:$X352),SUMIF(Phasing!$E$4:$X$4,Dashboard!$B$6,Phasing!$E352:$X352)))) -> 0 | D210: =IF($A210="",0,IF(Dashboard!$B$5="All Time",Phasing!$Y353,IF(Dashboard!$B$5="Year",SUMIF(Phasing!$E$3:$X$3,Dashboard!$D$5,Phasing!$E353:$X353),SUMIF(Phasing!$E$4:$X$4,Dashboard!$B$6,Phasing!$E353:$X353)))) -> 0 | E210: =IF($A210="",0,IF(Dashboard!$B$5="All Time",Phasing!$Y354,IF(Dashboard!$B$5="Year",SUMIF(Phasing!$E$3:$X$3,Dashboard!$D$5,Phasing!$E354:$X354),SUMIF(Phasing!$E$4:$X$4,Dashboard!$B$6,Phasing!$E354:$X354)))) -> 0 | F210: =SUM($C210:$E210) -> 0 | G210: =IF($F210<=0,"",COUNTIF($F$181:$F210,">0"))
A211: =IF(Inputs!$A36="","",Inputs!$A36) -> N23106-0100D | B211: =IF($A211="","",Inputs!$F36) -> Finalized | C211: =IF($A211="",0,IF(Dashboard!$B$5="All Time",Phasing!$Y355,IF(Dashboard!$B$5="Year",SUMIF(Phasing!$E$3:$X$3,Dashboard!$D$5,Phasing!$E355:$X355),SUMIF(Phasing!$E$4:$X$4,Dashboard!$B$6,Phasing!$E355:$X355)))) -> 0.18918919 | D211: =IF($A211="",0,IF(Dashboard!$B$5="All Time",Phasing!$Y356,IF(Dashboard!$B$5="Year",SUMIF(Phasing!$E$3:$X$3,Dashboard!$D$5,Phasing!$E356:$X356),SUMIF(Phasing!$E$4:$X$4,Dashboard!$B$6,Phasing!$E356:$X356)))) -> 0.25135135 | E211: =IF($A211="",0,IF(Dashboard!$B$5="All Time",Phasing!$Y357,IF(Dashboard!$B$5="Year",SUMIF(Phasing!$E$3:$X$3,Dashboard!$D$5,Phasing!$E357:$X357),SUMIF(Phasing!$E$4:$X$4,Dashboard!$B$6,Phasing!$E357:$X357)))) -> 0 | F211: =SUM($C211:$E211) -> 0.44054054 | G211: =IF($F211<=0,"",COUNTIF($F$181:$F211,">0")) -> 9
A212: =IF(Inputs!$A37="","",Inputs!$A37) -> OM23030-0100D | B212: =IF($A212="","",Inputs!$F37) -> Finalized | C212: =IF($A212="",0,IF(Dashboard!$B$5="All Time",Phasing!$Y358,IF(Dashboard!$B$5="Year",SUMIF(Phasing!$E$3:$X$3,Dashboard!$D$5,Phasing!$E358:$X358),SUMIF(Phasing!$E$4:$X$4,Dashboard!$B$6,Phasing!$E358:$X358)))) -> 0 | D212: =IF($A212="",0,IF(Dashboard!$B$5="All Time",Phasing!$Y359,IF(Dashboard!$B$5="Year",SUMIF(Phasing!$E$3:$X$3,Dashboard!$D$5,Phasing!$E359:$X359),SUMIF(Phasing!$E$4:$X$4,Dashboard!$B$6,Phasing!$E359:$X359)))) -> 0 | E212: =IF($A212="",0,IF(Dashboard!$B$5="All Time",Phasing!$Y360,IF(Dashboard!$B$5="Year",SUMIF(Phasing!$E$3:$X$3,Dashboard!$D$5,Phasing!$E360:$X360),SUMIF(Phasing!$E$4:$X$4,Dashboard!$B$6,Phasing!$E360:$X360)))) -> 0 | F212: =SUM($C212:$E212) -> 0 | G212: =IF($F212<=0,"",COUNTIF($F$181:$F212,">0"))
A213: =IF(Inputs!$A38="","",Inputs!$A38) -> Chargable Proposals 24 | B213: =IF($A213="","",Inputs!$F38) -> Finalized | C213: =IF($A213="",0,IF(Dashboard!$B$5="All Time",Phasing!$Y361,IF(Dashboard!$B$5="Year",SUMIF(Phasing!$E$3:$X$3,Dashboard!$D$5,Phasing!$E361:$X361),SUMIF(Phasing!$E$4:$X$4,Dashboard!$B$6,Phasing!$E361:$X361)))) -> 0 | D213: =IF($A213="",0,IF(Dashboard!$B$5="All Time",Phasing!$Y362,IF(Dashboard!$B$5="Year",SUMIF(Phasing!$E$3:$X$3,Dashboard!$D$5,Phasing!$E362:$X362),SUMIF(Phasing!$E$4:$X$4,Dashboard!$B$6,Phasing!$E362:$X362)))) -> 0 | E213: =IF($A213="",0,IF(Dashboard!$B$5="All Time",Phasing!$Y363,IF(Dashboard!$B$5="Year",SUMIF(Phasing!$E$3:$X$3,Dashboard!$D$5,Phasing!$E363:$X363),SUMIF(Phasing!$E$4:$X$4,Dashboard!$B$6,Phasing!$E363:$X363)))) -> 0 | F213: =SUM($C213:$E213) -> 0 | G213: =IF($F213<=0,"",COUNTIF($F$181:$F213,">0"))
A214: =IF(Inputs!$A39="","",Inputs!$A39) -> Proposals 24 | B214: =IF($A214="","",Inputs!$F39) -> Finalized | C214: =IF($A214="",0,IF(Dashboard!$B$5="All Time",Phasing!$Y364,IF(Dashboard!$B$5="Year",SUMIF(Phasing!$E$3:$X$3,Dashboard!$D$5,Phasing!$E364:$X364),SUMIF(Phasing!$E$4:$X$4,Dashboard!$B$6,Phasing!$E364:$X364)))) -> 0 | D214: =IF($A214="",0,IF(Dashboard!$B$5="All Time",Phasing!$Y365,IF(Dashboard!$B$5="Year",SUMIF(Phasing!$E$3:$X$3,Dashboard!$D$5,Phasing!$E365:$X365),SUMIF(Phasing!$E$4:$X$4,Dashboard!$B$6,Phasing!$E365:$X365)))) -> 0 | E214: =IF($A214="",0,IF(Dashboard!$B$5="All Time",Phasing!$Y366,IF(Dashboard!$B$5="Year",SUMIF(Phasing!$E$3:$X$3,Dashboard!$D$5,Phasing!$E366:$X366),SUMIF(Phasing!$E$4:$X$4,Dashboard!$B$6,Phasing!$E366:$X366)))) -> 0 | F214: =SUM($C214:$E214) -> 0 | G214: =IF($F214<=0,"",COUNTIF($F$181:$F214,">0"))
A215: =IF(Inputs!$A40="","",Inputs!$A40) -> S23204-0100D | B215: =IF($A215="","",Inputs!$F40) -> Finalized | C215: =IF($A215="",0,IF(Dashboard!$B$5="All Time",Phasing!$Y367,IF(Dashboard!$B$5="Year",SUMIF(Phasing!$E$3:$X$3,Dashboard!$D$5,Phasing!$E367:$X367),SUMIF(Phasing!$E$4:$X$4,Dashboard!$B$6,Phasing!$E367:$X367)))) -> 0 | D215: =IF($A215="",0,IF(Dashboard!$B$5="All Time",Phasing!$Y368,IF(Dashboard!$B$5="Year",SUMIF(Phasing!$E$3:$X$3,Dashboard!$D$5,Phasing!$E368:$X368),SUMIF(Phasing!$E$4:$X$4,Dashboard!$B$6,Phasing!$E368:$X368)))) -> 0 | E215: =IF($A215="",0,IF(Dashboard!$B$5="All Time",Phasing!$Y369,IF(Dashboard!$B$5="Year",SUMIF(Phasing!$E$3:$X$3,Dashboard!$D$5,Phasing!$E369:$X369),SUMIF(Phasing!$E$4:$X$4,Dashboard!$B$6,Phasing!$E369:$X369)))) -> 0 | F215: =SUM($C215:$E215) -> 0 | G215: =IF($F215<=0,"",COUNTIF($F$181:$F215,">0"))
A216: =IF(Inputs!$A41="","",Inputs!$A41) -> S24100-0100D | B216: =IF($A216="","",Inputs!$F41) -> Finalized | C216: =IF($A216="",0,IF(Dashboard!$B$5="All Time",Phasing!$Y370,IF(Dashboard!$B$5="Year",SUMIF(Phasing!$E$3:$X$3,Dashboard!$D$5,Phasing!$E370:$X370),SUMIF(Phasing!$E$4:$X$4,Dashboard!$B$6,Phasing!$E370:$X370)))) -> 0 | D216: =IF($A216="",0,IF(Dashboard!$B$5="All Time",Phasing!$Y371,IF(Dashboard!$B$5="Year",SUMIF(Phasing!$E$3:$X$3,Dashboard!$D$5,Phasing!$E371:$X371),SUMIF(Phasing!$E$4:$X$4,Dashboard!$B$6,Phasing!$E371:$X371)))) -> 0 | E216: =IF($A216="",0,IF(Dashboard!$B$5="All Time",Phasing!$Y372,IF(Dashboard!$B$5="Year",SUMIF(Phasing!$E$3:$X$3,Dashboard!$D$5,Phasing!$E372:$X372),SUMIF(Phasing!$E$4:$X$4,Dashboard!$B$6,Phasing!$E372:$X372)))) -> 0 | F216: =SUM($C216:$E216) -> 0 | G216: =IF($F216<=0,"",COUNTIF($F$181:$F216,">0"))
A217: =IF(Inputs!$A42="","",Inputs!$A42) -> TA23011-0100R | B217: =IF($A217="","",Inputs!$F42) -> Finalized | C217: =IF($A217="",0,IF(Dashboard!$B$5="All Time",Phasing!$Y373,IF(Dashboard!$B$5="Year",SUMIF(Phasing!$E$3:$X$3,Dashboard!$D$5,Phasing!$E373:$X373),SUMIF(Phasing!$E$4:$X$4,Dashboard!$B$6,Phasing!$E373:$X373)))) -> 0 | D217: =IF($A217="",0,IF(Dashboard!$B$5="All Time",Phasing!$Y374,IF(Dashboard!$B$5="Year",SUMIF(Phasing!$E$3:$X$3,Dashboard!$D$5,Phasing!$E374:$X374),SUMIF(Phasing!$E$4:$X$4,Dashboard!$B$6,Phasing!$E374:$X374)))) -> 0 | E217: =IF($A217="",0,IF(Dashboard!$B$5="All Time",Phasing!$Y375,IF(Dashboard!$B$5="Year",SUMIF(Phasing!$E$3:$X$3,Dashboard!$D$5,Phasing!$E375:$X375),SUMIF(Phasing!$E$4:$X$4,Dashboard!$B$6,Phasing!$E375:$X375)))) -> 0 | F217: =SUM($C217:$E217) -> 0 | G217: =IF($F217<=0,"",COUNTIF($F$181:$F217,">0"))
A218: =IF(Inputs!$A43="","",Inputs!$A43) -> AL25148-0100D | B218: =IF($A218="","",Inputs!$F43) -> Not Started | C218: =IF($A218="",0,IF(Dashboard!$B$5="All Time",Phasing!$Y376,IF(Dashboard!$B$5="Year",SUMIF(Phasing!$E$3:$X$3,Dashboard!$D$5,Phasing!$E376:$X376),SUMIF(Phasing!$E$4:$X$4,Dashboard!$B$6,Phasing!$E376:$X376)))) -> 0 | D218: =IF($A218="",0,IF(Dashboard!$B$5="All Time",Phasing!$Y377,IF(Dashboard!$B$5="Year",SUMIF(Phasing!$E$3:$X$3,Dashboard!$D$5,Phasing!$E377:$X377),SUMIF(Phasing!$E$4:$X$4,Dashboard!$B$6,Phasing!$E377:$X377)))) -> 0 | E218: =IF($A218="",0,IF(Dashboard!$B$5="All Time",Phasing!$Y378,IF(Dashboard!$B$5="Year",SUMIF(Phasing!$E$3:$X$3,Dashboard!$D$5,Phasing!$E378:$X378),SUMIF(Phasing!$E$4:$X$4,Dashboard!$B$6,Phasing!$E378:$X378)))) -> 0 | F218: =SUM($C218:$E218) -> 0 | G218: =IF($F218<=0,"",COUNTIF($F$181:$F218,">0"))
A219: =IF(Inputs!$A44="","",Inputs!$A44) -> Chargable Proposals 26 | B219: =IF($A219="","",Inputs!$F44) -> Active | C219: =IF($A219="",0,IF(Dashboard!$B$5="All Time",Phasing!$Y379,IF(Dashboard!$B$5="Year",SUMIF(Phasing!$E$3:$X$3,Dashboard!$D$5,Phasing!$E379:$X379),SUMIF(Phasing!$E$4:$X$4,Dashboard!$B$6,Phasing!$E379:$X379)))) -> 0.10945946 | D219: =IF($A219="",0,IF(Dashboard!$B$5="All Time",Phasing!$Y380,IF(Dashboard!$B$5="Year",SUMIF(Phasing!$E$3:$X$3,Dashboard!$D$5,Phasing!$E380:$X380),SUMIF(Phasing!$E$4:$X$4,Dashboard!$B$6,Phasing!$E380:$X380)))) -> 0 | E219: =IF($A219="",0,IF(Dashboard!$B$5="All Time",Phasing!$Y381,IF(Dashboard!$B$5="Year",SUMIF(Phasing!$E$3:$X$3,Dashboard!$D$5,Phasing!$E381:$X381),SUMIF(Phasing!$E$4:$X$4,Dashboard!$B$6,Phasing!$E381:$X381)))) -> 0.22162162 | F219: =SUM($C219:$E219) -> 0.33108108 | G219: =IF($F219<=0,"",COUNTIF($F$181:$F219,">0")) -> 10
A220: =IF(Inputs!$A45="","",Inputs!$A45) | B220: =IF($A220="","",Inputs!$F45) | C220: =IF($A220="",0,IF(Dashboard!$B$5="All Time",Phasing!$Y382,IF(Dashboard!$B$5="Year",SUMIF(Phasing!$E$3:$X$3,Dashboard!$D$5,Phasing!$E382:$X382),SUMIF(Phasing!$E$4:$X$4,Dashboard!$B$6,Phasing!$E382:$X382)))) -> 0 | D220: =IF($A220="",0,IF(Dashboard!$B$5="All Time",Phasing!$Y383,IF(Dashboard!$B$5="Year",SUMIF(Phasing!$E$3:$X$3,Dashboard!$D$5,Phasing!$E383:$X383),SUMIF(Phasing!$E$4:$X$4,Dashboard!$B$6,Phasing!$E383:$X383)))) -> 0 | E220: =IF($A220="",0,IF(Dashboard!$B$5="All Time",Phasing!$Y384,IF(Dashboard!$B$5="Year",SUMIF(Phasing!$E$3:$X$3,Dashboard!$D$5,Phasing!$E384:$X384),SUMIF(Phasing!$E$4:$X$4,Dashboard!$B$6,Phasing!$E384:$X384)))) -> 0 | F220: =SUM($C220:$E220) -> 0 | G220: =IF($F220<=0,"",COUNTIF($F$181:$F220,">0"))
A221: =IF(Inputs!$A46="","",Inputs!$A46) -> Proposals 26 | B221: =IF($A221="","",Inputs!$F46) -> Active | C221: =IF($A221="",0,IF(Dashboard!$B$5="All Time",Phasing!$Y385,IF(Dashboard!$B$5="Year",SUMIF(Phasing!$E$3:$X$3,Dashboard!$D$5,Phasing!$E385:$X385),SUMIF(Phasing!$E$4:$X$4,Dashboard!$B$6,Phasing!$E385:$X385)))) -> 0.07027027 | D221: =IF($A221="",0,IF(Dashboard!$B$5="All Time",Phasing!$Y386,IF(Dashboard!$B$5="Year",SUMIF(Phasing!$E$3:$X$3,Dashboard!$D$5,Phasing!$E386:$X386),SUMIF(Phasing!$E$4:$X$4,Dashboard!$B$6,Phasing!$E386:$X386)))) -> 0 | E221: =IF($A221="",0,IF(Dashboard!$B$5="All Time",Phasing!$Y387,IF(Dashboard!$B$5="Year",SUMIF(Phasing!$E$3:$X$3,Dashboard!$D$5,Phasing!$E387:$X387),SUMIF(Phasing!$E$4:$X$4,Dashboard!$B$6,Phasing!$E387:$X387)))) -> 0 | F221: =SUM($C221:$E221) -> 0.07027027 | G221: =IF($F221<=0,"",COUNTIF($F$181:$F221,">0")) -> 11
A222: =IF(Inputs!$A47="","",Inputs!$A47) | B222: =IF($A222="","",Inputs!$F47) | C222: =IF($A222="",0,IF(Dashboard!$B$5="All Time",Phasing!$Y388,IF(Dashboard!$B$5="Year",SUMIF(Phasing!$E$3:$X$3,Dashboard!$D$5,Phasing!$E388:$X388),SUMIF(Phasing!$E$4:$X$4,Dashboard!$B$6,Phasing!$E388:$X388)))) -> 0 | D222: =IF($A222="",0,IF(Dashboard!$B$5="All Time",Phasing!$Y389,IF(Dashboard!$B$5="Year",SUMIF(Phasing!$E$3:$X$3,Dashboard!$D$5,Phasing!$E389:$X389),SUMIF(Phasing!$E$4:$X$4,Dashboard!$B$6,Phasing!$E389:$X389)))) -> 0 | E222: =IF($A222="",0,IF(Dashboard!$B$5="All Time",Phasing!$Y390,IF(Dashboard!$B$5="Year",SUMIF(Phasing!$E$3:$X$3,Dashboard!$D$5,Phasing!$E390:$X390),SUMIF(Phasing!$E$4:$X$4,Dashboard!$B$6,Phasing!$E390:$X390)))) -> 0 | F222: =SUM($C222:$E222) -> 0 | G222: =IF($F222<=0,"",COUNTIF($F$181:$F222,">0"))
A223: =IF(Inputs!$A48="","",Inputs!$A48) | B223: =IF($A223="","",Inputs!$F48) | C223: =IF($A223="",0,IF(Dashboard!$B$5="All Time",Phasing!$Y391,IF(Dashboard!$B$5="Year",SUMIF(Phasing!$E$3:$X$3,Dashboard!$D$5,Phasing!$E391:$X391),SUMIF(Phasing!$E$4:$X$4,Dashboard!$B$6,Phasing!$E391:$X391)))) -> 0 | D223: =IF($A223="",0,IF(Dashboard!$B$5="All Time",Phasing!$Y392,IF(Dashboard!$B$5="Year",SUMIF(Phasing!$E$3:$X$3,Dashboard!$D$5,Phasing!$E392:$X392),SUMIF(Phasing!$E$4:$X$4,Dashboard!$B$6,Phasing!$E392:$X392)))) -> 0 | E223: =IF($A223="",0,IF(Dashboard!$B$5="All Time",Phasing!$Y393,IF(Dashboard!$B$5="Year",SUMIF(Phasing!$E$3:$X$3,Dashboard!$D$5,Phasing!$E393:$X393),SUMIF(Phasing!$E$4:$X$4,Dashboard!$B$6,Phasing!$E393:$X393)))) -> 0 | F223: =SUM($C223:$E223) -> 0 | G223: =IF($F223<=0,"",COUNTIF($F$181:$F223,">0"))
A224: =IF(Inputs!$A49="","",Inputs!$A49) | B224: =IF($A224="","",Inputs!$F49) | C224: =IF($A224="",0,IF(Dashboard!$B$5="All Time",Phasing!$Y394,IF(Dashboard!$B$5="Year",SUMIF(Phasing!$E$3:$X$3,Dashboard!$D$5,Phasing!$E394:$X394),SUMIF(Phasing!$E$4:$X$4,Dashboard!$B$6,Phasing!$E394:$X394)))) -> 0 | D224: =IF($A224="",0,IF(Dashboard!$B$5="All Time",Phasing!$Y395,IF(Dashboard!$B$5="Year",SUMIF(Phasing!$E$3:$X$3,Dashboard!$D$5,Phasing!$E395:$X395),SUMIF(Phasing!$E$4:$X$4,Dashboard!$B$6,Phasing!$E395:$X395)))) -> 0 | E224: =IF($A224="",0,IF(Dashboard!$B$5="All Time",Phasing!$Y396,IF(Dashboard!$B$5="Year",SUMIF(Phasing!$E$3:$X$3,Dashboard!$D$5,Phasing!$E396:$X396),SUMIF(Phasing!$E$4:$X$4,Dashboard!$B$6,Phasing!$E396:$X396)))) -> 0 | F224: =SUM($C224:$E224) -> 0 | G224: =IF($F224<=0,"",COUNTIF($F$181:$F224,">0"))
A225: =IF(Inputs!$A50="","",Inputs!$A50) | B225: =IF($A225="","",Inputs!$F50) | C225: =IF($A225="",0,IF(Dashboard!$B$5="All Time",Phasing!$Y397,IF(Dashboard!$B$5="Year",SUMIF(Phasing!$E$3:$X$3,Dashboard!$D$5,Phasing!$E397:$X397),SUMIF(Phasing!$E$4:$X$4,Dashboard!$B$6,Phasing!$E397:$X397)))) -> 0 | D225: =IF($A225="",0,IF(Dashboard!$B$5="All Time",Phasing!$Y398,IF(Dashboard!$B$5="Year",SUMIF(Phasing!$E$3:$X$3,Dashboard!$D$5,Phasing!$E398:$X398),SUMIF(Phasing!$E$4:$X$4,Dashboard!$B$6,Phasing!$E398:$X398)))) -> 0 | E225: =IF($A225="",0,IF(Dashboard!$B$5="All Time",Phasing!$Y399,IF(Dashboard!$B$5="Year",SUMIF(Phasing!$E$3:$X$3,Dashboard!$D$5,Phasing!$E399:$X399),SUMIF(Phasing!$E$4:$X$4,Dashboard!$B$6,Phasing!$E399:$X399)))) -> 0 | F225: =SUM($C225:$E225) -> 0 | G225: =IF($F225<=0,"",COUNTIF($F$181:$F225,">0"))
A226: =IF(Inputs!$A51="","",Inputs!$A51) | B226: =IF($A226="","",Inputs!$F51) | C226: =IF($A226="",0,IF(Dashboard!$B$5="All Time",Phasing!$Y400,IF(Dashboard!$B$5="Year",SUMIF(Phasing!$E$3:$X$3,Dashboard!$D$5,Phasing!$E400:$X400),SUMIF(Phasing!$E$4:$X$4,Dashboard!$B$6,Phasing!$E400:$X400)))) -> 0 | D226: =IF($A226="",0,IF(Dashboard!$B$5="All Time",Phasing!$Y401,IF(Dashboard!$B$5="Year",SUMIF(Phasing!$E$3:$X$3,Dashboard!$D$5,Phasing!$E401:$X401),SUMIF(Phasing!$E$4:$X$4,Dashboard!$B$6,Phasing!$E401:$X401)))) -> 0 | E226: =IF($A226="",0,IF(Dashboard!$B$5="All Time",Phasing!$Y402,IF(Dashboard!$B$5="Year",SUMIF(Phasing!$E$3:$X$3,Dashboard!$D$5,Phasing!$E402:$X402),SUMIF(Phasing!$E$4:$X$4,Dashboard!$B$6,Phasing!$E402:$X402)))) -> 0 | F226: =SUM($C226:$E226) -> 0 | G226: =IF($F226<=0,"",COUNTIF($F$181:$F226,">0"))
A227: =IF(Inputs!$A52="","",Inputs!$A52) | B227: =IF($A227="","",Inputs!$F52) | C227: =IF($A227="",0,IF(Dashboard!$B$5="All Time",Phasing!$Y403,IF(Dashboard!$B$5="Year",SUMIF(Phasing!$E$3:$X$3,Dashboard!$D$5,Phasing!$E403:$X403),SUMIF(Phasing!$E$4:$X$4,Dashboard!$B$6,Phasing!$E403:$X403)))) -> 0 | D227: =IF($A227="",0,IF(Dashboard!$B$5="All Time",Phasing!$Y404,IF(Dashboard!$B$5="Year",SUMIF(Phasing!$E$3:$X$3,Dashboard!$D$5,Phasing!$E404:$X404),SUMIF(Phasing!$E$4:$X$4,Dashboard!$B$6,Phasing!$E404:$X404)))) -> 0 | E227: =IF($A227="",0,IF(Dashboard!$B$5="All Time",Phasing!$Y405,IF(Dashboard!$B$5="Year",SUMIF(Phasing!$E$3:$X$3,Dashboard!$D$5,Phasing!$E405:$X405),SUMIF(Phasing!$E$4:$X$4,Dashboard!$B$6,Phasing!$E405:$X405)))) -> 0 | F227: =SUM($C227:$E227) -> 0 | G227: =IF($F227<=0,"",COUNTIF($F$181:$F227,">0"))
A228: =IF(Inputs!$A53="","",Inputs!$A53) | B228: =IF($A228="","",Inputs!$F53) | C228: =IF($A228="",0,IF(Dashboard!$B$5="All Time",Phasing!$Y406,IF(Dashboard!$B$5="Year",SUMIF(Phasing!$E$3:$X$3,Dashboard!$D$5,Phasing!$E406:$X406),SUMIF(Phasing!$E$4:$X$4,Dashboard!$B$6,Phasing!$E406:$X406)))) -> 0 | D228: =IF($A228="",0,IF(Dashboard!$B$5="All Time",Phasing!$Y407,IF(Dashboard!$B$5="Year",SUMIF(Phasing!$E$3:$X$3,Dashboard!$D$5,Phasing!$E407:$X407),SUMIF(Phasing!$E$4:$X$4,Dashboard!$B$6,Phasing!$E407:$X407)))) -> 0 | E228: =IF($A228="",0,IF(Dashboard!$B$5="All Time",Phasing!$Y408,IF(Dashboard!$B$5="Year",SUMIF(Phasing!$E$3:$X$3,Dashboard!$D$5,Phasing!$E408:$X408),SUMIF(Phasing!$E$4:$X$4,Dashboard!$B$6,Phasing!$E408:$X408)))) -> 0 | F228: =SUM($C228:$E228) -> 0 | G228: =IF($F228<=0,"",COUNTIF($F$181:$F228,">0"))
A229: =IF(Inputs!$A54="","",Inputs!$A54) | B229: =IF($A229="","",Inputs!$F54) | C229: =IF($A229="",0,IF(Dashboard!$B$5="All Time",Phasing!$Y409,IF(Dashboard!$B$5="Year",SUMIF(Phasing!$E$3:$X$3,Dashboard!$D$5,Phasing!$E409:$X409),SUMIF(Phasing!$E$4:$X$4,Dashboard!$B$6,Phasing!$E409:$X409)))) -> 0 | D229: =IF($A229="",0,IF(Dashboard!$B$5="All Time",Phasing!$Y410,IF(Dashboard!$B$5="Year",SUMIF(Phasing!$E$3:$X$3,Dashboard!$D$5,Phasing!$E410:$X410),SUMIF(Phasing!$E$4:$X$4,Dashboard!$B$6,Phasing!$E410:$X410)))) -> 0 | E229: =IF($A229="",0,IF(Dashboard!$B$5="All Time",Phasing!$Y411,IF(Dashboard!$B$5="Year",SUMIF(Phasing!$E$3:$X$3,Dashboard!$D$5,Phasing!$E411:$X411),SUMIF(Phasing!$E$4:$X$4,Dashboard!$B$6,Phasing!$E411:$X411)))) -> 0 | F229: =SUM($C229:$E229) -> 0 | G229: =IF($F229<=0,"",COUNTIF($F$181:$F229,">0"))
A230: =IF(Inputs!$A55="","",Inputs!$A55) | B230: =IF($A230="","",Inputs!$F55) | C230: =IF($A230="",0,IF(Dashboard!$B$5="All Time",Phasing!$Y412,IF(Dashboard!$B$5="Year",SUMIF(Phasing!$E$3:$X$3,Dashboard!$D$5,Phasing!$E412:$X412),SUMIF(Phasing!$E$4:$X$4,Dashboard!$B$6,Phasing!$E412:$X412)))) -> 0 | D230: =IF($A230="",0,IF(Dashboard!$B$5="All Time",Phasing!$Y413,IF(Dashboard!$B$5="Year",SUMIF(Phasing!$E$3:$X$3,Dashboard!$D$5,Phasing!$E413:$X413),SUMIF(Phasing!$E$4:$X$4,Dashboard!$B$6,Phasing!$E413:$X413)))) -> 0 | E230: =IF($A230="",0,IF(Dashboard!$B$5="All Time",Phasing!$Y414,IF(Dashboard!$B$5="Year",SUMIF(Phasing!$E$3:$X$3,Dashboard!$D$5,Phasing!$E414:$X414),SUMIF(Phasing!$E$4:$X$4,Dashboard!$B$6,Phasing!$E414:$X414)))) -> 0 | F230: =SUM($C230:$E230) -> 0 | G230: =IF($F230<=0,"",COUNTIF($F$181:$F230,">0"))
A231: =IF(Inputs!$A56="","",Inputs!$A56) | B231: =IF($A231="","",Inputs!$F56) | C231: =IF($A231="",0,IF(Dashboard!$B$5="All Time",Phasing!$Y415,IF(Dashboard!$B$5="Year",SUMIF(Phasing!$E$3:$X$3,Dashboard!$D$5,Phasing!$E415:$X415),SUMIF(Phasing!$E$4:$X$4,Dashboard!$B$6,Phasing!$E415:$X415)))) -> 0 | D231: =IF($A231="",0,IF(Dashboard!$B$5="All Time",Phasing!$Y416,IF(Dashboard!$B$5="Year",SUMIF(Phasing!$E$3:$X$3,Dashboard!$D$5,Phasing!$E416:$X416),SUMIF(Phasing!$E$4:$X$4,Dashboard!$B$6,Phasing!$E416:$X416)))) -> 0 | E231: =IF($A231="",0,IF(Dashboard!$B$5="All Time",Phasing!$Y417,IF(Dashboard!$B$5="Year",SUMIF(Phasing!$E$3:$X$3,Dashboard!$D$5,Phasing!$E417:$X417),SUMIF(Phasing!$E$4:$X$4,Dashboard!$B$6,Phasing!$E417:$X417)))) -> 0 | F231: =SUM($C231:$E231) -> 0 | G231: =IF($F231<=0,"",COUNTIF($F$181:$F231,">0"))
A232: =IF(Inputs!$A57="","",Inputs!$A57) | B232: =IF($A232="","",Inputs!$F57) | C232: =IF($A232="",0,IF(Dashboard!$B$5="All Time",Phasing!$Y418,IF(Dashboard!$B$5="Year",SUMIF(Phasing!$E$3:$X$3,Dashboard!$D$5,Phasing!$E418:$X418),SUMIF(Phasing!$E$4:$X$4,Dashboard!$B$6,Phasing!$E418:$X418)))) -> 0 | D232: =IF($A232="",0,IF(Dashboard!$B$5="All Time",Phasing!$Y419,IF(Dashboard!$B$5="Year",SUMIF(Phasing!$E$3:$X$3,Dashboard!$D$5,Phasing!$E419:$X419),SUMIF(Phasing!$E$4:$X$4,Dashboard!$B$6,Phasing!$E419:$X419)))) -> 0 | E232: =IF($A232="",0,IF(Dashboard!$B$5="All Time",Phasing!$Y420,IF(Dashboard!$B$5="Year",SUMIF(Phasing!$E$3:$X$3,Dashboard!$D$5,Phasing!$E420:$X420),SUMIF(Phasing!$E$4:$X$4,Dashboard!$B$6,Phasing!$E420:$X420)))) -> 0 | F232: =SUM($C232:$E232) -> 0 | G232: =IF($F232<=0,"",COUNTIF($F$181:$F232,">0"))
A233: =IF(Inputs!$A58="","",Inputs!$A58) | B233: =IF($A233="","",Inputs!$F58) | C233: =IF($A233="",0,IF(Dashboard!$B$5="All Time",Phasing!$Y421,IF(Dashboard!$B$5="Year",SUMIF(Phasing!$E$3:$X$3,Dashboard!$D$5,Phasing!$E421:$X421),SUMIF(Phasing!$E$4:$X$4,Dashboard!$B$6,Phasing!$E421:$X421)))) -> 0 | D233: =IF($A233="",0,IF(Dashboard!$B$5="All Time",Phasing!$Y422,IF(Dashboard!$B$5="Year",SUMIF(Phasing!$E$3:$X$3,Dashboard!$D$5,Phasing!$E422:$X422),SUMIF(Phasing!$E$4:$X$4,Dashboard!$B$6,Phasing!$E422:$X422)))) -> 0 | E233: =IF($A233="",0,IF(Dashboard!$B$5="All Time",Phasing!$Y423,IF(Dashboard!$B$5="Year",SUMIF(Phasing!$E$3:$X$3,Dashboard!$D$5,Phasing!$E423:$X423),SUMIF(Phasing!$E$4:$X$4,Dashboard!$B$6,Phasing!$E423:$X423)))) -> 0 | F233: =SUM($C233:$E233) -> 0 | G233: =IF($F233<=0,"",COUNTIF($F$181:$F233,">0"))
A234: =IF(Inputs!$A59="","",Inputs!$A59) | B234: =IF($A234="","",Inputs!$F59) | C234: =IF($A234="",0,IF(Dashboard!$B$5="All Time",Phasing!$Y424,IF(Dashboard!$B$5="Year",SUMIF(Phasing!$E$3:$X$3,Dashboard!$D$5,Phasing!$E424:$X424),SUMIF(Phasing!$E$4:$X$4,Dashboard!$B$6,Phasing!$E424:$X424)))) -> 0 | D234: =IF($A234="",0,IF(Dashboard!$B$5="All Time",Phasing!$Y425,IF(Dashboard!$B$5="Year",SUMIF(Phasing!$E$3:$X$3,Dashboard!$D$5,Phasing!$E425:$X425),SUMIF(Phasing!$E$4:$X$4,Dashboard!$B$6,Phasing!$E425:$X425)))) -> 0 | E234: =IF($A234="",0,IF(Dashboard!$B$5="All Time",Phasing!$Y426,IF(Dashboard!$B$5="Year",SUMIF(Phasing!$E$3:$X$3,Dashboard!$D$5,Phasing!$E426:$X426),SUMIF(Phasing!$E$4:$X$4,Dashboard!$B$6,Phasing!$E426:$X426)))) -> 0 | F234: =SUM($C234:$E234) -> 0 | G234: =IF($F234<=0,"",COUNTIF($F$181:$F234,">0"))
A235: =IF(Inputs!$A60="","",Inputs!$A60) | B235: =IF($A235="","",Inputs!$F60) | C235: =IF($A235="",0,IF(Dashboard!$B$5="All Time",Phasing!$Y427,IF(Dashboard!$B$5="Year",SUMIF(Phasing!$E$3:$X$3,Dashboard!$D$5,Phasing!$E427:$X427),SUMIF(Phasing!$E$4:$X$4,Dashboard!$B$6,Phasing!$E427:$X427)))) -> 0 | D235: =IF($A235="",0,IF(Dashboard!$B$5="All Time",Phasing!$Y428,IF(Dashboard!$B$5="Year",SUMIF(Phasing!$E$3:$X$3,Dashboard!$D$5,Phasing!$E428:$X428),SUMIF(Phasing!$E$4:$X$4,Dashboard!$B$6,Phasing!$E428:$X428)))) -> 0 | E235: =IF($A235="",0,IF(Dashboard!$B$5="All Time",Phasing!$Y429,IF(Dashboard!$B$5="Year",SUMIF(Phasing!$E$3:$X$3,Dashboard!$D$5,Phasing!$E429:$X429),SUMIF(Phasing!$E$4:$X$4,Dashboard!$B$6,Phasing!$E429:$X429)))) -> 0 | F235: =SUM($C235:$E235) -> 0 | G235: =IF($F235<=0,"",COUNTIF($F$181:$F235,">0"))
A236: =IF(Inputs!$A61="","",Inputs!$A61) | B236: =IF($A236="","",Inputs!$F61) | C236: =IF($A236="",0,IF(Dashboard!$B$5="All Time",Phasing!$Y430,IF(Dashboard!$B$5="Year",SUMIF(Phasing!$E$3:$X$3,Dashboard!$D$5,Phasing!$E430:$X430),SUMIF(Phasing!$E$4:$X$4,Dashboard!$B$6,Phasing!$E430:$X430)))) -> 0 | D236: =IF($A236="",0,IF(Dashboard!$B$5="All Time",Phasing!$Y431,IF(Dashboard!$B$5="Year",SUMIF(Phasing!$E$3:$X$3,Dashboard!$D$5,Phasing!$E431:$X431),SUMIF(Phasing!$E$4:$X$4,Dashboard!$B$6,Phasing!$E431:$X431)))) -> 0 | E236: =IF($A236="",0,IF(Dashboard!$B$5="All Time",Phasing!$Y432,IF(Dashboard!$B$5="Year",SUMIF(Phasing!$E$3:$X$3,Dashboard!$D$5,Phasing!$E432:$X432),SUMIF(Phasing!$E$4:$X$4,Dashboard!$B$6,Phasing!$E432:$X432)))) -> 0 | F236: =SUM($C236:$E236) -> 0 | G236: =IF($F236<=0,"",COUNTIF($F$181:$F236,">0"))
A237: =IF(Inputs!$A62="","",Inputs!$A62) | B237: =IF($A237="","",Inputs!$F62) | C237: =IF($A237="",0,IF(Dashboard!$B$5="All Time",Phasing!$Y433,IF(Dashboard!$B$5="Year",SUMIF(Phasing!$E$3:$X$3,Dashboard!$D$5,Phasing!$E433:$X433),SUMIF(Phasing!$E$4:$X$4,Dashboard!$B$6,Phasing!$E433:$X433)))) -> 0 | D237: =IF($A237="",0,IF(Dashboard!$B$5="All Time",Phasing!$Y434,IF(Dashboard!$B$5="Year",SUMIF(Phasing!$E$3:$X$3,Dashboard!$D$5,Phasing!$E434:$X434),SUMIF(Phasing!$E$4:$X$4,Dashboard!$B$6,Phasing!$E434:$X434)))) -> 0 | E237: =IF($A237="",0,IF(Dashboard!$B$5="All Time",Phasing!$Y435,IF(Dashboard!$B$5="Year",SUMIF(Phasing!$E$3:$X$3,Dashboard!$D$5,Phasing!$E435:$X435),SUMIF(Phasing!$E$4:$X$4,Dashboard!$B$6,Phasing!$E435:$X435)))) -> 0 | F237: =SUM($C237:$E237) -> 0 | G237: =IF($F237<=0,"",COUNTIF($F$181:$F237,">0"))
A238: =IF(Inputs!$A63="","",Inputs!$A63) | B238: =IF($A238="","",Inputs!$F63) | C238: =IF($A238="",0,IF(Dashboard!$B$5="All Time",Phasing!$Y436,IF(Dashboard!$B$5="Year",SUMIF(Phasing!$E$3:$X$3,Dashboard!$D$5,Phasing!$E436:$X436),SUMIF(Phasing!$E$4:$X$4,Dashboard!$B$6,Phasing!$E436:$X436)))) -> 0 | D238: =IF($A238="",0,IF(Dashboard!$B$5="All Time",Phasing!$Y437,IF(Dashboard!$B$5="Year",SUMIF(Phasing!$E$3:$X$3,Dashboard!$D$5,Phasing!$E437:$X437),SUMIF(Phasing!$E$4:$X$4,Dashboard!$B$6,Phasing!$E437:$X437)))) -> 0 | E238: =IF($A238="",0,IF(Dashboard!$B$5="All Time",Phasing!$Y438,IF(Dashboard!$B$5="Year",SUMIF(Phasing!$E$3:$X$3,Dashboard!$D$5,Phasing!$E438:$X438),SUMIF(Phasing!$E$4:$X$4,Dashboard!$B$6,Phasing!$E438:$X438)))) -> 0 | F238: =SUM($C238:$E238) -> 0 | G238: =IF($F238<=0,"",COUNTIF($F$181:$F238,">0"))
A239: =IF(Inputs!$A64="","",Inputs!$A64) | B239: =IF($A239="","",Inputs!$F64) | C239: =IF($A239="",0,IF(Dashboard!$B$5="All Time",Phasing!$Y439,IF(Dashboard!$B$5="Year",SUMIF(Phasing!$E$3:$X$3,Dashboard!$D$5,Phasing!$E439:$X439),SUMIF(Phasing!$E$4:$X$4,Dashboard!$B$6,Phasing!$E439:$X439)))) -> 0 | D239: =IF($A239="",0,IF(Dashboard!$B$5="All Time",Phasing!$Y440,IF(Dashboard!$B$5="Year",SUMIF(Phasing!$E$3:$X$3,Dashboard!$D$5,Phasing!$E440:$X440),SUMIF(Phasing!$E$4:$X$4,Dashboard!$B$6,Phasing!$E440:$X440)))) -> 0 | E239: =IF($A239="",0,IF(Dashboard!$B$5="All Time",Phasing!$Y441,IF(Dashboard!$B$5="Year",SUMIF(Phasing!$E$3:$X$3,Dashboard!$D$5,Phasing!$E441:$X441),SUMIF(Phasing!$E$4:$X$4,Dashboard!$B$6,Phasing!$E441:$X441)))) -> 0 | F239: =SUM($C239:$E239) -> 0 | G239: =IF($F239<=0,"",COUNTIF($F$181:$F239,">0"))
A240: =IF(Inputs!$A65="","",Inputs!$A65) | B240: =IF($A240="","",Inputs!$F65) | C240: =IF($A240="",0,IF(Dashboard!$B$5="All Time",Phasing!$Y442,IF(Dashboard!$B$5="Year",SUMIF(Phasing!$E$3:$X$3,Dashboard!$D$5,Phasing!$E442:$X442),SUMIF(Phasing!$E$4:$X$4,Dashboard!$B$6,Phasing!$E442:$X442)))) -> 0 | D240: =IF($A240="",0,IF(Dashboard!$B$5="All Time",Phasing!$Y443,IF(Dashboard!$B$5="Year",SUMIF(Phasing!$E$3:$X$3,Dashboard!$D$5,Phasing!$E443:$X443),SUMIF(Phasing!$E$4:$X$4,Dashboard!$B$6,Phasing!$E443:$X443)))) -> 0 | E240: =IF($A240="",0,IF(Dashboard!$B$5="All Time",Phasing!$Y444,IF(Dashboard!$B$5="Year",SUMIF(Phasing!$E$3:$X$3,Dashboard!$D$5,Phasing!$E444:$X444),SUMIF(Phasing!$E$4:$X$4,Dashboard!$B$6,Phasing!$E444:$X444)))) -> 0 | F240: =SUM($C240:$E240) -> 0 | G240: =IF($F240<=0,"",COUNTIF($F$181:$F240,">0"))
A241: =IF(Inputs!$A66="","",Inputs!$A66) | B241: =IF($A241="","",Inputs!$F66) | C241: =IF($A241="",0,IF(Dashboard!$B$5="All Time",Phasing!$Y445,IF(Dashboard!$B$5="Year",SUMIF(Phasing!$E$3:$X$3,Dashboard!$D$5,Phasing!$E445:$X445),SUMIF(Phasing!$E$4:$X$4,Dashboard!$B$6,Phasing!$E445:$X445)))) -> 0 | D241: =IF($A241="",0,IF(Dashboard!$B$5="All Time",Phasing!$Y446,IF(Dashboard!$B$5="Year",SUMIF(Phasing!$E$3:$X$3,Dashboard!$D$5,Phasing!$E446:$X446),SUMIF(Phasing!$E$4:$X$4,Dashboard!$B$6,Phasing!$E446:$X446)))) -> 0 | E241: =IF($A241="",0,IF(Dashboard!$B$5="All Time",Phasing!$Y447,IF(Dashboard!$B$5="Year",SUMIF(Phasing!$E$3:$X$3,Dashboard!$D$5,Phasing!$E447:$X447),SUMIF(Phasing!$E$4:$X$4,Dashboard!$B$6,Phasing!$E447:$X447)))) -> 0 | F241: =SUM($C241:$E241) -> 0 | G241: =IF($F241<=0,"",COUNTIF($F$181:$F241,">0"))
A242: =IF(Inputs!$A67="","",Inputs!$A67) | B242: =IF($A242="","",Inputs!$F67) | C242: =IF($A242="",0,IF(Dashboard!$B$5="All Time",Phasing!$Y448,IF(Dashboard!$B$5="Year",SUMIF(Phasing!$E$3:$X$3,Dashboard!$D$5,Phasing!$E448:$X448),SUMIF(Phasing!$E$4:$X$4,Dashboard!$B$6,Phasing!$E448:$X448)))) -> 0 | D242: =IF($A242="",0,IF(Dashboard!$B$5="All Time",Phasing!$Y449,IF(Dashboard!$B$5="Year",SUMIF(Phasing!$E$3:$X$3,Dashboard!$D$5,Phasing!$E449:$X449),SUMIF(Phasing!$E$4:$X$4,Dashboard!$B$6,Phasing!$E449:$X449)))) -> 0 | E242: =IF($A242="",0,IF(Dashboard!$B$5="All Time",Phasing!$Y450,IF(Dashboard!$B$5="Year",SUMIF(Phasing!$E$3:$X$3,Dashboard!$D$5,Phasing!$E450:$X450),SUMIF(Phasing!$E$4:$X$4,Dashboard!$B$6,Phasing!$E450:$X450)))) -> 0 | F242: =SUM($C242:$E242) -> 0 | G242: =IF($F242<=0,"",COUNTIF($F$181:$F242,">0"))
A243: =IF(Inputs!$A68="","",Inputs!$A68) | B243: =IF($A243="","",Inputs!$F68) | C243: =IF($A243="",0,IF(Dashboard!$B$5="All Time",Phasing!$Y451,IF(Dashboard!$B$5="Year",SUMIF(Phasing!$E$3:$X$3,Dashboard!$D$5,Phasing!$E451:$X451),SUMIF(Phasing!$E$4:$X$4,Dashboard!$B$6,Phasing!$E451:$X451)))) -> 0 | D243: =IF($A243="",0,IF(Dashboard!$B$5="All Time",Phasing!$Y452,IF(Dashboard!$B$5="Year",SUMIF(Phasing!$E$3:$X$3,Dashboard!$D$5,Phasing!$E452:$X452),SUMIF(Phasing!$E$4:$X$4,Dashboard!$B$6,Phasing!$E452:$X452)))) -> 0 | E243: =IF($A243="",0,IF(Dashboard!$B$5="All Time",Phasing!$Y453,IF(Dashboard!$B$5="Year",SUMIF(Phasing!$E$3:$X$3,Dashboard!$D$5,Phasing!$E453:$X453),SUMIF(Phasing!$E$4:$X$4,Dashboard!$B$6,Phasing!$E453:$X453)))) -> 0 | F243: =SUM($C243:$E243) -> 0 | G243: =IF($F243<=0,"",COUNTIF($F$181:$F243,">0"))
...

Sheet Team Member
A1: ="PERSONAL PERFORMANCE REPORT — "&UPPER($B$4)&" | "&TEXT($D$4,"0") -> PERSONAL PERFORMANCE REPORT — AHMED | 2025
A2: All effort in Man-Months (MM). Choose your name and the year below — this sheet is independent of the Dashboard filter.
A4: Team member: | B4: Ahmed | C4: Year: | D4: 2025 | E4: As at: | F4: =Inputs!$B$96 -> 46266 | H4: =MATCH($B$4,Inputs!$A$91:$A$93,0) -> 1
A5: {="As at "&TEXT($F$4,"dd mmm yyyy")&", "&TEXT(SUMPRODUCT((Analysis!$E$3:$X$3=$D$4)*Analysis!$E$31:$X$31)/4,"0.0%")&" of "&TEXT($D$4,"0")&" has elapsed. Capacity and plan targets below are pro-rated to that point, not to 31 December."} -> As at 01 Sep 2026, 100.0% of 2025 has elapsed. Capacity and plan targets below are pro-rated to that point, not to 31 December. | H5: {=SUMPRODUCT((Analysis!$E$3:$X$3=$D$4)*Analysis!$E$31:$X$31)/4} -> 1
H6: {=IFERROR(INDEX(Inputs!$B$91:$F$93,$H$4,MATCH($D$4,Inputs!$B$90:$F$90,0))*4*Inputs!$B$94,0)} -> 12
A7: YOUR NUMBERS FOR THE YEAR
A8: Metric | B8: Value | C8: What it means
A9: Actual MM you booked | B9: =SUM($E$154:$E$233) -> 9.2594595 | C9: ="time you actually logged in "&TEXT($D$4,"0") -> time you actually logged in 2025
A10: Planned MM to date (your allocation) | B10: =SUMPRODUCT($H$154:$H$233,$F$154:$F$233) -> 22.761725 | C10: ="what the plan expected of you by "&TEXT($F$4,"dd mmm") -> what the plan expected of you by 01 Sep
A11: Earned MM (value you delivered) | B11: =SUMPRODUCT($D$154:$D$233,$F$154:$F$233) -> 20.015598 | C11: ="budget value earned on your share of the work" -> budget value earned on your share of the work
A12: Capacity MM to date | B12: =$H$6*$H$5 -> 12 | C12: ="your available time up to "&TEXT($F$4,"dd mmm") -> your available time up to 01 Sep
A13: Utilisation vs capacity to date | B13: =IF($B$12=0,"n/a",$B$9/$B$12) -> 0.77162162 | C13: =IF($B$13="n/a","no capacity set",IF($B$13>1,"above capacity — overloaded","within capacity")) -> within capacity
A14: Plan adherence to date | B14: =IF($B$10=0,"n/a",$B$9/$B$10) -> 0.40679955 | C14: =IF($B$14="n/a","no plan to compare",IF($B$14>1,"ahead of the plan","behind the plan")) -> behind the plan
A15: Efficiency (CPI) | B15: =IF($B$9=0,"n/a",$B$11/$B$9) -> 2.1616379 | C15: =IF($B$15="n/a","no time booked",IF($B$15>=1,"delivering more value than time spent","spending more time than value delivered")) -> delivering more value than time spent
A16: Projects you worked on | B16: =COUNTIF($E$154:$E$233,">0") -> 20 | C16: ="projects with time booked in the year" -> projects with time booked in the year
A17: Average MM per project | B17: =IF($B$16=0,"n/a",$B$9/$B$16) -> 0.46297297 | C17: ="average effort per project" -> average effort per project
A18: Remaining workload allocated to you | B18: =SUMPRODUCT(Inputs!$R$6:$R$85,Inputs!$M$6:$M$85,$F$154:$F$233) -> 31.120935 | C18: ="still to do on projects assigned to you" -> still to do on projects assigned to you
A20: QUARTER BY QUARTER
A21: Metric | B21: ="Q1-"&TEXT(MOD($D$4,100),"00") -> Q1-25 | C21: ="Q2-"&TEXT(MOD($D$4,100),"00") -> Q2-25 | D21: ="Q3-"&TEXT(MOD($D$4,100),"00") -> Q3-25 | E21: ="Q4-"&TEXT(MOD($D$4,100),"00") -> Q4-25 | F21: Year
A22: Your actual MM | B22: {=SUMPRODUCT((Phasing!$E$4:$X$4=B$21)*INDEX(Phasing!$E$680:$X$682,$H$4,0))} -> 2.2243243 | C22: {=SUMPRODUCT((Phasing!$E$4:$X$4=C$21)*INDEX(Phasing!$E$680:$X$682,$H$4,0))} -> 2.0716216 | D22: {=SUMPRODUCT((Phasing!$E$4:$X$4=D$21)*INDEX(Phasing!$E$680:$X$682,$H$4,0))} -> 2.2554054 | E22: {=SUMPRODUCT((Phasing!$E$4:$X$4=E$21)*INDEX(Phasing!$E$680:$X$682,$H$4,0))} -> 2.7081081 | F22: =SUM(B22:E22) -> 9.2594595
A23: Your capacity to date | B23: =$H$6/4*B24 -> 3 | C23: =$H$6/4*C24 -> 3 | D23: =$H$6/4*D24 -> 3 | E23: =$H$6/4*E24 -> 3 | F23: =SUM(B23:E23) -> 12
A24: Elapsed of quarter | B24: {=SUMPRODUCT((Analysis!$E$4:$X$4=B$21)*Analysis!$E$31:$X$31)} -> 1 | C24: {=SUMPRODUCT((Analysis!$E$4:$X$4=C$21)*Analysis!$E$31:$X$31)} -> 1 | D24: {=SUMPRODUCT((Analysis!$E$4:$X$4=D$21)*Analysis!$E$31:$X$31)} -> 1 | E24: {=SUMPRODUCT((Analysis!$E$4:$X$4=E$21)*Analysis!$E$31:$X$31)} -> 1 | F24: =$H$5 -> 1
A25: Utilisation vs capacity to date | B25: =IF(B23=0,"n/a",B22/B23) -> 0.74144144 | C25: =IF(C23=0,"n/a",C22/C23) -> 0.69054054 | D25: =IF(D23=0,"n/a",D22/D23) -> 0.7518018 | E25: =IF(E23=0,"n/a",E22/E23) -> 0.9027027 | F25: =IF(F23=0,"n/a",F22/F23) -> 0.77162162
A26: Your earned MM (value delivered) | B26: =SUMPRODUCT(INDEX(Phasing!$E$595:$X$674,0,MATCH(B$21,Phasing!$E$4:$X$4,0)),$F$154:$F$233) -> 2.1625485 | C26: =SUMPRODUCT(INDEX(Phasing!$E$595:$X$674,0,MATCH(C$21,Phasing!$E$4:$X$4,0)),$F$154:$F$233) -> 7.8547623 | D26: =SUMPRODUCT(INDEX(Phasing!$E$595:$X$674,0,MATCH(D$21,Phasing!$E$4:$X$4,0)),$F$154:$F$233) -> 7.5314146 | E26: =SUMPRODUCT(INDEX(Phasing!$E$595:$X$674,0,MATCH(E$21,Phasing!$E$4:$X$4,0)),$F$154:$F$233) -> 2.4668729 | F26: =SUM(B26:E26) -> 20.015598
A27: Your efficiency (CPI) | B27: =IF(B22=0,"n/a",B26/B22) -> 0.97222715 | C27: =IF(C22=0,"n/a",C26/C22) -> 3.7916008 | D27: =IF(D22=0,"n/a",D26/D22) -> 3.3392731 | E27: =IF(E22=0,"n/a",E26/E22) -> 0.91092111 | F27: =IF(F22=0,"n/a",F26/F22) -> 2.1616379
A28: Your contribution to team MM | B28: {=IF(SUMPRODUCT((Phasing!$E$4:$X$4=B$21)*Phasing!$E$505:$X$505)=0,"n/a",B22/SUMPRODUCT((Phasing!$E$4:$X$4=B$21)*Phasing!$E$505:$X$505))} -> 0.30749113 | C28: {=IF(SUMPRODUCT((Phasing!$E$4:$X$4=C$21)*Phasing!$E$505:$X$505)=0,"n/a",C22/SUMPRODUCT((Phasing!$E$4:$X$4=C$21)*Phasing!$E$505:$X$505))} -> 0.34754024 | D28: {=IF(SUMPRODUCT((Phasing!$E$4:$X$4=D$21)*Phasing!$E$505:$X$505)=0,"n/a",D22/SUMPRODUCT((Phasing!$E$4:$X$4=D$21)*Phasing!$E$505:$X$505))} -> 0.25672973 | E28: {=IF(SUMPRODUCT((Phasing!$E$4:$X$4=E$21)*Phasing!$E$505:$X$505)=0,"n/a",E22/SUMPRODUCT((Phasing!$E$4:$X$4=E$21)*Phasing!$E$505:$X$505))} -> 0.3311302 | F28: {=IF(SUMPRODUCT((Analysis!$E$3:$X$3=$D$4)*Phasing!$E$505:$X$505)=0,"n/a",F22/SUMPRODUCT((Analysis!$E$3:$X$3=$D$4)*Phasing!$E$505:$X$505))} -> 0.30703051
A30: YOUR PROJECTS THIS YEAR
A31: Project | B31: Status | C31: Your MM | D31: Share of your time | E31: Planned to date | F31: Your allocation %
A32: =IFERROR(INDEX($A$154:$A$233,MATCH(ROW()-31,$G$154:$G$233,0)),"") -> N25185-0100D | B32: =IF($A32="","",INDEX($B$154:$B$233,MATCH(ROW()-31,$G$154:$G$233,0))) -> Active | C32: =IF($A32="","",INDEX($E$154:$E$233,MATCH(ROW()-31,$G$154:$G$233,0))) -> 1.6283784 | D32: =IF($A32="","",IF($C$60=0,"",$C32/$C$60)) -> 0.17586106 | E32: =IF($A32="","",INDEX($H$154:$H$233,MATCH(ROW()-31,$G$154:$G$233,0))) -> 5.2341357 | F32: =IF($A32="","",INDEX($F$154:$F$233,MATCH(ROW()-31,$G$154:$G$233,0))) -> 0.41582278
A33: =IFERROR(INDEX($A$154:$A$233,MATCH(ROW()-31,$G$154:$G$233,0)),"") -> AD24217-0100D | B33: =IF($A33="","",INDEX($B$154:$B$233,MATCH(ROW()-31,$G$154:$G$233,0))) -> Finalized | C33: =IF($A33="","",INDEX($E$154:$E$233,MATCH(ROW()-31,$G$154:$G$233,0))) -> 0.25945946 | D33: =IF($A33="","",IF($C$60=0,"",$C33/$C$60)) -> 0.028021016 | E33: =IF($A33="","",INDEX($H$154:$H$233,MATCH(ROW()-31,$G$154:$G$233,0))) -> 3 | F33: =IF($A33="","",INDEX($F$154:$F$233,MATCH(ROW()-31,$G$154:$G$233,0))) -> 0.4
A34: =IFERROR(INDEX($A$154:$A$233,MATCH(ROW()-31,$G$154:$G$233,0)),"") -> AN23276-0100D | B34: =IF($A34="","",INDEX($B$154:$B$233,MATCH(ROW()-31,$G$154:$G$233,0))) -> On Hold | C34: =IF($A34="","",INDEX($E$154:$E$233,MATCH(ROW()-31,$G$154:$G$233,0))) -> 0.010810811 | D34: =IF($A34="","",IF($C$60=0,"",$C34/$C$60)) -> 0.0011675423 | E34: =IF($A34="","",INDEX($H$154:$H$233,MATCH(ROW()-31,$G$154:$G$233,0))) -> 2.2201946 | F34: =IF($A34="","",INDEX($F$154:$F$233,MATCH(ROW()-31,$G$154:$G$233,0))) -> 0.4
A35: =IFERROR(INDEX($A$154:$A$233,MATCH(ROW()-31,$G$154:$G$233,0)),"") -> AN24073-0100D | B35: =IF($A35="","",INDEX($B$154:$B$233,MATCH(ROW()-31,$G$154:$G$233,0))) -> On Hold | C35: =IF($A35="","",INDEX($E$154:$E$233,MATCH(ROW()-31,$G$154:$G$233,0))) -> 0.010810811 | D35: =IF($A35="","",IF($C$60=0,"",$C35/$C$60)) -> 0.0011675423 | E35: =IF($A35="","",INDEX($H$154:$H$233,MATCH(ROW()-31,$G$154:$G$233,0))) -> 0.50328228 | F35: =IF($A35="","",INDEX($F$154:$F$233,MATCH(ROW()-31,$G$154:$G$233,0))) -> 0.1
A36: =IFERROR(INDEX($A$154:$A$233,MATCH(ROW()-31,$G$154:$G$233,0)),"") -> AN24140-0100R | B36: =IF($A36="","",INDEX($B$154:$B$233,MATCH(ROW()-31,$G$154:$G$233,0))) -> Active | C36: =IF($A36="","",INDEX($E$154:$E$233,MATCH(ROW()-31,$G$154:$G$233,0))) -> 0.0054054054 | D36: =IF($A36="","",IF($C$60=0,"",$C36/$C$60)) -> 0.00058377116 | E36: =IF($A36="","",INDEX($H$154:$H$233,MATCH(ROW()-31,$G$154:$G$233,0))) -> 0.79274611 | F36: =IF($A36="","",INDEX($F$154:$F$233,MATCH(ROW()-31,$G$154:$G$233,0))) -> 0.1
A37: =IFERROR(INDEX($A$154:$A$233,MATCH(ROW()-31,$G$154:$G$233,0)),"") -> CS24035-0100D | B37: =IF($A37="","",INDEX($B$154:$B$233,MATCH(ROW()-31,$G$154:$G$233,0))) -> On Hold | C37: =IF($A37="","",INDEX($E$154:$E$233,MATCH(ROW()-31,$G$154:$G$233,0))) -> 1.0337838 | D37: =IF($A37="","",IF($C$60=0,"",$C37/$C$60)) -> 0.11164623 | E37: =IF($A37="","",INDEX($H$154:$H$233,MATCH(ROW()-31,$G$154:$G$233,0))) -> 0.80525164 | F37: =IF($A37="","",INDEX($F$154:$F$233,MATCH(ROW()-31,$G$154:$G$233,0))) -> 0.5
A38: =IFERROR(INDEX($A$154:$A$233,MATCH(ROW()-31,$G$154:$G$233,0)),"") -> J23152-0100D | B38: =IF($A38="","",INDEX($B$154:$B$233,MATCH(ROW()-31,$G$154:$G$233,0))) -> Finalized | C38: =IF($A38="","",INDEX($E$154:$E$233,MATCH(ROW()-31,$G$154:$G$233,0))) -> 0.016216216 | D38: =IF($A38="","",IF($C$60=0,"",$C38/$C$60)) -> 0.0017513135 | E38: =IF($A38="","",INDEX($H$154:$H$233,MATCH(ROW()-31,$G$154:$G$233,0))) -> 0 | F38: =IF($A38="","",INDEX($F$154:$F$233,MATCH(ROW()-31,$G$154:$G$233,0))) -> 1
A39: =IFERROR(INDEX($A$154:$A$233,MATCH(ROW()-31,$G$154:$G$233,0)),"") -> Q25008-0100D | B39: =IF($A39="","",INDEX($B$154:$B$233,MATCH(ROW()-31,$G$154:$G$233,0))) -> Finalized | C39: =IF($A39="","",INDEX($E$154:$E$233,MATCH(ROW()-31,$G$154:$G$233,0))) -> 0.078378378 | D39: =IF($A39="","",IF($C$60=0,"",$C39/$C$60)) -> 0.0084646818 | E39: =IF($A39="","",INDEX($H$154:$H$233,MATCH(ROW()-31,$G$154:$G$233,0))) -> 0 | F39: =IF($A39="","",INDEX($F$154:$F$233,MATCH(ROW()-31,$G$154:$G$233,0))) -> 0.2
A40: =IFERROR(INDEX($A$154:$A$233,MATCH(ROW()-31,$G$154:$G$233,0)),"") -> S24014-0102D | B40: =IF($A40="","",INDEX($B$154:$B$233,MATCH(ROW()-31,$G$154:$G$233,0))) -> Finalized | C40: =IF($A40="","",INDEX($E$154:$E$233,MATCH(ROW()-31,$G$154:$G$233,0))) -> 2.2364865 | D40: =IF($A40="","",IF($C$60=0,"",$C40/$C$60)) -> 0.24153532 | E40: =IF($A40="","",INDEX($H$154:$H$233,MATCH(ROW()-31,$G$154:$G$233,0))) -> 5.266481 | F40: =IF($A40="","",INDEX($F$154:$F$233,MATCH(ROW()-31,$G$154:$G$233,0))) -> 0.7
A41: =IFERROR(INDEX($A$154:$A$233,MATCH(ROW()-31,$G$154:$G$233,0)),"") -> S24014-0104D | B41: =IF($A41="","",INDEX($B$154:$B$233,MATCH(ROW()-31,$G$154:$G$233,0))) -> Finalized | C41: =IF($A41="","",INDEX($E$154:$E$233,MATCH(ROW()-31,$G$154:$G$233,0))) -> 0.67162162 | D41: =IF($A41="","",IF($C$60=0,"",$C41/$C$60)) -> 0.072533567 | E41: =IF($A41="","",INDEX($H$154:$H$233,MATCH(ROW()-31,$G$154:$G$233,0))) -> 8.3144051 | F41: =IF($A41="","",INDEX($F$154:$F$233,MATCH(ROW()-31,$G$154:$G$233,0))) -> 1
A42: =IFERROR(INDEX($A$154:$A$233,MATCH(ROW()-31,$G$154:$G$233,0)),"") -> S22058-0700D | B42: =IF($A42="","",INDEX($B$154:$B$233,MATCH(ROW()-31,$G$154:$G$233,0))) -> Finalized | C42: =IF($A42="","",INDEX($E$154:$E$233,MATCH(ROW()-31,$G$154:$G$233,0))) -> 0.90540541 | D42: =IF($A42="","",IF($C$60=0,"",$C42/$C$60)) -> 0.09778167 | E42: =IF($A42="","",INDEX($H$154:$H$233,MATCH(ROW()-31,$G$154:$G$233,0))) -> 3.5842451 | F42: =IF($A42="","",INDEX($F$154:$F$233,MATCH(ROW()-31,$G$154:$G$233,0))) -> 0.15
A43: =IFERROR(INDEX($A$154:$A$233,MATCH(ROW()-31,$G$154:$G$233,0)),"") -> AN24185-0100R | B43: =IF($A43="","",INDEX($B$154:$B$233,MATCH(ROW()-31,$G$154:$G$233,0))) -> Finalized | C43: =IF($A43="","",INDEX($E$154:$E$233,MATCH(ROW()-31,$G$154:$G$233,0))) -> 0.010810811 | D43: =IF($A43="","",IF($C$60=0,"",$C43/$C$60)) -> 0.0011675423 | E43: =IF($A43="","",INDEX($H$154:$H$233,MATCH(ROW()-31,$G$154:$G$233,0))) -> 2.6691042 | F43: =IF($A43="","",INDEX($F$154:$F$233,MATCH(ROW()-31,$G$154:$G$233,0))) -> 0.05
... A59: =IFERROR(INDEX($A$154:$A$233,MATCH(ROW()-31,$G$154:$G$233,0)),"") | B59: =IF($A59="","",INDEX($B$154:$B$233,MATCH(ROW()-31,$G$154:$G$233,0))) | C59: =IF($A59="","",INDEX($E$154:$E$233,MATCH(ROW()-31,$G$154:$G$233,0))) | D59: =IF($A59="","",IF($C$60=0,"",$C59/$C$60)) | E59: =IF($A59="","",INDEX($H$154:$H$233,MATCH(ROW()-31,$G$154:$G$233,0))) | F59: =IF($A59="","",INDEX($F$154:$F$233,MATCH(ROW()-31,$G$154:$G$233,0)))
A60: ="TOTAL — "&COUNTIF($A$32:$A$59,"?*")&" project(s)" -> TOTAL — 20 project(s) | C60: =SUM(C32:C59) -> 9.2594595 | D60: =IF($C$60=0,"",1) -> 1 | E60: =SUM(E32:E59) -> 40.029359
A131: Project | B131: Your MM
C153: Planned in Year | D153: Earned in Year | E153: Your Actual MM | F153: Your Allocation % | G153: Rank | H153: Planned to Date in Year
A154: =IF(Inputs!$A6="","",Inputs!$A6) -> N25178-0100D | B154: =IF($A154="","",Inputs!$F6) -> Active | C154: {=IF($A154="",0,SUMPRODUCT((Phasing!$E$3:$X$3=$D$4)*Phasing!$E180:$X180))} -> 0 | D154: {=IF($A154="",0,SUMPRODUCT((Phasing!$E$3:$X$3=$D$4)*Phasing!$E595:$X595))} -> 0 | E154: {=IF($A154="",0,SUMPRODUCT((Phasing!$E$3:$X$3=$D$4)*INDEX(Phasing!$E$265:$X$267,$H$4,0)))} -> 0 | F154: {=IF($A154="",0,INDEX(Inputs!$I6:$K6,1,$H$4))} -> 1 | G154: =IF($E154<=0,"",COUNTIF($E$154:$E154,">0")) | H154: {=IF($A154="",0,SUMPRODUCT((Analysis!$E$3:$X$3=$D$4)*Phasing!$E180:$X180*Analysis!$E$31:$X$31))} -> 0
A155: =IF(Inputs!$A7="","",Inputs!$A7) -> E26084-0100D | B155: =IF($A155="","",Inputs!$F7) -> Active | C155: {=IF($A155="",0,SUMPRODUCT((Phasing!$E$3:$X$3=$D$4)*Phasing!$E181:$X181))} -> 1.2078775 | D155: {=IF($A155="",0,SUMPRODUCT((Phasing!$E$3:$X$3=$D$4)*Phasing!$E596:$X596))} -> 0 | E155: {=IF($A155="",0,SUMPRODUCT((Phasing!$E$3:$X$3=$D$4)*INDEX(Phasing!$E$268:$X$270,$H$4,0)))} -> 0 | F155: {=IF($A155="",0,INDEX(Inputs!$I7:$K7,1,$H$4))} -> 0.15 | G155: =IF($E155<=0,"",COUNTIF($E$154:$E155,">0")) | H155: {=IF($A155="",0,SUMPRODUCT((Analysis!$E$3:$X$3=$D$4)*Phasing!$E181:$X181*Analysis!$E$31:$X$31))} -> 1.2078775
A156: =IF(Inputs!$A8="","",Inputs!$A8) -> N25185-0100D | B156: =IF($A156="","",Inputs!$F8) -> Active | C156: {=IF($A156="",0,SUMPRODUCT((Phasing!$E$3:$X$3=$D$4)*Phasing!$E182:$X182))} -> 5.2341357 | D156: {=IF($A156="",0,SUMPRODUCT((Phasing!$E$3:$X$3=$D$4)*Phasing!$E597:$X597))} -> 2.2179962 | E156: {=IF($A156="",0,SUMPRODUCT((Phasing!$E$3:$X$3=$D$4)*INDEX(Phasing!$E$271:$X$273,$H$4,0)))} -> 1.6283784 | F156: {=IF($A156="",0,INDEX(Inputs!$I8:$K8,1,$H$4))} -> 0.41582278 | G156: =IF($E156<=0,"",COUNTIF($E$154:$E156,">0")) -> 1 | H156: {=IF($A156="",0,SUMPRODUCT((Analysis!$E$3:$X$3=$D$4)*Phasing!$E182:$X182*Analysis!$E$31:$X$31))} -> 5.2341357
A157: =IF(Inputs!$A9="","",Inputs!$A9) -> AN22137-0100D | B157: =IF($A157="","",Inputs!$F9) -> Not Started | C157: {=IF($A157="",0,SUMPRODUCT((Phasing!$E$3:$X$3=$D$4)*Phasing!$E183:$X183))} -> 0 | D157: {=IF($A157="",0,SUMPRODUCT((Phasing!$E$3:$X$3=$D$4)*Phasing!$E598:$X598))} -> 0 | E157: {=IF($A157="",0,SUMPRODUCT((Phasing!$E$3:$X$3=$D$4)*INDEX(Phasing!$E$274:$X$276,$H$4,0)))} -> 0 | F157: {=IF($A157="",0,INDEX(Inputs!$I9:$K9,1,$H$4))} -> 0.6 | G157: =IF($E157<=0,"",COUNTIF($E$154:$E157,">0")) | H157: {=IF($A157="",0,SUMPRODUCT((Analysis!$E$3:$X$3=$D$4)*Phasing!$E183:$X183*Analysis!$E$31:$X$31))} -> 0
A158: =IF(Inputs!$A10="","",Inputs!$A10) -> D26058-0100D | B158: =IF($A158="","",Inputs!$F10) -> Not Started | C158: {=IF($A158="",0,SUMPRODUCT((Phasing!$E$3:$X$3=$D$4)*Phasing!$E184:$X184))} -> 0 | D158: {=IF($A158="",0,SUMPRODUCT((Phasing!$E$3:$X$3=$D$4)*Phasing!$E599:$X599))} -> 0 | E158: {=IF($A158="",0,SUMPRODUCT((Phasing!$E$3:$X$3=$D$4)*INDEX(Phasing!$E$277:$X$279,$H$4,0)))} -> 0 | F158: {=IF($A158="",0,INDEX(Inputs!$I10:$K10,1,$H$4))} -> 0.6 | G158: =IF($E158<=0,"",COUNTIF($E$154:$E158,">0")) | H158: {=IF($A158="",0,SUMPRODUCT((Analysis!$E$3:$X$3=$D$4)*Phasing!$E184:$X184*Analysis!$E$31:$X$31))} -> 0
A159: =IF(Inputs!$A11="","",Inputs!$A11) -> AD24217-0100D | B159: =IF($A159="","",Inputs!$F11) -> Finalized | C159: {=IF($A159="",0,SUMPRODUCT((Phasing!$E$3:$X$3=$D$4)*Phasing!$E185:$X185))} -> 3 | D159: {=IF($A159="",0,SUMPRODUCT((Phasing!$E$3:$X$3=$D$4)*Phasing!$E600:$X600))} -> 3 | E159: {=IF($A159="",0,SUMPRODUCT((Phasing!$E$3:$X$3=$D$4)*INDEX(Phasing!$E$280:$X$282,$H$4,0)))} -> 0.25945946 | F159: {=IF($A159="",0,INDEX(Inputs!$I11:$K11,1,$H$4))} -> 0.4 | G159: =IF($E159<=0,"",COUNTIF($E$154:$E159,">0")) -> 2 | H159: {=IF($A159="",0,SUMPRODUCT((Analysis!$E$3:$X$3=$D$4)*Phasing!$E185:$X185*Analysis!$E$31:$X$31))} -> 3
A160: =IF(Inputs!$A12="","",Inputs!$A12) -> AN23207-0500D | B160: =IF($A160="","",Inputs!$F12) -> On Hold | C160: {=IF($A160="",0,SUMPRODUCT((Phasing!$E$3:$X$3=$D$4)*Phasing!$E186:$X186))} -> 0 | D160: {=IF($A160="",0,SUMPRODUCT((Phasing!$E$3:$X$3=$D$4)*Phasing!$E601:$X601))} -> 0 | E160: {=IF($A160="",0,SUMPRODUCT((Phasing!$E$3:$X$3=$D$4)*INDEX(Phasing!$E$283:$X$285,$H$4,0)))} -> 0 | F160: {=IF($A160="",0,INDEX(Inputs!$I12:$K12,1,$H$4))} -> 0.2 | G160: =IF($E160<=0,"",COUNTIF($E$154:$E160,">0")) | H160: {=IF($A160="",0,SUMPRODUCT((Analysis!$E$3:$X$3=$D$4)*Phasing!$E186:$X186*Analysis!$E$31:$X$31))} -> 0
A161: =IF(Inputs!$A13="","",Inputs!$A13) -> AN23276-0100D | B161: =IF($A161="","",Inputs!$F13) -> On Hold | C161: {=IF($A161="",0,SUMPRODUCT((Phasing!$E$3:$X$3=$D$4)*Phasing!$E187:$X187))} -> 2.2201946 | D161: {=IF($A161="",0,SUMPRODUCT((Phasing!$E$3:$X$3=$D$4)*Phasing!$E602:$X602))} -> 0.53343465 | E161: {=IF($A161="",0,SUMPRODUCT((Phasing!$E$3:$X$3=$D$4)*INDEX(Phasing!$E$286:$X$288,$H$4,0)))} -> 0.010810811 | F161: {=IF($A161="",0,INDEX(Inputs!$I13:$K13,1,$H$4))} -> 0.4 | G161: =IF($E161<=0,"",COUNTIF($E$154:$E161,">0")) -> 3 | H161: {=IF($A161="",0,SUMPRODUCT((Analysis!$E$3:$X$3=$D$4)*Phasing!$E187:$X187*Analysis!$E$31:$X$31))} -> 2.2201946
A162: =IF(Inputs!$A14="","",Inputs!$A14) -> AN24073-0100D | B162: =IF($A162="","",Inputs!$F14) -> On Hold | C162: {=IF($A162="",0,SUMPRODUCT((Phasing!$E$3:$X$3=$D$4)*Phasing!$E188:$X188))} -> 0.50328228 | D162: {=IF($A162="",0,SUMPRODUCT((Phasing!$E$3:$X$3=$D$4)*Phasing!$E603:$X603))} -> 1.125 | E162: {=IF($A162="",0,SUMPRODUCT((Phasing!$E$3:$X$3=$D$4)*INDEX(Phasing!$E$289:$X$291,$H$4,0)))} -> 0.010810811 | F162: {=IF($A162="",0,INDEX(Inputs!$I14:$K14,1,$H$4))} -> 0.1 | G162: =IF($E162<=0,"",COUNTIF($E$154:$E162,">0")) -> 4 | H162: {=IF($A162="",0,SUMPRODUCT((Analysis!$E$3:$X$3=$D$4)*Phasing!$E188:$X188*Analysis!$E$31:$X$31))} -> 0.50328228
A163: =IF(Inputs!$A15="","",Inputs!$A15) -> AN24140-0100R | B163: =IF($A163="","",Inputs!$F15) -> Active | C163: {=IF($A163="",0,SUMPRODUCT((Phasing!$E$3:$X$3=$D$4)*Phasing!$E189:$X189))} -> 0.79274611 | D163: {=IF($A163="",0,SUMPRODUCT((Phasing!$E$3:$X$3=$D$4)*Phasing!$E604:$X604))} -> 0.1233871 | E163: {=IF($A163="",0,SUMPRODUCT((Phasing!$E$3:$X$3=$D$4)*INDEX(Phasing!$E$292:$X$294,$H$4,0)))} -> 0.0054054054 | F163: {=IF($A163="",0,INDEX(Inputs!$I15:$K15,1,$H$4))} -> 0.1 | G163: =IF($E163<=0,"",COUNTIF($E$154:$E163,">0")) -> 5 | H163: {=IF($A163="",0,SUMPRODUCT((Analysis!$E$3:$X$3=$D$4)*Phasing!$E189:$X189*Analysis!$E$31:$X$31))} -> 0.79274611
A164: =IF(Inputs!$A16="","",Inputs!$A16) -> CS24035-0100D | B164: =IF($A164="","",Inputs!$F16) -> On Hold | C164: {=IF($A164="",0,SUMPRODUCT((Phasing!$E$3:$X$3=$D$4)*Phasing!$E190:$X190))} -> 0.80525164 | D164: {=IF($A164="",0,SUMPRODUCT((Phasing!$E$3:$X$3=$D$4)*Phasing!$E605:$X605))} -> 2.7458154 | E164: {=IF($A164="",0,SUMPRODUCT((Phasing!$E$3:$X$3=$D$4)*INDEX(Phasing!$E$295:$X$297,$H$4,0)))} -> 1.0337838 | F164: {=IF($A164="",0,INDEX(Inputs!$I16:$K16,1,$H$4))} -> 0.5 | G164: =IF($E164<=0,"",COUNTIF($E$154:$E164,">0")) -> 6 | H164: {=IF($A164="",0,SUMPRODUCT((Analysis!$E$3:$X$3=$D$4)*Phasing!$E190:$X190*Analysis!$E$31:$X$31))} -> 0.80525164
A165: =IF(Inputs!$A17="","",Inputs!$A17) -> E24181-0100D | B165: =IF($A165="","",Inputs!$F17) -> Finalized | C165: {=IF($A165="",0,SUMPRODUCT((Phasing!$E$3:$X$3=$D$4)*Phasing!$E191:$X191))} -> 0 | D165: {=IF($A165="",0,SUMPRODUCT((Phasing!$E$3:$X$3=$D$4)*Phasing!$E606:$X606))} -> 0 | E165: {=IF($A165="",0,SUMPRODUCT((Phasing!$E$3:$X$3=$D$4)*INDEX(Phasing!$E$298:$X$300,$H$4,0)))} -> 0 | F165: {=IF($A165="",0,INDEX(Inputs!$I17:$K17,1,$H$4))} -> 1 | G165: =IF($E165<=0,"",COUNTIF($E$154:$E165,">0")) | H165: {=IF($A165="",0,SUMPRODUCT((Analysis!$E$3:$X$3=$D$4)*Phasing!$E191:$X191*Analysis!$E$31:$X$31))} -> 0
A166: =IF(Inputs!$A18="","",Inputs!$A18) -> J23152-0100D | B166: =IF($A166="","",Inputs!$F18) -> Finalized | C166: {=IF($A166="",0,SUMPRODUCT((Phasing!$E$3:$X$3=$D$4)*Phasing!$E192:$X192))} -> 0 | D166: {=IF($A166="",0,SUMPRODUCT((Phasing!$E$3:$X$3=$D$4)*Phasing!$E607:$X607))} -> 0.073170732 | E166: {=IF($A166="",0,SUMPRODUCT((Phasing!$E$3:$X$3=$D$4)*INDEX(Phasing!$E$301:$X$303,$H$4,0)))} -> 0.016216216 | F166: {=IF($A166="",0,INDEX(Inputs!$I18:$K18,1,$H$4))} -> 1 | G166: =IF($E166<=0,"",COUNTIF($E$154:$E166,">0")) -> 7 | H166: {=IF($A166="",0,SUMPRODUCT((Analysis!$E$3:$X$3=$D$4)*Phasing!$E192:$X192*Analysis!$E$31:$X$31))} -> 0
A167: =IF(Inputs!$A19="","",Inputs!$A19) -> Q25008-0100D | B167: =IF($A167="","",Inputs!$F19) -> Finalized | C167: {=IF($A167="",0,SUMPRODUCT((Phasing!$E$3:$X$3=$D$4)*Phasing!$E193:$X193))} -> 0 | D167: {=IF($A167="",0,SUMPRODUCT((Phasing!$E$3:$X$3=$D$4)*Phasing!$E608:$X608))} -> 0.30112045 | E167: {=IF($A167="",0,SUMPRODUCT((Phasing!$E$3:$X$3=$D$4)*INDEX(Phasing!$E$304:$X$306,$H$4,0)))} -> 0.078378378 | F167: {=IF($A167="",0,INDEX(Inputs!$I19:$K19,1,$H$4))} -> 0.2 | G167: =IF($E167<=0,"",COUNTIF($E$154:$E167,">0")) -> 8 | H167: {=IF($A167="",0,SUMPRODUCT((Analysis!$E$3:$X$3=$D$4)*Phasing!$E193:$X193*Analysis!$E$31:$X$31))} -> 0
A168: =IF(Inputs!$A20="","",Inputs!$A20) -> S24014-0101D | B168: =IF($A168="","",Inputs!$F20) -> Finalized | C168: {=IF($A168="",0,SUMPRODUCT((Phasing!$E$3:$X$3=$D$4)*Phasing!$E194:$X194))} -> 0 | D168: {=IF($A168="",0,SUMPRODUCT((Phasing!$E$3:$X$3=$D$4)*Phasing!$E609:$X609))} -> 0 | E168: {=IF($A168="",0,SUMPRODUCT((Phasing!$E$3:$X$3=$D$4)*INDEX(Phasing!$E$307:$X$309,$H$4,0)))} -> 0 | F168: {=IF($A168="",0,INDEX(Inputs!$I20:$K20,1,$H$4))} -> 1 | G168: =IF($E168<=0,"",COUNTIF($E$154:$E168,">0")) | H168: {=IF($A168="",0,SUMPRODUCT((Analysis!$E$3:$X$3=$D$4)*Phasing!$E194:$X194*Analysis!$E$31:$X$31))} -> 0
A169: =IF(Inputs!$A21="","",Inputs!$A21) -> S24014-0102D | B169: =IF($A169="","",Inputs!$F21) -> Finalized | C169: {=IF($A169="",0,SUMPRODUCT((Phasing!$E$3:$X$3=$D$4)*Phasing!$E195:$X195))} -> 5.266481 | D169: {=IF($A169="",0,SUMPRODUCT((Phasing!$E$3:$X$3=$D$4)*Phasing!$E610:$X610))} -> 7.62 | E169: {=IF($A169="",0,SUMPRODUCT((Phasing!$E$3:$X$3=$D$4)*INDEX(Phasing!$E$310:$X$312,$H$4,0)))} -> 2.2364865 | F169: {=IF($A169="",0,INDEX(Inputs!$I21:$K21,1,$H$4))} -> 0.7 | G169: =IF($E169<=0,"",COUNTIF($E$154:$E169,">0")) -> 9 | H169: {=IF($A169="",0,SUMPRODUCT((Analysis!$E$3:$X$3=$D$4)*Phasing!$E195:$X195*Analysis!$E$31:$X$31))} -> 5.266481
A170: =IF(Inputs!$A22="","",Inputs!$A22) -> S24014-0103D | B170: =IF($A170="","",Inputs!$F22) -> Finalized | C170: {=IF($A170="",0,SUMPRODUCT((Phasing!$E$3:$X$3=$D$4)*Phasing!$E196:$X196))} -> 4.3956456 | D170: {=IF($A170="",0,SUMPRODUCT((Phasing!$E$3:$X$3=$D$4)*Phasing!$E611:$X611))} -> 0 | E170: {=IF($A170="",0,SUMPRODUCT((Phasing!$E$3:$X$3=$D$4)*INDEX(Phasing!$E$313:$X$315,$H$4,0)))} -> 0 | F170: {=IF($A170="",0,INDEX(Inputs!$I22:$K22,1,$H$4))} -> 0.5 | G170: =IF($E170<=0,"",COUNTIF($E$154:$E170,">0")) | H170: {=IF($A170="",0,SUMPRODUCT((Analysis!$E$3:$X$3=$D$4)*Phasing!$E196:$X196*Analysis!$E$31:$X$31))} -> 4.3956456
A171: =IF(Inputs!$A23="","",Inputs!$A23) -> S24014-0104D | B171: =IF($A171="","",Inputs!$F23) -> Finalized | C171: {=IF($A171="",0,SUMPRODUCT((Phasing!$E$3:$X$3=$D$4)*Phasing!$E197:$X197))} -> 8.3144051 | D171: {=IF($A171="",0,SUMPRODUCT((Phasing!$E$3:$X$3=$D$4)*Phasing!$E612:$X612))} -> 6.6432333 | E171: {=IF($A171="",0,SUMPRODUCT((Phasing!$E$3:$X$3=$D$4)*INDEX(Phasing!$E$316:$X$318,$H$4,0)))} -> 0.67162162 | F171: {=IF($A171="",0,INDEX(Inputs!$I23:$K23,1,$H$4))} -> 1 | G171: =IF($E171<=0,"",COUNTIF($E$154:$E171,">0")) -> 10 | H171: {=IF($A171="",0,SUMPRODUCT((Analysis!$E$3:$X$3=$D$4)*Phasing!$E197:$X197*Analysis!$E$31:$X$31))} -> 8.3144051
A172: =IF(Inputs!$A24="","",Inputs!$A24) -> S22058-0700D | B172: =IF($A172="","",Inputs!$F24) -> Finalized | C172: {=IF($A172="",0,SUMPRODUCT((Phasing!$E$3:$X$3=$D$4)*Phasing!$E198:$X198))} -> 3.5842451 | D172: {=IF($A172="",0,SUMPRODUCT((Phasing!$E$3:$X$3=$D$4)*Phasing!$E613:$X613))} -> 5.1870048 | E172: {=IF($A172="",0,SUMPRODUCT((Phasing!$E$3:$X$3=$D$4)*INDEX(Phasing!$E$319:$X$321,$H$4,0)))} -> 0.90540541 | F172: {=IF($A172="",0,INDEX(Inputs!$I24:$K24,1,$H$4))} -> 0.15 | G172: =IF($E172<=0,"",COUNTIF($E$154:$E172,">0")) -> 11 | H172: {=IF($A172="",0,SUMPRODUCT((Analysis!$E$3:$X$3=$D$4)*Phasing!$E198:$X198*Analysis!$E$31:$X$31))} -> 3.5842451
A173: =IF(Inputs!$A25="","",Inputs!$A25) -> AN24185-0100R | B173: =IF($A173="","",Inputs!$F25) -> Finalized | C173: {=IF($A173="",0,SUMPRODUCT((Phasing!$E$3:$X$3=$D$4)*Phasing!$E199:$X199))} -> 2.6691042 | D173: {=IF($A173="",0,SUMPRODUCT((Phasing!$E$3:$X$3=$D$4)*Phasing!$E614:$X614))} -> 2.2911912 | E173: {=IF($A173="",0,SUMPRODUCT((Phasing!$E$3:$X$3=$D$4)*INDEX(Phasing!$E$322:$X$324,$H$4,0)))} -> 0.010810811 | F173: {=IF($A173="",0,INDEX(Inputs!$I25:$K25,1,$H$4))} -> 0.05 | G173: =IF($E173<=0,"",COUNTIF($E$154:$E173,">0")) -> 12 | H173: {=IF($A173="",0,SUMPRODUCT((Analysis!$E$3:$X$3=$D$4)*Phasing!$E199:$X199*Analysis!$E$31:$X$31))} -> 2.6691042
A174: =IF(Inputs!$A26="","",Inputs!$A26) -> AN24135-0100R | B174: =IF($A174="","",Inputs!$F26) -> On Hold | C174: {=IF($A174="",0,SUMPRODUCT((Phasing!$E$3:$X$3=$D$4)*Phasing!$E200:$X200))} -> 1.6008772 | D174: {=IF($A174="",0,SUMPRODUCT((Phasing!$E$3:$X$3=$D$4)*Phasing!$E615:$X615))} -> 0.29726937 | E174: {=IF($A174="",0,SUMPRODUCT((Phasing!$E$3:$X$3=$D$4)*INDEX(Phasing!$E$325:$X$327,$H$4,0)))} -> 0.025675676 | F174: {=IF($A174="",0,INDEX(Inputs!$I26:$K26,1,$H$4))} -> 0.05 | G174: =IF($E174<=0,"",COUNTIF($E$154:$E174,">0")) -> 13 | H174: {=IF($A174="",0,SUMPRODUCT((Analysis!$E$3:$X$3=$D$4)*Phasing!$E200:$X200*Analysis!$E$31:$X$31))} -> 1.6008772
A175: =IF(Inputs!$A27="","",Inputs!$A27) -> AN23232-0100D | B175: =IF($A175="","",Inputs!$F27) -> Finalized | C175: {=IF($A175="",0,SUMPRODUCT((Phasing!$E$3:$X$3=$D$4)*Phasing!$E201:$X201))} -> 0 | D175: {=IF($A175="",0,SUMPRODUCT((Phasing!$E$3:$X$3=$D$4)*Phasing!$E616:$X616))} -> 0.038052373 | E175: {=IF($A175="",0,SUMPRODUCT((Phasing!$E$3:$X$3=$D$4)*INDEX(Phasing!$E$328:$X$330,$H$4,0)))} -> 0.041891892 | F175: {=IF($A175="",0,INDEX(Inputs!$I27:$K27,1,$H$4))} -> 0.75 | G175: =IF($E175<=0,"",COUNTIF($E$154:$E175,">0")) -> 14 | H175: {=IF($A175="",0,SUMPRODUCT((Analysis!$E$3:$X$3=$D$4)*Phasing!$E201:$X201*Analysis!$E$31:$X$31))} -> 0
A176: =IF(Inputs!$A28="","",Inputs!$A28) -> AN23108-0100R | B176: =IF($A176="","",Inputs!$F28) -> On Hold | C176: {=IF($A176="",0,SUMPRODUCT((Phasing!$E$3:$X$3=$D$4)*Phasing!$E202:$X202))} -> 0.75909091 | D176: {=IF($A176="",0,SUMPRODUCT((Phasing!$E$3:$X$3=$D$4)*Phasing!$E617:$X617))} -> 0.034313725 | E176: {=IF($A176="",0,SUMPRODUCT((Phasing!$E$3:$X$3=$D$4)*INDEX(Phasing!$E$331:$X$333,$H$4,0)))} -> 0.097297297 | F176: {=IF($A176="",0,INDEX(Inputs!$I28:$K28,1,$H$4))} -> 0.1 | G176: =IF($E176<=0,"",COUNTIF($E$154:$E176,">0")) -> 15 | H176: {=IF($A176="",0,SUMPRODUCT((Analysis!$E$3:$X$3=$D$4)*Phasing!$E202:$X202*Analysis!$E$31:$X$31))} -> 0.75909091
A177: =IF(Inputs!$A29="","",Inputs!$A29) -> TA24246-0200R | B177: =IF($A177="","",Inputs!$F29) -> On Hold | C177: {=IF($A177="",0,SUMPRODUCT((Phasing!$E$3:$X$3=$D$4)*Phasing!$E203:$X203))} -> 0.37954545 | D177: {=IF($A177="",0,SUMPRODUCT((Phasing!$E$3:$X$3=$D$4)*Phasing!$E618:$X618))} -> 0.55824595 | E177: {=IF($A177="",0,SUMPRODUCT((Phasing!$E$3:$X$3=$D$4)*INDEX(Phasing!$E$334:$X$336,$H$4,0)))} -> 0.085135135 | F177: {=IF($A177="",0,INDEX(Inputs!$I29:$K29,1,$H$4))} -> 0.1 | G177: =IF($E177<=0,"",COUNTIF($E$154:$E177,">0")) -> 16 | H177: {=IF($A177="",0,SUMPRODUCT((Analysis!$E$3:$X$3=$D$4)*Phasing!$E203:$X203*Analysis!$E$31:$X$31))} -> 0.37954545
A178: =IF(Inputs!$A30="","",Inputs!$A30) -> S22058-0900D | B178: =IF($A178="","",Inputs!$F30) -> Cancelled | C178: {=IF($A178="",0,SUMPRODUCT((Phasing!$E$3:$X$3=$D$4)*Phasing!$E204:$X204))} -> 0 | D178: {=IF($A178="",0,SUMPRODUCT((Phasing!$E$3:$X$3=$D$4)*Phasing!$E619:$X619))} -> 0.19366197 | E178: {=IF($A178="",0,SUMPRODUCT((Phasing!$E$3:$X$3=$D$4)*INDEX(Phasing!$E$337:$X$339,$H$4,0)))} -> 0.074324324 | F178: {=IF($A178="",0,INDEX(Inputs!$I30:$K30,1,$H$4))} -> 1 | G178: =IF($E178<=0,"",COUNTIF($E$154:$E178,">0")) -> 17 | H178: {=IF($A178="",0,SUMPRODUCT((Analysis!$E$3:$X$3=$D$4)*Phasing!$E204:$X204*Analysis!$E$31:$X$31))} -> 0
A179: =IF(Inputs!$A31="","",Inputs!$A31) -> S22058-0400D | B179: =IF($A179="","",Inputs!$F31) -> Finalized | C179: {=IF($A179="",0,SUMPRODUCT((Phasing!$E$3:$X$3=$D$4)*Phasing!$E205:$X205))} -> 0 | D179: {=IF($A179="",0,SUMPRODUCT((Phasing!$E$3:$X$3=$D$4)*Phasing!$E620:$X620))} -> 0.13333333 | E179: {=IF($A179="",0,SUMPRODUCT((Phasing!$E$3:$X$3=$D$4)*INDEX(Phasing!$E$340:$X$342,$H$4,0)))} -> 0.010810811 | F179: {=IF($A179="",0,INDEX(Inputs!$I31:$K31,1,$H$4))} -> 1 | G179: =IF($E179<=0,"",COUNTIF($E$154:$E179,">0")) -> 18 | H179: {=IF($A179="",0,SUMPRODUCT((Analysis!$E$3:$X$3=$D$4)*Phasing!$E205:$X205*Analysis!$E$31:$X$31))} -> 0
A180: =IF(Inputs!$A32="","",Inputs!$A32) -> Proposals 25 | B180: =IF($A180="","",Inputs!$F32) -> Finalized | C180: {=IF($A180="",0,SUMPRODUCT((Phasing!$E$3:$X$3=$D$4)*Phasing!$E206:$X206))} -> 1.9 | D180: {=IF($A180="",0,SUMPRODUCT((Phasing!$E$3:$X$3=$D$4)*Phasing!$E621:$X621))} -> 1.9 | E180: {=IF($A180="",0,SUMPRODUCT((Phasing!$E$3:$X$3=$D$4)*INDEX(Phasing!$E$343:$X$345,$H$4,0)))} -> 1.0716216 | F180: {=IF($A180="",0,INDEX(Inputs!$I32:$K32,1,$H$4))} -> 0.8 | G180: =IF($E180<=0,"",COUNTIF($E$154:$E180,">0")) -> 19 | H180: {=IF($A180="",0,SUMPRODUCT((Analysis!$E$3:$X$3=$D$4)*Phasing!$E206:$X206*Analysis!$E$31:$X$31))} -> 1.9
A181: =IF(Inputs!$A33="","",Inputs!$A33) -> Chargable Proposals 25 | B181: =IF($A181="","",Inputs!$F33) -> Finalized | C181: {=IF($A181="",0,SUMPRODUCT((Phasing!$E$3:$X$3=$D$4)*Phasing!$E207:$X207))} -> 3 | D181: {=IF($A181="",0,SUMPRODUCT((Phasing!$E$3:$X$3=$D$4)*Phasing!$E622:$X622))} -> 3 | E181: {=IF($A181="",0,SUMPRODUCT((Phasing!$E$3:$X$3=$D$4)*INDEX(Phasing!$E$346:$X$348,$H$4,0)))} -> 0.98513514 | F181: {=IF($A181="",0,INDEX(Inputs!$I33:$K33,1,$H$4))} -> 0.4 | G181: =IF($E181<=0,"",COUNTIF($E$154:$E181,">0")) -> 20 | H181: {=IF($A181="",0,SUMPRODUCT((Analysis!$E$3:$X$3=$D$4)*Phasing!$E207:$X207*Analysis!$E$31:$X$31))} -> 3
A182: =IF(Inputs!$A34="","",Inputs!$A34) -> AD23051-0101D | B182: =IF($A182="","",Inputs!$F34) -> Cancelled | C182: {=IF($A182="",0,SUMPRODUCT((Phasing!$E$3:$X$3=$D$4)*Phasing!$E208:$X208))} -> 0 | D182: {=IF($A182="",0,SUMPRODUCT((Phasing!$E$3:$X$3=$D$4)*Phasing!$E623:$X623))} -> 0 | E182: {=IF($A182="",0,SUMPRODUCT((Phasing!$E$3:$X$3=$D$4)*INDEX(Phasing!$E$349:$X$351,$H$4,0)))} -> 0 | F182: {=IF($A182="",0,INDEX(Inputs!$I34:$K34,1,$H$4))} -> 1 | G182: =IF($E182<=0,"",COUNTIF($E$154:$E182,">0")) | H182: {=IF($A182="",0,SUMPRODUCT((Analysis!$E$3:$X$3=$D$4)*Phasing!$E208:$X208*Analysis!$E$31:$X$31))} -> 0
A183: =IF(Inputs!$A35="","",Inputs!$A35) -> AN21146-0100R | B183: =IF($A183="","",Inputs!$F35) -> Finalized | C183: {=IF($A183="",0,SUMPRODUCT((Phasing!$E$3:$X$3=$D$4)*Phasing!$E209:$X209))} -> 0 | D183: {=IF($A183="",0,SUMPRODUCT((Phasing!$E$3:$X$3=$D$4)*Phasing!$E624:$X624))} -> 0 | E183: {=IF($A183="",0,SUMPRODUCT((Phasing!$E$3:$X$3=$D$4)*INDEX(Phasing!$E$352:$X$354,$H$4,0)))} -> 0 | F183: {=IF($A183="",0,INDEX(Inputs!$I35:$K35,1,$H$4))} -> 0.4 | G183: =IF($E183<=0,"",COUNTIF($E$154:$E183,">0")) | H183: {=IF($A183="",0,SUMPRODUCT((Analysis!$E$3:$X$3=$D$4)*Phasing!$E209:$X209*Analysis!$E$31:$X$31))} -> 0
A184: =IF(Inputs!$A36="","",Inputs!$A36) -> N23106-0100D | B184: =IF($A184="","",Inputs!$F36) -> Finalized | C184: {=IF($A184="",0,SUMPRODUCT((Phasing!$E$3:$X$3=$D$4)*Phasing!$E210:$X210))} -> 0 | D184: {=IF($A184="",0,SUMPRODUCT((Phasing!$E$3:$X$3=$D$4)*Phasing!$E625:$X625))} -> 0.048820179 | E184: {=IF($A184="",0,SUMPRODUCT((Phasing!$E$3:$X$3=$D$4)*INDEX(Phasing!$E$355:$X$357,$H$4,0)))} -> 0 | F184: {=IF($A184="",0,INDEX(Inputs!$I36:$K36,1,$H$4))} -> 0.6 | G184: =IF($E184<=0,"",COUNTIF($E$154:$E184,">0")) | H184: {=IF($A184="",0,SUMPRODUCT((Analysis!$E$3:$X$3=$D$4)*Phasing!$E210:$X210*Analysis!$E$31:$X$31))} -> 0
A185: =IF(Inputs!$A37="","",Inputs!$A37) -> OM23030-0100D | B185: =IF($A185="","",Inputs!$F37) -> Finalized | C185: {=IF($A185="",0,SUMPRODUCT((Phasing!$E$3:$X$3=$D$4)*Phasing!$E211:$X211))} -> 0 | D185: {=IF($A185="",0,SUMPRODUCT((Phasing!$E$3:$X$3=$D$4)*Phasing!$E626:$X626))} -> 0 | E185: {=IF($A185="",0,SUMPRODUCT((Phasing!$E$3:$X$3=$D$4)*INDEX(Phasing!$E$358:$X$360,$H$4,0)))} -> 0 | F185: {=IF($A185="",0,INDEX(Inputs!$I37:$K37,1,$H$4))} -> 1 | G185: =IF($E185<=0,"",COUNTIF($E$154:$E185,">0")) | H185: {=IF($A185="",0,SUMPRODUCT((Analysis!$E$3:$X$3=$D$4)*Phasing!$E211:$X211*Analysis!$E$31:$X$31))} -> 0
A186: =IF(Inputs!$A38="","",Inputs!$A38) -> Chargable Proposals 24 | B186: =IF($A186="","",Inputs!$F38) -> Finalized | C186: {=IF($A186="",0,SUMPRODUCT((Phasing!$E$3:$X$3=$D$4)*Phasing!$E212:$X212))} -> 0 | D186: {=IF($A186="",0,SUMPRODUCT((Phasing!$E$3:$X$3=$D$4)*Phasing!$E627:$X627))} -> 0 | E186: {=IF($A186="",0,SUMPRODUCT((Phasing!$E$3:$X$3=$D$4)*INDEX(Phasing!$E$361:$X$363,$H$4,0)))} -> 0 | F186: {=IF($A186="",0,INDEX(Inputs!$I38:$K38,1,$H$4))} -> 0.4 | G186: =IF($E186<=0,"",COUNTIF($E$154:$E186,">0")) | H186: {=IF($A186="",0,SUMPRODUCT((Analysis!$E$3:$X$3=$D$4)*Phasing!$E212:$X212*Analysis!$E$31:$X$31))} -> 0
A187: =IF(Inputs!$A39="","",Inputs!$A39) -> Proposals 24 | B187: =IF($A187="","",Inputs!$F39) -> Finalized | C187: {=IF($A187="",0,SUMPRODUCT((Phasing!$E$3:$X$3=$D$4)*Phasing!$E213:$X213))} -> 0 | D187: {=IF($A187="",0,SUMPRODUCT((Phasing!$E$3:$X$3=$D$4)*Phasing!$E628:$X628))} -> 0 | E187: {=IF($A187="",0,SUMPRODUCT((Phasing!$E$3:$X$3=$D$4)*INDEX(Phasing!$E$364:$X$366,$H$4,0)))} -> 0 | F187: {=IF($A187="",0,INDEX(Inputs!$I39:$K39,1,$H$4))} -> 0.8 | G187: =IF($E187<=0,"",COUNTIF($E$154:$E187,">0")) | H187: {=IF($A187="",0,SUMPRODUCT((Analysis!$E$3:$X$3=$D$4)*Phasing!$E213:$X213*Analysis!$E$31:$X$31))} -> 0
A188: =IF(Inputs!$A40="","",Inputs!$A40) -> S23204-0100D | B188: =IF($A188="","",Inputs!$F40) -> Finalized | C188: {=IF($A188="",0,SUMPRODUCT((Phasing!$E$3:$X$3=$D$4)*Phasing!$E214:$X214))} -> 0 | D188: {=IF($A188="",0,SUMPRODUCT((Phasing!$E$3:$X$3=$D$4)*Phasing!$E629:$X629))} -> 0 | E188: {=IF($A188="",0,SUMPRODUCT((Phasing!$E$3:$X$3=$D$4)*INDEX(Phasing!$E$367:$X$369,$H$4,0)))} -> 0 | F188: {=IF($A188="",0,INDEX(Inputs!$I40:$K40,1,$H$4))} -> 1 | G188: =IF($E188<=0,"",COUNTIF($E$154:$E188,">0")) | H188: {=IF($A188="",0,SUMPRODUCT((Analysis!$E$3:$X$3=$D$4)*Phasing!$E214:$X214*Analysis!$E$31:$X$31))} -> 0
A189: =IF(Inputs!$A41="","",Inputs!$A41) -> S24100-0100D | B189: =IF($A189="","",Inputs!$F41) -> Finalized | C189: {=IF($A189="",0,SUMPRODUCT((Phasing!$E$3:$X$3=$D$4)*Phasing!$E215:$X215))} -> 0 | D189: {=IF($A189="",0,SUMPRODUCT((Phasing!$E$3:$X$3=$D$4)*Phasing!$E630:$X630))} -> 0 | E189: {=IF($A189="",0,SUMPRODUCT((Phasing!$E$3:$X$3=$D$4)*INDEX(Phasing!$E$370:$X$372,$H$4,0)))} -> 0 | F189: {=IF($A189="",0,INDEX(Inputs!$I41:$K41,1,$H$4))} -> 0.25 | G189: =IF($E189<=0,"",COUNTIF($E$154:$E189,">0")) | H189: {=IF($A189="",0,SUMPRODUCT((Analysis!$E$3:$X$3=$D$4)*Phasing!$E215:$X215*Analysis!$E$31:$X$31))} -> 0
A190: =IF(Inputs!$A42="","",Inputs!$A42) -> TA23011-0100R | B190: =IF($A190="","",Inputs!$F42) -> Finalized | C190: {=IF($A190="",0,SUMPRODUCT((Phasing!$E$3:$X$3=$D$4)*Phasing!$E216:$X216))} -> 0 | D190: {=IF($A190="",0,SUMPRODUCT((Phasing!$E$3:$X$3=$D$4)*Phasing!$E631:$X631))} -> 0 | E190: {=IF($A190="",0,SUMPRODUCT((Phasing!$E$3:$X$3=$D$4)*INDEX(Phasing!$E$373:$X$375,$H$4,0)))} -> 0 | F190: {=IF($A190="",0,INDEX(Inputs!$I42:$K42,1,$H$4))} -> 1 | G190: =IF($E190<=0,"",COUNTIF($E$154:$E190,">0")) | H190: {=IF($A190="",0,SUMPRODUCT((Analysis!$E$3:$X$3=$D$4)*Phasing!$E216:$X216*Analysis!$E$31:$X$31))} -> 0
A191: =IF(Inputs!$A43="","",Inputs!$A43) -> AL25148-0100D | B191: =IF($A191="","",Inputs!$F43) -> Not Started | C191: {=IF($A191="",0,SUMPRODUCT((Phasing!$E$3:$X$3=$D$4)*Phasing!$E217:$X217))} -> 0 | D191: {=IF($A191="",0,SUMPRODUCT((Phasing!$E$3:$X$3=$D$4)*Phasing!$E632:$X632))} -> 0 | E191: {=IF($A191="",0,SUMPRODUCT((Phasing!$E$3:$X$3=$D$4)*INDEX(Phasing!$E$376:$X$378,$H$4,0)))} -> 0 | F191: {=IF($A191="",0,INDEX(Inputs!$I43:$K43,1,$H$4))} -> 0.6 | G191: =IF($E191<=0,"",COUNTIF($E$154:$E191,">0")) | H191: {=IF($A191="",0,SUMPRODUCT((Analysis!$E$3:$X$3=$D$4)*Phasing!$E217:$X217*Analysis!$E$31:$X$31))} -> 0
A192: =IF(Inputs!$A44="","",Inputs!$A44) -> Chargable Proposals 26 | B192: =IF($A192="","",Inputs!$F44) -> Active | C192: {=IF($A192="",0,SUMPRODUCT((Phasing!$E$3:$X$3=$D$4)*Phasing!$E218:$X218))} -> 0 | D192: {=IF($A192="",0,SUMPRODUCT((Phasing!$E$3:$X$3=$D$4)*Phasing!$E633:$X633))} -> 0 | E192: {=IF($A192="",0,SUMPRODUCT((Phasing!$E$3:$X$3=$D$4)*INDEX(Phasing!$E$379:$X$381,$H$4,0)))} -> 0 | F192: {=IF($A192="",0,INDEX(Inputs!$I44:$K44,1,$H$4))} -> 0.6 | G192: =IF($E192<=0,"",COUNTIF($E$154:$E192,">0")) | H192: {=IF($A192="",0,SUMPRODUCT((Analysis!$E$3:$X$3=$D$4)*Phasing!$E218:$X218*Analysis!$E$31:$X$31))} -> 0
A193: =IF(Inputs!$A45="","",Inputs!$A45) | B193: =IF($A193="","",Inputs!$F45) | C193: {=IF($A193="",0,SUMPRODUCT((Phasing!$E$3:$X$3=$D$4)*Phasing!$E219:$X219))} -> 0 | D193: {=IF($A193="",0,SUMPRODUCT((Phasing!$E$3:$X$3=$D$4)*Phasing!$E634:$X634))} -> 0 | E193: {=IF($A193="",0,SUMPRODUCT((Phasing!$E$3:$X$3=$D$4)*INDEX(Phasing!$E$382:$X$384,$H$4,0)))} -> 0 | F193: {=IF($A193="",0,INDEX(Inputs!$I45:$K45,1,$H$4))} -> 0 | G193: =IF($E193<=0,"",COUNTIF($E$154:$E193,">0")) | H193: {=IF($A193="",0,SUMPRODUCT((Analysis!$E$3:$X$3=$D$4)*Phasing!$E219:$X219*Analysis!$E$31:$X$31))} -> 0
A194: =IF(Inputs!$A46="","",Inputs!$A46) -> Proposals 26 | B194: =IF($A194="","",Inputs!$F46) -> Active | C194: {=IF($A194="",0,SUMPRODUCT((Phasing!$E$3:$X$3=$D$4)*Phasing!$E220:$X220))} -> 0 | D194: {=IF($A194="",0,SUMPRODUCT((Phasing!$E$3:$X$3=$D$4)*Phasing!$E635:$X635))} -> 0 | E194: {=IF($A194="",0,SUMPRODUCT((Phasing!$E$3:$X$3=$D$4)*INDEX(Phasing!$E$385:$X$387,$H$4,0)))} -> 0 | F194: {=IF($A194="",0,INDEX(Inputs!$I46:$K46,1,$H$4))} -> 1 | G194: =IF($E194<=0,"",COUNTIF($E$154:$E194,">0")) | H194: {=IF($A194="",0,SUMPRODUCT((Analysis!$E$3:$X$3=$D$4)*Phasing!$E220:$X220*Analysis!$E$31:$X$31))} -> 0
A195: =IF(Inputs!$A47="","",Inputs!$A47) | B195: =IF($A195="","",Inputs!$F47) | C195: {=IF($A195="",0,SUMPRODUCT((Phasing!$E$3:$X$3=$D$4)*Phasing!$E221:$X221))} -> 0 | D195: {=IF($A195="",0,SUMPRODUCT((Phasing!$E$3:$X$3=$D$4)*Phasing!$E636:$X636))} -> 0 | E195: {=IF($A195="",0,SUMPRODUCT((Phasing!$E$3:$X$3=$D$4)*INDEX(Phasing!$E$388:$X$390,$H$4,0)))} -> 0 | F195: {=IF($A195="",0,INDEX(Inputs!$I47:$K47,1,$H$4))} -> 0 | G195: =IF($E195<=0,"",COUNTIF($E$154:$E195,">0")) | H195: {=IF($A195="",0,SUMPRODUCT((Analysis!$E$3:$X$3=$D$4)*Phasing!$E221:$X221*Analysis!$E$31:$X$31))} -> 0
A196: =IF(Inputs!$A48="","",Inputs!$A48) | B196: =IF($A196="","",Inputs!$F48) | C196: {=IF($A196="",0,SUMPRODUCT((Phasing!$E$3:$X$3=$D$4)*Phasing!$E222:$X222))} -> 0 | D196: {=IF($A196="",0,SUMPRODUCT((Phasing!$E$3:$X$3=$D$4)*Phasing!$E637:$X637))} -> 0 | E196: {=IF($A196="",0,SUMPRODUCT((Phasing!$E$3:$X$3=$D$4)*INDEX(Phasing!$E$391:$X$393,$H$4,0)))} -> 0 | F196: {=IF($A196="",0,INDEX(Inputs!$I48:$K48,1,$H$4))} -> 0 | G196: =IF($E196<=0,"",COUNTIF($E$154:$E196,">0")) | H196: {=IF($A196="",0,SUMPRODUCT((Analysis!$E$3:$X$3=$D$4)*Phasing!$E222:$X222*Analysis!$E$31:$X$31))} -> 0
A197: =IF(Inputs!$A49="","",Inputs!$A49) | B197: =IF($A197="","",Inputs!$F49) | C197: {=IF($A197="",0,SUMPRODUCT((Phasing!$E$3:$X$3=$D$4)*Phasing!$E223:$X223))} -> 0 | D197: {=IF($A197="",0,SUMPRODUCT((Phasing!$E$3:$X$3=$D$4)*Phasing!$E638:$X638))} -> 0 | E197: {=IF($A197="",0,SUMPRODUCT((Phasing!$E$3:$X$3=$D$4)*INDEX(Phasing!$E$394:$X$396,$H$4,0)))} -> 0 | F197: {=IF($A197="",0,INDEX(Inputs!$I49:$K49,1,$H$4))} -> 0 | G197: =IF($E197<=0,"",COUNTIF($E$154:$E197,">0")) | H197: {=IF($A197="",0,SUMPRODUCT((Analysis!$E$3:$X$3=$D$4)*Phasing!$E223:$X223*Analysis!$E$31:$X$31))} -> 0
A198: =IF(Inputs!$A50="","",Inputs!$A50) | B198: =IF($A198="","",Inputs!$F50) | C198: {=IF($A198="",0,SUMPRODUCT((Phasing!$E$3:$X$3=$D$4)*Phasing!$E224:$X224))} -> 0 | D198: {=IF($A198="",0,SUMPRODUCT((Phasing!$E$3:$X$3=$D$4)*Phasing!$E639:$X639))} -> 0 | E198: {=IF($A198="",0,SUMPRODUCT((Phasing!$E$3:$X$3=$D$4)*INDEX(Phasing!$E$397:$X$399,$H$4,0)))} -> 0 | F198: {=IF($A198="",0,INDEX(Inputs!$I50:$K50,1,$H$4))} -> 0 | G198: =IF($E198<=0,"",COUNTIF($E$154:$E198,">0")) | H198: {=IF($A198="",0,SUMPRODUCT((Analysis!$E$3:$X$3=$D$4)*Phasing!$E224:$X224*Analysis!$E$31:$X$31))} -> 0
A199: =IF(Inputs!$A51="","",Inputs!$A51) | B199: =IF($A199="","",Inputs!$F51) | C199: {=IF($A199="",0,SUMPRODUCT((Phasing!$E$3:$X$3=$D$4)*Phasing!$E225:$X225))} -> 0 | D199: {=IF($A199="",0,SUMPRODUCT((Phasing!$E$3:$X$3=$D$4)*Phasing!$E640:$X640))} -> 0 | E199: {=IF($A199="",0,SUMPRODUCT((Phasing!$E$3:$X$3=$D$4)*INDEX(Phasing!$E$400:$X$402,$H$4,0)))} -> 0 | F199: {=IF($A199="",0,INDEX(Inputs!$I51:$K51,1,$H$4))} -> 0 | G199: =IF($E199<=0,"",COUNTIF($E$154:$E199,">0")) | H199: {=IF($A199="",0,SUMPRODUCT((Analysis!$E$3:$X$3=$D$4)*Phasing!$E225:$X225*Analysis!$E$31:$X$31))} -> 0
A200: =IF(Inputs!$A52="","",Inputs!$A52) | B200: =IF($A200="","",Inputs!$F52) | C200: {=IF($A200="",0,SUMPRODUCT((Phasing!$E$3:$X$3=$D$4)*Phasing!$E226:$X226))} -> 0 | D200: {=IF($A200="",0,SUMPRODUCT((Phasing!$E$3:$X$3=$D$4)*Phasing!$E641:$X641))} -> 0 | E200: {=IF($A200="",0,SUMPRODUCT((Phasing!$E$3:$X$3=$D$4)*INDEX(Phasing!$E$403:$X$405,$H$4,0)))} -> 0 | F200: {=IF($A200="",0,INDEX(Inputs!$I52:$K52,1,$H$4))} -> 0 | G200: =IF($E200<=0,"",COUNTIF($E$154:$E200,">0")) | H200: {=IF($A200="",0,SUMPRODUCT((Analysis!$E$3:$X$3=$D$4)*Phasing!$E226:$X226*Analysis!$E$31:$X$31))} -> 0
A201: =IF(Inputs!$A53="","",Inputs!$A53) | B201: =IF($A201="","",Inputs!$F53) | C201: {=IF($A201="",0,SUMPRODUCT((Phasing!$E$3:$X$3=$D$4)*Phasing!$E227:$X227))} -> 0 | D201: {=IF($A201="",0,SUMPRODUCT((Phasing!$E$3:$X$3=$D$4)*Phasing!$E642:$X642))} -> 0 | E201: {=IF($A201="",0,SUMPRODUCT((Phasing!$E$3:$X$3=$D$4)*INDEX(Phasing!$E$406:$X$408,$H$4,0)))} -> 0 | F201: {=IF($A201="",0,INDEX(Inputs!$I53:$K53,1,$H$4))} -> 0 | G201: =IF($E201<=0,"",COUNTIF($E$154:$E201,">0")) | H201: {=IF($A201="",0,SUMPRODUCT((Analysis!$E$3:$X$3=$D$4)*Phasing!$E227:$X227*Analysis!$E$31:$X$31))} -> 0
A202: =IF(Inputs!$A54="","",Inputs!$A54) | B202: =IF($A202="","",Inputs!$F54) | C202: {=IF($A202="",0,SUMPRODUCT((Phasing!$E$3:$X$3=$D$4)*Phasing!$E228:$X228))} -> 0 | D202: {=IF($A202="",0,SUMPRODUCT((Phasing!$E$3:$X$3=$D$4)*Phasing!$E643:$X643))} -> 0 | E202: {=IF($A202="",0,SUMPRODUCT((Phasing!$E$3:$X$3=$D$4)*INDEX(Phasing!$E$409:$X$411,$H$4,0)))} -> 0 | F202: {=IF($A202="",0,INDEX(Inputs!$I54:$K54,1,$H$4))} -> 0 | G202: =IF($E202<=0,"",COUNTIF($E$154:$E202,">0")) | H202: {=IF($A202="",0,SUMPRODUCT((Analysis!$E$3:$X$3=$D$4)*Phasing!$E228:$X228*Analysis!$E$31:$X$31))} -> 0
A203: =IF(Inputs!$A55="","",Inputs!$A55) | B203: =IF($A203="","",Inputs!$F55) | C203: {=IF($A203="",0,SUMPRODUCT((Phasing!$E$3:$X$3=$D$4)*Phasing!$E229:$X229))} -> 0 | D203: {=IF($A203="",0,SUMPRODUCT((Phasing!$E$3:$X$3=$D$4)*Phasing!$E644:$X644))} -> 0 | E203: {=IF($A203="",0,SUMPRODUCT((Phasing!$E$3:$X$3=$D$4)*INDEX(Phasing!$E$412:$X$414,$H$4,0)))} -> 0 | F203: {=IF($A203="",0,INDEX(Inputs!$I55:$K55,1,$H$4))} -> 0 | G203: =IF($E203<=0,"",COUNTIF($E$154:$E203,">0")) | H203: {=IF($A203="",0,SUMPRODUCT((Analysis!$E$3:$X$3=$D$4)*Phasing!$E229:$X229*Analysis!$E$31:$X$31))} -> 0
A204: =IF(Inputs!$A56="","",Inputs!$A56) | B204: =IF($A204="","",Inputs!$F56) | C204: {=IF($A204="",0,SUMPRODUCT((Phasing!$E$3:$X$3=$D$4)*Phasing!$E230:$X230))} -> 0 | D204: {=IF($A204="",0,SUMPRODUCT((Phasing!$E$3:$X$3=$D$4)*Phasing!$E645:$X645))} -> 0 | E204: {=IF($A204="",0,SUMPRODUCT((Phasing!$E$3:$X$3=$D$4)*INDEX(Phasing!$E$415:$X$417,$H$4,0)))} -> 0 | F204: {=IF($A204="",0,INDEX(Inputs!$I56:$K56,1,$H$4))} -> 0 | G204: =IF($E204<=0,"",COUNTIF($E$154:$E204,">0")) | H204: {=IF($A204="",0,SUMPRODUCT((Analysis!$E$3:$X$3=$D$4)*Phasing!$E230:$X230*Analysis!$E$31:$X$31))} -> 0
A205: =IF(Inputs!$A57="","",Inputs!$A57) | B205: =IF($A205="","",Inputs!$F57) | C205: {=IF($A205="",0,SUMPRODUCT((Phasing!$E$3:$X$3=$D$4)*Phasing!$E231:$X231))} -> 0 | D205: {=IF($A205="",0,SUMPRODUCT((Phasing!$E$3:$X$3=$D$4)*Phasing!$E646:$X646))} -> 0 | E205: {=IF($A205="",0,SUMPRODUCT((Phasing!$E$3:$X$3=$D$4)*INDEX(Phasing!$E$418:$X$420,$H$4,0)))} -> 0 | F205: {=IF($A205="",0,INDEX(Inputs!$I57:$K57,1,$H$4))} -> 0 | G205: =IF($E205<=0,"",COUNTIF($E$154:$E205,">0")) | H205: {=IF($A205="",0,SUMPRODUCT((Analysis!$E$3:$X$3=$D$4)*Phasing!$E231:$X231*Analysis!$E$31:$X$31))} -> 0
A206: =IF(Inputs!$A58="","",Inputs!$A58) | B206: =IF($A206="","",Inputs!$F58) | C206: {=IF($A206="",0,SUMPRODUCT((Phasing!$E$3:$X$3=$D$4)*Phasing!$E232:$X232))} -> 0 | D206: {=IF($A206="",0,SUMPRODUCT((Phasing!$E$3:$X$3=$D$4)*Phasing!$E647:$X647))} -> 0 | E206: {=IF($A206="",0,SUMPRODUCT((Phasing!$E$3:$X$3=$D$4)*INDEX(Phasing!$E$421:$X$423,$H$4,0)))} -> 0 | F206: {=IF($A206="",0,INDEX(Inputs!$I58:$K58,1,$H$4))} -> 0 | G206: =IF($E206<=0,"",COUNTIF($E$154:$E206,">0")) | H206: {=IF($A206="",0,SUMPRODUCT((Analysis!$E$3:$X$3=$D$4)*Phasing!$E232:$X232*Analysis!$E$31:$X$31))} -> 0
A207: =IF(Inputs!$A59="","",Inputs!$A59) | B207: =IF($A207="","",Inputs!$F59) | C207: {=IF($A207="",0,SUMPRODUCT((Phasing!$E$3:$X$3=$D$4)*Phasing!$E233:$X233))} -> 0 | D207: {=IF($A207="",0,SUMPRODUCT((Phasing!$E$3:$X$3=$D$4)*Phasing!$E648:$X648))} -> 0 | E207: {=IF($A207="",0,SUMPRODUCT((Phasing!$E$3:$X$3=$D$4)*INDEX(Phasing!$E$424:$X$426,$H$4,0)))} -> 0 | F207: {=IF($A207="",0,INDEX(Inputs!$I59:$K59,1,$H$4))} -> 0 | G207: =IF($E207<=0,"",COUNTIF($E$154:$E207,">0")) | H207: {=IF($A207="",0,SUMPRODUCT((Analysis!$E$3:$X$3=$D$4)*Phasing!$E233:$X233*Analysis!$E$31:$X$31))} -> 0
A208: =IF(Inputs!$A60="","",Inputs!$A60) | B208: =IF($A208="","",Inputs!$F60) | C208: {=IF($A208="",0,SUMPRODUCT((Phasing!$E$3:$X$3=$D$4)*Phasing!$E234:$X234))} -> 0 | D208: {=IF($A208="",0,SUMPRODUCT((Phasing!$E$3:$X$3=$D$4)*Phasing!$E649:$X649))} -> 0 | E208: {=IF($A208="",0,SUMPRODUCT((Phasing!$E$3:$X$3=$D$4)*INDEX(Phasing!$E$427:$X$429,$H$4,0)))} -> 0 | F208: {=IF($A208="",0,INDEX(Inputs!$I60:$K60,1,$H$4))} -> 0 | G208: =IF($E208<=0,"",COUNTIF($E$154:$E208,">0")) | H208: {=IF($A208="",0,SUMPRODUCT((Analysis!$E$3:$X$3=$D$4)*Phasing!$E234:$X234*Analysis!$E$31:$X$31))} -> 0
A209: =IF(Inputs!$A61="","",Inputs!$A61) | B209: =IF($A209="","",Inputs!$F61) | C209: {=IF($A209="",0,SUMPRODUCT((Phasing!$E$3:$X$3=$D$4)*Phasing!$E235:$X235))} -> 0 | D209: {=IF($A209="",0,SUMPRODUCT((Phasing!$E$3:$X$3=$D$4)*Phasing!$E650:$X650))} -> 0 | E209: {=IF($A209="",0,SUMPRODUCT((Phasing!$E$3:$X$3=$D$4)*INDEX(Phasing!$E$430:$X$432,$H$4,0)))} -> 0 | F209: {=IF($A209="",0,INDEX(Inputs!$I61:$K61,1,$H$4))} -> 0 | G209: =IF($E209<=0,"",COUNTIF($E$154:$E209,">0")) | H209: {=IF($A209="",0,SUMPRODUCT((Analysis!$E$3:$X$3=$D$4)*Phasing!$E235:$X235*Analysis!$E$31:$X$31))} -> 0
...

Sheet Scorecard
A1: TEAM SCORECARD — WEIGHTED RANKING
A2: ="Viewing: "&Dashboard!$H$5&" | Weights below are yours to set — change them and the ranking updates." -> Viewing: Full year 2026 | Weights below are yours to set — change them and the ranking updates.
A4: SCORING FACTORS — edit the blue cells
A5: Factor | B5: Weight | C5: Direction | D5: Target | E5: How it is scored
A6: Efficiency (CPI, type-weighted) | B6: 0.3 | C6: Higher is better | E6: Best performer scores 100; others in proportion. Earned MM is weighted by project type factor — scoring only.
A7: Utilisation vs capacity | B7: 0.2 | C7: Target band | D7: 1 | E7: 100 when exactly on target; falls away as it deviates either side.
A8: Plan adherence | B8: 0.15 | C8: Target band | D8: 1 | E8: 100 when exactly on plan; over- and under-running both lose points.
A9: Earned MM delivered (type-weighted) | B9: 0.2 | C9: Higher is better | E9: Rewards absolute value delivered, weighted by project type factor — scoring only.
A10: Actual MM contributed | B10: 0.1 | C10: Higher is better | E10: Rewards volume of effort carried.
A11: Projects worked | B11: 0.05 | C11: Higher is better | E11: Rewards breadth across the portfolio.
A12: TOTAL WEIGHT | B12: =SUM(B6:B11) -> 1 | C12: =IF(ROUND($B$12,4)=1,"OK","MUST TOTAL 100%") -> OK
A14: RAW VALUES FOR THE SELECTED PERIOD
A15: Factor | B15: =Inputs!$A$91 -> Ahmed | C15: =Inputs!$A$92 -> Osama | D15: =Inputs!$A$93 -> Kirolos | E15: Best
A16: =$A6 -> Efficiency (CPI, type-weighted) | B16: =IFERROR('Mgmt Review'!B26,0) -> 0.83722042 | C16: =IFERROR('Mgmt Review'!C26,0) -> 0.64016234 | D16: =IFERROR('Mgmt Review'!D26,0) -> 0.73189989 | E16: =MAX(B16:D16) -> 0.83722042
A17: =$A7 -> Utilisation vs capacity | B17: =IFERROR('Mgmt Review'!B18,0) -> 0.71037677 | C17: =IFERROR('Mgmt Review'!C18,0) -> 0.74426815 | D17: =IFERROR('Mgmt Review'!D18,0) -> 0.76876391 | E17: =MAX(B17:D17) -> 0.76876391
A18: =$A8 -> Plan adherence | B18: =IFERROR('Mgmt Review'!B19,0) -> 0.46790235 | C18: =IFERROR('Mgmt Review'!C19,0) -> 0.64062724 | D18: =IFERROR('Mgmt Review'!D19,0) -> 0.55599547 | E18: =MAX(B18:D18) -> 0.64062724
A19: =$A9 -> Earned MM delivered (type-weighted) | B19: =IFERROR('Mgmt Review'!B25,0) -> 4.7902585 | C19: =IFERROR('Mgmt Review'!C25,0) -> 3.8375137 | D19: =IFERROR('Mgmt Review'!D25,0) -> 4.531845 | E19: =MAX(B19:D19) -> 4.7902585
A20: =$A10 -> Actual MM contributed | B20: =IFERROR('Mgmt Review'!B13,0) -> 5.7216216 | C20: =IFERROR('Mgmt Review'!C13,0) -> 5.9945946 | D20: =IFERROR('Mgmt Review'!D13,0) -> 6.1918919 | E20: =MAX(B20:D20) -> 6.1918919
A21: =$A11 -> Projects worked | B21: =IFERROR('Engineer KPIs'!B18,0) -> 6 | C21: =IFERROR('Engineer KPIs'!C18,0) -> 4 | D21: =IFERROR('Engineer KPIs'!D18,0) -> 7 | E21: =MAX(B21:D21) -> 7
A23: NORMALISED SCORES (0 = worst, 100 = best)
A24: Factor | B24: =Inputs!$A$91 -> Ahmed | C24: =Inputs!$A$92 -> Osama | D24: =Inputs!$A$93 -> Kirolos | E24: Weight
A25: =$A6 -> Efficiency (CPI, type-weighted) | B25: =IF($C6="Higher is better",IF($E16=0,0,B16/$E16*100),MAX(0,(1-MIN(1,ABS(B16-$D6)/IF($D6=0,1,$D6)))*100)) -> 100 | C25: =IF($C6="Higher is better",IF($E16=0,0,C16/$E16*100),MAX(0,(1-MIN(1,ABS(C16-$D6)/IF($D6=0,1,$D6)))*100)) -> 76.46282 | D25: =IF($C6="Higher is better",IF($E16=0,0,D16/$E16*100),MAX(0,(1-MIN(1,ABS(D16-$D6)/IF($D6=0,1,$D6)))*100)) -> 87.420215 | E25: =$B6 -> 0.3
A26: =$A7 -> Utilisation vs capacity | B26: =IF($C7="Higher is better",IF($E17=0,0,B17/$E17*100),MAX(0,(1-MIN(1,ABS(B17-$D7)/IF($D7=0,1,$D7)))*100)) -> 71.037677 | C26: =IF($C7="Higher is better",IF($E17=0,0,C17/$E17*100),MAX(0,(1-MIN(1,ABS(C17-$D7)/IF($D7=0,1,$D7)))*100)) -> 74.426815 | D26: =IF($C7="Higher is better",IF($E17=0,0,D17/$E17*100),MAX(0,(1-MIN(1,ABS(D17-$D7)/IF($D7=0,1,$D7)))*100)) -> 76.876391 | E26: =$B7 -> 0.2
A27: =$A8 -> Plan adherence | B27: =IF($C8="Higher is better",IF($E18=0,0,B18/$E18*100),MAX(0,(1-MIN(1,ABS(B18-$D8)/IF($D8=0,1,$D8)))*100)) -> 46.790235 | C27: =IF($C8="Higher is better",IF($E18=0,0,C18/$E18*100),MAX(0,(1-MIN(1,ABS(C18-$D8)/IF($D8=0,1,$D8)))*100)) -> 64.062724 | D27: =IF($C8="Higher is better",IF($E18=0,0,D18/$E18*100),MAX(0,(1-MIN(1,ABS(D18-$D8)/IF($D8=0,1,$D8)))*100)) -> 55.599547 | E27: =$B8 -> 0.15
A28: =$A9 -> Earned MM delivered (type-weighted) | B28: =IF($C9="Higher is better",IF($E19=0,0,B19/$E19*100),MAX(0,(1-MIN(1,ABS(B19-$D9)/IF($D9=0,1,$D9)))*100)) -> 100 | C28: =IF($C9="Higher is better",IF($E19=0,0,C19/$E19*100),MAX(0,(1-MIN(1,ABS(C19-$D9)/IF($D9=0,1,$D9)))*100)) -> 80.110786 | D28: =IF($C9="Higher is better",IF($E19=0,0,D19/$E19*100),MAX(0,(1-MIN(1,ABS(D19-$D9)/IF($D9=0,1,$D9)))*100)) -> 94.605438 | E28: =$B9 -> 0.2
A29: =$A10 -> Actual MM contributed | B29: =IF($C10="Higher is better",IF($E20=0,0,B20/$E20*100),MAX(0,(1-MIN(1,ABS(B20-$D10)/IF($D10=0,1,$D10)))*100)) -> 92.405063 | C29: =IF($C10="Higher is better",IF($E20=0,0,C20/$E20*100),MAX(0,(1-MIN(1,ABS(C20-$D10)/IF($D10=0,1,$D10)))*100)) -> 96.813619 | D29: =IF($C10="Higher is better",IF($E20=0,0,D20/$E20*100),MAX(0,(1-MIN(1,ABS(D20-$D10)/IF($D10=0,1,$D10)))*100)) -> 100 | E29: =$B10 -> 0.1
A30: =$A11 -> Projects worked | B30: =IF($C11="Higher is better",IF($E21=0,0,B21/$E21*100),MAX(0,(1-MIN(1,ABS(B21-$D11)/IF($D11=0,1,$D11)))*100)) -> 85.714286 | C30: =IF($C11="Higher is better",IF($E21=0,0,C21/$E21*100),MAX(0,(1-MIN(1,ABS(C21-$D11)/IF($D11=0,1,$D11)))*100)) -> 57.142857 | D30: =IF($C11="Higher is better",IF($E21=0,0,D21/$E21*100),MAX(0,(1-MIN(1,ABS(D21-$D11)/IF($D11=0,1,$D11)))*100)) -> 100 | E30: =$B11 -> 0.05
A31: WEIGHTED SCORE | B31: =SUMPRODUCT(B25:B30,$E$25:$E$30) -> 84.752291 | C31: =SUMPRODUCT(C25:C30,$E$25:$E$30) -> 75.99428 | D31: =SUMPRODUCT(D25:D30,$E$25:$E$30) -> 83.862362
A32: RANK | B32: =RANK(B31,$B$31:$D$31) -> 1 | C32: =RANK(C31,$B$31:$D$31) -> 3 | D32: =RANK(D31,$B$31:$D$31) -> 2
A34: RANKING
A35: Rank | B35: Engineer | C35: Weighted Score | D35: Strongest factor | E35: Weakest factor | F35: idx
A36: 1 | B36: {=INDEX($B$24:$D$24,$F36)} -> Ahmed | C36: {=INDEX($B$31:$D$31,$F36)} -> 84.752291 | D36: =INDEX($A$25:$A$30,MATCH(MAX(INDEX($B$25:$D$30,0,$F36)),INDEX($B$25:$D$30,0,$F36),0)) -> Efficiency (CPI, type-weighted) | E36: =INDEX($A$25:$A$30,MATCH(MIN(INDEX($B$25:$D$30,0,$F36)),INDEX($B$25:$D$30,0,$F36),0)) -> Plan adherence | F36: =MATCH(1,$B$32:$D$32,0) -> 1
A37: 2 | B37: {=INDEX($B$24:$D$24,$F37)} -> Kirolos | C37: {=INDEX($B$31:$D$31,$F37)} -> 83.862362 | D37: =INDEX($A$25:$A$30,MATCH(MAX(INDEX($B$25:$D$30,0,$F37)),INDEX($B$25:$D$30,0,$F37),0)) -> Actual MM contributed | E37: =INDEX($A$25:$A$30,MATCH(MIN(INDEX($B$25:$D$30,0,$F37)),INDEX($B$25:$D$30,0,$F37),0)) -> Plan adherence | F37: =MATCH(2,$B$32:$D$32,0) -> 3
A38: 3 | B38: {=INDEX($B$24:$D$24,$F38)} -> Osama | C38: {=INDEX($B$31:$D$31,$F38)} -> 75.99428 | D38: =INDEX($A$25:$A$30,MATCH(MAX(INDEX($B$25:$D$30,0,$F38)),INDEX($B$25:$D$30,0,$F38),0)) -> Actual MM contributed | E38: =INDEX($A$25:$A$30,MATCH(MIN(INDEX($B$25:$D$30,0,$F38)),INDEX($B$25:$D$30,0,$F38),0)) -> Projects worked | F38: =MATCH(3,$B$32:$D$32,0) -> 2
A61: Chart data — do not edit
A62: Engineer | B62: Weighted Score
A63: =$B$24 -> Ahmed | B63: =$B$31 -> 84.752291
A64: =$C$24 -> Osama | B64: =$C$31 -> 75.99428
A65: =$D$24 -> Kirolos | B65: =$D$31 -> 83.862362

Sheet Delivery Sequence
A1: DELIVERY SEQUENCE — THE PLAN IN ORDER
A2: Read top to bottom: this is the order to deliver in. Everything above the capacity line is in this year's plan; everything below it needs capacity the team does not have. To change the plan, type expected hours in column K of the Profit Plan sheet — this list re-sorts itself.
A4: THE PLAN AT A GLANCE | D4: TEAM EARNINGS UNDER THIS SEQUENCE
A5: Capacity left (MM) | C5: ='Profit Plan'!$B$11 -> 11.9 | D5: Engineer | E5: Hours in plan | F5: MM in plan | G5: Earned MM (pro-rata on hours) | H5: Hours available to year end | I5: Load | J5: Check
A6: Capacity left (hrs) | C6: ='Profit Plan'!$B$12 -> 2201.5 | D6: Ahmed | E6: ='Profit Plan'!$I$16 -> 775.0375 | F6: =$E6/'Profit Plan'!$B$5 -> 4.1893919 | G6: =IF($E$10=0,0,$E6/$E$10*$C$10) -> 9.4679179 | H6: ='Profit Plan'!$B$12/3 -> 733.83333 | I6: =IF($H6="","",$E6/$H6) -> 1.0561492 | J6: =IF($H6="","-",IF($I6>1,"OVER by "&TEXT($E6-$H6,"#,##0")&" hrs","within capacity")) -> OVER by 41 hrs
A7: Deliverables to do | C7: ='Profit Plan'!$I$5 -> 27 | D7: Osama | E7: ='Profit Plan'!$I$17 -> 729.6 | F7: =$E7/'Profit Plan'!$B$5 -> 3.9437838 | G7: =IF($E$10=0,0,$E7/$E$10*$C$10) -> 8.9128498 | H7: ='Profit Plan'!$B$12/3 -> 733.83333 | I7: =IF($H7="","",$E7/$H7) -> 0.99423121 | J7: =IF($H7="","-",IF($I7>1,"OVER by "&TEXT($E7-$H7,"#,##0")&" hrs","within capacity")) -> within capacity
A8: MM committed | C8: ='Profit Plan'!$I$6 -> 11.813851 | D8: Kirolos | E8: ='Profit Plan'!$I$18 -> 680.925 | F8: =$E8/'Profit Plan'!$B$5 -> 3.6806757 | G8: =IF($E$10=0,0,$E8/$E$10*$C$10) -> 8.3182323 | H8: ='Profit Plan'!$B$12/3 -> 733.83333 | I8: =IF($H8="","",$E8/$H8) -> 0.92790143 | J8: =IF($H8="","-",IF($I8>1,"OVER by "&TEXT($E8-$H8,"#,##0")&" hrs","within capacity")) -> within capacity
A9: Hours committed | C9: ='Profit Plan'!$I$7 -> 2185.5625 | D9: Unassigned | E9: ='Profit Plan'!$I$19 -> 0 | F9: =$E9/'Profit Plan'!$B$5 -> 0 | G9: =IF($E$10=0,0,$E9/$E$10*$C$10) -> 0 | H9: ="" | I9: =IF($H9="","",$E9/$H9) | J9: =IF($H9="","-",IF($I9>1,"OVER by "&TEXT($E9-$H9,"#,##0")&" hrs","within capacity")) -> -
A10: Value to be earned (MM) | C10: ='Profit Plan'!$I$9 -> 26.699 | D10: Total | E10: =SUM($E$6:$E$9) -> 2185.5625 | F10: =SUM($F$6:$F$9) -> 11.813851 | G10: =SUM($G$6:$G$9) -> 26.699
A11: Profit added (MM) | C11: ='Profit Plan'!$I$10 -> 14.885149
A12: Year-end profit (MM) | C12: ='Profit Plan'!$I$11 -> 11.163178
A13: Deferred to next year | C13: ='Profit Plan'!$I$22 -> 5
A14: Value deferred (MM) | C14: ='Profit Plan'!$I$24 -> 17.1125
A15: Implied CPI of this plan | C15: ='Profit Plan'!$E$12 -> 2.2599743 | D15: ='Profit Plan'!$E$13 -> NOT CREDIBLE - implied 2.26x is above the 2.00x ceiling; expected hours are too optimistic
A16: DELIVERY SEQUENCE — RANKED BY VALUE EARNED PER MAN-MONTH
A17: # | B17: Project | C17: Deliverable / Phase | D17: Decision | E17: Hours to finish | F17: MM to finish | G17: Value earned (MM) | H17: Profit added (MM) | I17: Cumulative MM | J17: Capacity used | K17: Start month | L17: Finish month | M17: Ahmed hrs | N17: Osama hrs | O17: Kirolos hrs | P17: Year-end profit after this item (MM) | R17: src row
A18: =IF(ROW()-17>COUNT('Profit Plan'!$P$27:$P$226),"",ROW()-17) -> 1 | B18: {=IF($R18="","",INDEX('Profit Plan'!$A$27:$A$226,$R18))} -> N25185-0100D | C18: {=IF($R18="","",INDEX('Profit Plan'!$B$27:$B$226,$R18))} -> Final Design - Apapa Berth 12 | D18: {=IF($R18="","",INDEX('Profit Plan'!$R$27:$R$226,$R18))} -> DO | E18: {=IF($R18="","",INDEX('Profit Plan'!$M$27:$M$226,$R18))} -> 50 | F18: {=IF($R18="","",INDEX('Profit Plan'!$L$27:$L$226,$R18))} -> 0.27027027 | G18: {=IF($R18="","",INDEX('Profit Plan'!$J$27:$J$226,$R18))} -> 0.936 | H18: =IF($D18="DO",$G18-$F18,"") -> 0.66572973 | I18: {=IF($R18="","",INDEX('Profit Plan'!$Q$27:$Q$226,$R18))} -> 0.27027027 | J18: =IF($R18="","",$I18/'Profit Plan'!$B$11) -> 0.022711787 | K18: =IF($D18<>"DO","-",TEXT(EOMONTH('Profit Plan'!$B$7,INT(($I18-$F18)/'Profit Plan'!$B$8))+1,"mmm yy")) -> Oct 26 | L18: =IF($D18<>"DO","-",TEXT(EOMONTH('Profit Plan'!$B$7,MAX(0,CEILING($I18/'Profit Plan'!$B$8,1)-1))+1,"mmm yy")) -> Oct 26 | M18: {=IF($D18<>"DO","",INDEX('Profit Plan'!$T$27:$T$226,$R18))} -> 12.5 | N18: {=IF($D18<>"DO","",INDEX('Profit Plan'!$U$27:$U$226,$R18))} -> 0 | O18: {=IF($D18<>"DO","",INDEX('Profit Plan'!$V$27:$V$226,$R18))} -> 37.5 | P18: =IF($R18="","",'Profit Plan'!$E$8+SUM($H$18:$H18)) -> -3.0562411 | R18: =IF($A18="","",IFERROR(MATCH($A18,'Profit Plan'!$P$27:$P$226,0),"")) -> 23
A19: =IF(ROW()-17>COUNT('Profit Plan'!$P$27:$P$226),"",ROW()-17) -> 2 | B19: {=IF($R19="","",INDEX('Profit Plan'!$A$27:$A$226,$R19))} -> N25185-0100D | C19: {=IF($R19="","",INDEX('Profit Plan'!$B$27:$B$226,$R19))} -> Final Design - Apapa Berth 13 | D19: {=IF($R19="","",INDEX('Profit Plan'!$R$27:$R$226,$R19))} -> DO | E19: {=IF($R19="","",INDEX('Profit Plan'!$M$27:$M$226,$R19))} -> 50 | F19: {=IF($R19="","",INDEX('Profit Plan'!$L$27:$L$226,$R19))} -> 0.27027027 | G19: {=IF($R19="","",INDEX('Profit Plan'!$J$27:$J$226,$R19))} -> 0.936 | H19: =IF($D19="DO",$G19-$F19,"") -> 0.66572973 | I19: {=IF($R19="","",INDEX('Profit Plan'!$Q$27:$Q$226,$R19))} -> 0.54054054 | J19: =IF($R19="","",$I19/'Profit Plan'!$B$11) -> 0.045423575 | K19: =IF($D19<>"DO","-",TEXT(EOMONTH('Profit Plan'!$B$7,INT(($I19-$F19)/'Profit Plan'!$B$8))+1,"mmm yy")) -> Oct 26 | L19: =IF($D19<>"DO","-",TEXT(EOMONTH('Profit Plan'!$B$7,MAX(0,CEILING($I19/'Profit Plan'!$B$8,1)-1))+1,"mmm yy")) -> Oct 26 | M19: {=IF($D19<>"DO","",INDEX('Profit Plan'!$T$27:$T$226,$R19))} -> 12.5 | N19: {=IF($D19<>"DO","",INDEX('Profit Plan'!$U$27:$U$226,$R19))} -> 0 | O19: {=IF($D19<>"DO","",INDEX('Profit Plan'!$V$27:$V$226,$R19))} -> 37.5 | P19: =IF($R19="","",'Profit Plan'!$E$8+SUM($H$18:$H19)) -> -2.3905113 | R19: =IF($A19="","",IFERROR(MATCH($A19,'Profit Plan'!$P$27:$P$226,0),"")) -> 24
A20: =IF(ROW()-17>COUNT('Profit Plan'!$P$27:$P$226),"",ROW()-17) -> 3 | B20: {=IF($R20="","",INDEX('Profit Plan'!$A$27:$A$226,$R20))} -> N25185-0100D | C20: {=IF($R20="","",INDEX('Profit Plan'!$B$27:$B$226,$R20))} -> Final Design - Apapa Berth 14 | D20: {=IF($R20="","",INDEX('Profit Plan'!$R$27:$R$226,$R20))} -> DO | E20: {=IF($R20="","",INDEX('Profit Plan'!$M$27:$M$226,$R20))} -> 50 | F20: {=IF($R20="","",INDEX('Profit Plan'!$L$27:$L$226,$R20))} -> 0.27027027 | G20: {=IF($R20="","",INDEX('Profit Plan'!$J$27:$J$226,$R20))} -> 0.936 | H20: =IF($D20="DO",$G20-$F20,"") -> 0.66572973 | I20: {=IF($R20="","",INDEX('Profit Plan'!$Q$27:$Q$226,$R20))} -> 0.81081081 | J20: =IF($R20="","",$I20/'Profit Plan'!$B$11) -> 0.068135362 | K20: =IF($D20<>"DO","-",TEXT(EOMONTH('Profit Plan'!$B$7,INT(($I20-$F20)/'Profit Plan'!$B$8))+1,"mmm yy")) -> Oct 26 | L20: =IF($D20<>"DO","-",TEXT(EOMONTH('Profit Plan'!$B$7,MAX(0,CEILING($I20/'Profit Plan'!$B$8,1)-1))+1,"mmm yy")) -> Oct 26 | M20: {=IF($D20<>"DO","",INDEX('Profit Plan'!$T$27:$T$226,$R20))} -> 12.5 | N20: {=IF($D20<>"DO","",INDEX('Profit Plan'!$U$27:$U$226,$R20))} -> 0 | O20: {=IF($D20<>"DO","",INDEX('Profit Plan'!$V$27:$V$226,$R20))} -> 37.5 | P20: =IF($R20="","",'Profit Plan'!$E$8+SUM($H$18:$H20)) -> -1.7247816 | R20: =IF($A20="","",IFERROR(MATCH($A20,'Profit Plan'!$P$27:$P$226,0),"")) -> 25
A21: =IF(ROW()-17>COUNT('Profit Plan'!$P$27:$P$226),"",ROW()-17) -> 4 | B21: {=IF($R21="","",INDEX('Profit Plan'!$A$27:$A$226,$R21))} -> D26058-0100D | C21: {=IF($R21="","",INDEX('Profit Plan'!$B$27:$B$226,$R21))} -> Concept Design | D21: {=IF($R21="","",INDEX('Profit Plan'!$R$27:$R$226,$R21))} -> DO | E21: {=IF($R21="","",INDEX('Profit Plan'!$M$27:$M$226,$R21))} -> 50 | F21: {=IF($R21="","",INDEX('Profit Plan'!$L$27:$L$226,$R21))} -> 0.27027027 | G21: {=IF($R21="","",INDEX('Profit Plan'!$J$27:$J$226,$R21))} -> 0.75 | H21: =IF($D21="DO",$G21-$F21,"") -> 0.47972973 | I21: {=IF($R21="","",INDEX('Profit Plan'!$Q$27:$Q$226,$R21))} -> 1.0810811 | J21: =IF($R21="","",$I21/'Profit Plan'!$B$11) -> 0.09084715 | K21: =IF($D21<>"DO","-",TEXT(EOMONTH('Profit Plan'!$B$7,INT(($I21-$F21)/'Profit Plan'!$B$8))+1,"mmm yy")) -> Oct 26 | L21: =IF($D21<>"DO","-",TEXT(EOMONTH('Profit Plan'!$B$7,MAX(0,CEILING($I21/'Profit Plan'!$B$8,1)-1))+1,"mmm yy")) -> Oct 26 | M21: {=IF($D21<>"DO","",INDEX('Profit Plan'!$T$27:$T$226,$R21))} -> 30 | N21: {=IF($D21<>"DO","",INDEX('Profit Plan'!$U$27:$U$226,$R21))} -> 20 | O21: {=IF($D21<>"DO","",INDEX('Profit Plan'!$V$27:$V$226,$R21))} -> 0 | P21: =IF($R21="","",'Profit Plan'!$E$8+SUM($H$18:$H21)) -> -1.2450519 | R21: =IF($A21="","",IFERROR(MATCH($A21,'Profit Plan'!$P$27:$P$226,0),"")) -> 27
A22: =IF(ROW()-17>COUNT('Profit Plan'!$P$27:$P$226),"",ROW()-17) -> 5 | B22: {=IF($R22="","",INDEX('Profit Plan'!$A$27:$A$226,$R22))} -> N25185-0100D | C22: {=IF($R22="","",INDEX('Profit Plan'!$B$27:$B$226,$R22))} -> Final Design - Tin Can Berth 5 | D22: {=IF($R22="","",INDEX('Profit Plan'!$R$27:$R$226,$R22))} -> DO | E22: {=IF($R22="","",INDEX('Profit Plan'!$M$27:$M$226,$R22))} -> 12 | F22: {=IF($R22="","",INDEX('Profit Plan'!$L$27:$L$226,$R22))} -> 0.064864865 | G22: {=IF($R22="","",INDEX('Profit Plan'!$J$27:$J$226,$R22))} -> 0.156 | H22: =IF($D22="DO",$G22-$F22,"") -> 0.091135135 | I22: {=IF($R22="","",INDEX('Profit Plan'!$Q$27:$Q$226,$R22))} -> 1.1459459 | J22: =IF($R22="","",$I22/'Profit Plan'!$B$11) -> 0.096297979 | K22: =IF($D22<>"DO","-",TEXT(EOMONTH('Profit Plan'!$B$7,INT(($I22-$F22)/'Profit Plan'!$B$8))+1,"mmm yy")) -> Oct 26 | L22: =IF($D22<>"DO","-",TEXT(EOMONTH('Profit Plan'!$B$7,MAX(0,CEILING($I22/'Profit Plan'!$B$8,1)-1))+1,"mmm yy")) -> Oct 26 | M22: {=IF($D22<>"DO","",INDEX('Profit Plan'!$T$27:$T$226,$R22))} -> 5.4 | N22: {=IF($D22<>"DO","",INDEX('Profit Plan'!$U$27:$U$226,$R22))} -> 5.4 | O22: {=IF($D22<>"DO","",INDEX('Profit Plan'!$V$27:$V$226,$R22))} -> 1.2 | P22: =IF($R22="","",'Profit Plan'!$E$8+SUM($H$18:$H22)) -> -1.1539167 | R22: =IF($A22="","",IFERROR(MATCH($A22,'Profit Plan'!$P$27:$P$226,0),"")) -> 9
A23: =IF(ROW()-17>COUNT('Profit Plan'!$P$27:$P$226),"",ROW()-17) -> 6 | B23: {=IF($R23="","",INDEX('Profit Plan'!$A$27:$A$226,$R23))} -> N25185-0100D | C23: {=IF($R23="","",INDEX('Profit Plan'!$B$27:$B$226,$R23))} -> Final Design - Tin Can Berth 6 | D23: {=IF($R23="","",INDEX('Profit Plan'!$R$27:$R$226,$R23))} -> DO | E23: {=IF($R23="","",INDEX('Profit Plan'!$M$27:$M$226,$R23))} -> 12 | F23: {=IF($R23="","",INDEX('Profit Plan'!$L$27:$L$226,$R23))} -> 0.064864865 | G23: {=IF($R23="","",INDEX('Profit Plan'!$J$27:$J$226,$R23))} -> 0.156 | H23: =IF($D23="DO",$G23-$F23,"") -> 0.091135135 | I23: {=IF($R23="","",INDEX('Profit Plan'!$Q$27:$Q$226,$R23))} -> 1.2108108 | J23: =IF($R23="","",$I23/'Profit Plan'!$B$11) -> 0.10174881 | K23: =IF($D23<>"DO","-",TEXT(EOMONTH('Profit Plan'!$B$7,INT(($I23-$F23)/'Profit Plan'!$B$8))+1,"mmm yy")) -> Oct 26 | L23: =IF($D23<>"DO","-",TEXT(EOMONTH('Profit Plan'!$B$7,MAX(0,CEILING($I23/'Profit Plan'!$B$8,1)-1))+1,"mmm yy")) -> Oct 26 | M23: {=IF($D23<>"DO","",INDEX('Profit Plan'!$T$27:$T$226,$R23))} -> 5.4 | N23: {=IF($D23<>"DO","",INDEX('Profit Plan'!$U$27:$U$226,$R23))} -> 5.4 | O23: {=IF($D23<>"DO","",INDEX('Profit Plan'!$V$27:$V$226,$R23))} -> 1.2 | P23: =IF($R23="","",'Profit Plan'!$E$8+SUM($H$18:$H23)) -> -1.0627816 | R23: =IF($A23="","",IFERROR(MATCH($A23,'Profit Plan'!$P$27:$P$226,0),"")) -> 10
